Workbook

Sheet Cover
B3: KSESTOR
B4: MONTHLY SALES REPORT
B5: Interactive performance monitoring · Amazon US/CA/UK · TikTok Shop · Shopify & Faire · Walmart
B8: WORKBOOK MAP
B10: # | C10: Sheet | D10: What you'll find
B11: 01 | C11: Cover | D11: This page
B12: 02 | C12: Executive Summary | D12: Month/Year selectors · full annual view below
B13: 03 | C13: Amazon Dashboard | D13: Country dropdown (US/CA/UK) · KPIs · monthly trend with year selector · expandable breakdown
B14: 04 | C14: TikTok Dashboard | D14: KPIs · monthly trend with year selector · expandable breakdown
B15: 05 | C15: Shopify Dashboard | D15: KPIs · monthly trend with year selector · expandable breakdown
B16: 06 | C16: Walmart Dashboard | D16: KPIs · monthly trend with year selector · expandable breakdown
B17: 07 | C17: Monthly Data | D17: Month-over-month totals for every marketplace
B18: 08 | C18: Sales Data | D18: Raw · colored headers by marketplace · soft-blue entry cells
B19: 09 | C19: Main Expenses | D19: Raw expense data · main category
B20: 10 | C20: Sub Expenses | D20: Raw expense data · sub category
B21: 11 | C21: Setup | D21: Dropdown lists · do not edit
B24: How to use
B25: • Use dropdowns at top of each dashboard — Month, Year, Country.
B26: • Every KPI is driven by SUMIFS formulas. Change selectors — numbers refresh automatically.
B27: • The Monthly Trend section has its own Year dropdown.
B28: • Enter new data in soft-blue cells on Sales Data and Expenses sheets.
B29: • In Expense Breakdown, click the + icon on the left margin of each main category row to expand sub-categories.
B30: • Amazon dashboard supports US, CA, and UK — switch via the Marketplace dropdown.
B32: Generated April 24, 2026 · Prepared for Kseniia · KSESTOR

Sheet Executive Summary
B2: EXECUTIVE SUMMARY
B3: Cross-marketplace monitoring · pick month & year for snapshot · full annual view below.
B6: MONTH | C6: YEAR
B7: Mar | C7: 2026
B10: MONTHLY SNAPSHOT · ALL MARKETPLACES
B11: Marketplace | C11: Sales (USD) | D11: Expenses (USD) | E11: Net Profit | F11: Margin % | G11: Sales %
B12: Amazon US | C12: =SUMIFS('Sales Data'!$E$6:$E$10000,'Sales Data'!$B$6:$B$10000,"Amazon US",'Sales Data'!$BC$6:$BC$10000,$B$7,'Sales Data'!$BD$6:$BD$10000,$C$7) | D12: =SUMIFS('Main Expenses'!$E$6:$E$10000,'Main Expenses'!$B$6:$B$10000,"Amazon US",'Main Expenses'!$K$6:$K$10000,$B$7,'Main Expenses'!$L$6:$L$10000,$C$7) | E12: =C12+D12 | F12: =IFERROR(E12/C12,0) | G12: =IFERROR(C12/SUMIFS('Sales Data'!$E$6:$E$10000,'Sales Data'!$BC$6:$BC$10000,$B$7,'Sales Data'!$BD$6:$BD$10000,$C$7),0)
B13: Amazon CA | C13: =SUMIFS('Sales Data'!$E$6:$E$10000,'Sales Data'!$B$6:$B$10000,"Amazon CA",'Sales Data'!$BC$6:$BC$10000,$B$7,'Sales Data'!$BD$6:$BD$10000,$C$7) | D13: =SUMIFS('Main Expenses'!$E$6:$E$10000,'Main Expenses'!$B$6:$B$10000,"Amazon CA",'Main Expenses'!$K$6:$K$10000,$B$7,'Main Expenses'!$L$6:$L$10000,$C$7) | E13: =C13+D13 | F13: =IFERROR(E13/C13,0) | G13: =IFERROR(C13/SUMIFS('Sales Data'!$E$6:$E$10000,'Sales Data'!$BC$6:$BC$10000,$B$7,'Sales Data'!$BD$6:$BD$10000,$C$7),0)
B14: Amazon UK | C14: =SUMIFS('Sales Data'!$E$6:$E$10000,'Sales Data'!$B$6:$B$10000,"Amazon UK",'Sales Data'!$BC$6:$BC$10000,$B$7,'Sales Data'!$BD$6:$BD$10000,$C$7) | D14: =SUMIFS('Main Expenses'!$E$6:$E$10000,'Main Expenses'!$B$6:$B$10000,"Amazon UK",'Main Expenses'!$K$6:$K$10000,$B$7,'Main Expenses'!$L$6:$L$10000,$C$7) | E14: =C14+D14 | F14: =IFERROR(E14/C14,0) | G14: =IFERROR(C14/SUMIFS('Sales Data'!$E$6:$E$10000,'Sales Data'!$BC$6:$BC$10000,$B$7,'Sales Data'!$BD$6:$BD$10000,$C$7),0)
B15: TikTok Shop | C15: =SUMIFS('Sales Data'!$E$6:$E$10000,'Sales Data'!$B$6:$B$10000,"Tiktok",'Sales Data'!$BC$6:$BC$10000,$B$7,'Sales Data'!$BD$6:$BD$10000,$C$7) | D15: =SUMIFS('Main Expenses'!$E$6:$E$10000,'Main Expenses'!$B$6:$B$10000,"Tiktok",'Main Expenses'!$K$6:$K$10000,$B$7,'Main Expenses'!$L$6:$L$10000,$C$7) | E15: =C15+D15 | F15: =IFERROR(E15/C15,0) | G15: =IFERROR(C15/SUMIFS('Sales Data'!$E$6:$E$10000,'Sales Data'!$BC$6:$BC$10000,$B$7,'Sales Data'!$BD$6:$BD$10000,$C$7),0)
B16: Shopify & Faire | C16: =SUMIFS('Sales Data'!$E$6:$E$10000,'Sales Data'!$B$6:$B$10000,"Shopify",'Sales Data'!$BC$6:$BC$10000,$B$7,'Sales Data'!$BD$6:$BD$10000,$C$7) | D16: =SUMIFS('Main Expenses'!$E$6:$E$10000,'Main Expenses'!$B$6:$B$10000,"Shopify",'Main Expenses'!$K$6:$K$10000,$B$7,'Main Expenses'!$L$6:$L$10000,$C$7) | E16: =C16+D16 | F16: =IFERROR(E16/C16,0) | G16: =IFERROR(C16/SUMIFS('Sales Data'!$E$6:$E$10000,'Sales Data'!$BC$6:$BC$10000,$B$7,'Sales Data'!$BD$6:$BD$10000,$C$7),0)
B17: Walmart | C17: =SUMIFS('Sales Data'!$E$6:$E$10000,'Sales Data'!$B$6:$B$10000,"Walmart",'Sales Data'!$BC$6:$BC$10000,$B$7,'Sales Data'!$BD$6:$BD$10000,$C$7) | D17: =SUMIFS('Main Expenses'!$E$6:$E$10000,'Main Expenses'!$B$6:$B$10000,"Walmart",'Main Expenses'!$K$6:$K$10000,$B$7,'Main Expenses'!$L$6:$L$10000,$C$7) | E17: =C17+D17 | F17: =IFERROR(E17/C17,0) | G17: =IFERROR(C17/SUMIFS('Sales Data'!$E$6:$E$10000,'Sales Data'!$BC$6:$BC$10000,$B$7,'Sales Data'!$BD$6:$BD$10000,$C$7),0)
B18: TOTAL | C18: =SUM(C12:C17) | D18: =SUM(D12:D17) | E18: =SUM(E12:E17) | F18: =IFERROR(E18/C18,0) | G18: 1
B21: FULL YEAR VIEW · MONTHLY TRENDS | N21: Year: | O21: 2026
B23: MARKETPLACE | C23: METRIC | D23: Jan | E23: Feb | F23: Mar | G23: Apr | H23: May | I23: Jun | J23: Jul | K23: Aug | L23: Sep | M23: Oct | N23: Nov | O23: Dec | P23: YEAR TOTAL
B24: Amazon US | C24: Sales | D24: =SUMIFS('Sales Data'!$E$6:$E$10000,'Sales Data'!$B$6:$B$10000,"Amazon US",'Sales Data'!$BC$6:$BC$10000,"Jan",'Sales Data'!$BD$6:$BD$10000,$O$21) | E24: =SUMIFS('Sales Data'!$E$6:$E$10000,'Sales Data'!$B$6:$B$10000,"Amazon US",'Sales Data'!$BC$6:$BC$10000,"Feb",'Sales Data'!$BD$6:$BD$10000,$O$21) | F24: =SUMIFS('Sales Data'!$E$6:$E$10000,'Sales Data'!$B$6:$B$10000,"Amazon US",'Sales Data'!$BC$6:$BC$10000,"Mar",'Sales Data'!$BD$6:$BD$10000,$O$21) | G24: =SUMIFS('Sales Data'!$E$6:$E$10000,'Sales Data'!$B$6:$B$10000,"Amazon US",'Sales Data'!$BC$6:$BC$10000,"Apr",'Sales Data'!$BD$6:$BD$10000,$O$21) | H24: =SUMIFS('Sales Data'!$E$6:$E$10000,'Sales Data'!$B$6:$B$10000,"Amazon US",'Sales Data'!$BC$6:$BC$10000,"May",'Sales Data'!$BD$6:$BD$10000,$O$21) | I24: =SUMIFS('Sales Data'!$E$6:$E$10000,'Sales Data'!$B$6:$B$10000,"Amazon US",'Sales Data'!$BC$6:$BC$10000,"Jun",'Sales Data'!$BD$6:$BD$10000,$O$21) | J24: =SUMIFS('Sales Data'!$E$6:$E$10000,'Sales Data'!$B$6:$B$10000,"Amazon US",'Sales Data'!$BC$6:$BC$10000,"Jul",'Sales Data'!$BD$6:$BD$10000,$O$21) | K24: =SUMIFS('Sales Data'!$E$6:$E$10000,'Sales Data'!$B$6:$B$10000,"Amazon US",'Sales Data'!$BC$6:$BC$10000,"Aug",'Sales Data'!$BD$6:$BD$10000,$O$21) | L24: =SUMIFS('Sales Data'!$E$6:$E$10000,'Sales Data'!$B$6:$B$10000,"Amazon US",'Sales Data'!$BC$6:$BC$10000,"Sep",'Sales Data'!$BD$6:$BD$10000,$O$21) | M24: =SUMIFS('Sales Data'!$E$6:$E$10000,'Sales Data'!$B$6:$B$10000,"Amazon US",'Sales Data'!$BC$6:$BC$10000,"Oct",'Sales Data'!$BD$6:$BD$10000,$O$21) | N24: =SUMIFS('Sales Data'!$E$6:$E$10000,'Sales Data'!$B$6:$B$10000,"Amazon US",'Sales Data'!$BC$6:$BC$10000,"Nov",'Sales Data'!$BD$6:$BD$10000,$O$21) | O24: =SUMIFS('Sales Data'!$E$6:$E$10000,'Sales Data'!$B$6:$B$10000,"Amazon US",'Sales Data'!$BC$6:$BC$10000,"Dec",'Sales Data'!$BD$6:$BD$10000,$O$21) | P24: =SUM(D24:O24)
C25: Expenses | D25: =SUMIFS('Main Expenses'!$E$6:$E$10000,'Main Expenses'!$B$6:$B$10000,"Amazon US",'Main Expenses'!$K$6:$K$10000,"Jan",'Main Expenses'!$L$6:$L$10000,$O$21) | E25: =SUMIFS('Main Expenses'!$E$6:$E$10000,'Main Expenses'!$B$6:$B$10000,"Amazon US",'Main Expenses'!$K$6:$K$10000,"Feb",'Main Expenses'!$L$6:$L$10000,$O$21) | F25: =SUMIFS('Main Expenses'!$E$6:$E$10000,'Main Expenses'!$B$6:$B$10000,"Amazon US",'Main Expenses'!$K$6:$K$10000,"Mar",'Main Expenses'!$L$6:$L$10000,$O$21) | G25: =SUMIFS('Main Expenses'!$E$6:$E$10000,'Main Expenses'!$B$6:$B$10000,"Amazon US",'Main Expenses'!$K$6:$K$10000,"Apr",'Main Expenses'!$L$6:$L$10000,$O$21) | H25: =SUMIFS('Main Expenses'!$E$6:$E$10000,'Main Expenses'!$B$6:$B$10000,"Amazon US",'Main Expenses'!$K$6:$K$10000,"May",'Main Expenses'!$L$6:$L$10000,$O$21) | I25: =SUMIFS('Main Expenses'!$E$6:$E$10000,'Main Expenses'!$B$6:$B$10000,"Amazon US",'Main Expenses'!$K$6:$K$10000,"Jun",'Main Expenses'!$L$6:$L$10000,$O$21) | J25: =SUMIFS('Main Expenses'!$E$6:$E$10000,'Main Expenses'!$B$6:$B$10000,"Amazon US",'Main Expenses'!$K$6:$K$10000,"Jul",'Main Expenses'!$L$6:$L$10000,$O$21) | K25: =SUMIFS('Main Expenses'!$E$6:$E$10000,'Main Expenses'!$B$6:$B$10000,"Amazon US",'Main Expenses'!$K$6:$K$10000,"Aug",'Main Expenses'!$L$6:$L$10000,$O$21) | L25: =SUMIFS('Main Expenses'!$E$6:$E$10000,'Main Expenses'!$B$6:$B$10000,"Amazon US",'Main Expenses'!$K$6:$K$10000,"Sep",'Main Expenses'!$L$6:$L$10000,$O$21) | M25: =SUMIFS('Main Expenses'!$E$6:$E$10000,'Main Expenses'!$B$6:$B$10000,"Amazon US",'Main Expenses'!$K$6:$K$10000,"Oct",'Main Expenses'!$L$6:$L$10000,$O$21) | N25: =SUMIFS('Main Expenses'!$E$6:$E$10000,'Main Expenses'!$B$6:$B$10000,"Amazon US",'Main Expenses'!$K$6:$K$10000,"Nov",'Main Expenses'!$L$6:$L$10000,$O$21) | O25: =SUMIFS('Main Expenses'!$E$6:$E$10000,'Main Expenses'!$B$6:$B$10000,"Amazon US",'Main Expenses'!$K$6:$K$10000,"Dec",'Main Expenses'!$L$6:$L$10000,$O$21) | P25: =SUM(D25:O25)
C26: Net Profit | D26: =D24+D25 | E26: =E24+E25 | F26: =F24+F25 | G26: =G24+G25 | H26: =H24+H25 | I26: =I24+I25 | J26: =J24+J25 | K26: =K24+K25 | ... O26: =O24+O25 | P26: =SUM(D26:O26)
C27: Margin % | D27: =IFERROR(D26/D24,0) | E27: =IFERROR(E26/E24,0) | F27: =IFERROR(F26/F24,0) | G27: =IFERROR(G26/G24,0) | H27: =IFERROR(H26/H24,0) | I27: =IFERROR(I26/I24,0) | J27: =IFERROR(J26/J24,0) | K27: =IFERROR(K26/K24,0) | ... P27: =IFERROR(P26/P24,0)
B28: Amazon CA | C28: Sales | D28: =SUMIFS('Sales Data'!$E$6:$E$10000,'Sales Data'!$B$6:$B$10000,"Amazon CA",'Sales Data'!$BC$6:$BC$10000,"Jan",'Sales Data'!$BD$6:$BD$10000,$O$21) | E28: =SUMIFS('Sales Data'!$E$6:$E$10000,'Sales Data'!$B$6:$B$10000,"Amazon CA",'Sales Data'!$BC$6:$BC$10000,"Feb",'Sales Data'!$BD$6:$BD$10000,$O$21) | F28: =SUMIFS('Sales Data'!$E$6:$E$10000,'Sales Data'!$B$6:$B$10000,"Amazon CA",'Sales Data'!$BC$6:$BC$10000,"Mar",'Sales Data'!$BD$6:$BD$10000,$O$21) | G28: =SUMIFS('Sales Data'!$E$6:$E$10000,'Sales Data'!$B$6:$B$10000,"Amazon CA",'Sales Data'!$BC$6:$BC$10000,"Apr",'Sales Data'!$BD$6:$BD$10000,$O$21) | H28: =SUMIFS('Sales Data'!$E$6:$E$10000,'Sales Data'!$B$6:$B$10000,"Amazon CA",'Sales Data'!$BC$6:$BC$10000,"May",'Sales Data'!$BD$6:$BD$10000,$O$21) | I28: =SUMIFS('Sales Data'!$E$6:$E$10000,'Sales Data'!$B$6:$B$10000,"Amazon CA",'Sales Data'!$BC$6:$BC$10000,"Jun",'Sales Data'!$BD$6:$BD$10000,$O$21) | J28: =SUMIFS('Sales Data'!$E$6:$E$10000,'Sales Data'!$B$6:$B$10000,"Amazon CA",'Sales Data'!$BC$6:$BC$10000,"Jul",'Sales Data'!$BD$6:$BD$10000,$O$21) | K28: =SUMIFS('Sales Data'!$E$6:$E$10000,'Sales Data'!$B$6:$B$10000,"Amazon CA",'Sales Data'!$BC$6:$BC$10000,"Aug",'Sales Data'!$BD$6:$BD$10000,$O$21) | L28: =SUMIFS('Sales Data'!$E$6:$E$10000,'Sales Data'!$B$6:$B$10000,"Amazon CA",'Sales Data'!$BC$6:$BC$10000,"Sep",'Sales Data'!$BD$6:$BD$10000,$O$21) | M28: =SUMIFS('Sales Data'!$E$6:$E$10000,'Sales Data'!$B$6:$B$10000,"Amazon CA",'Sales Data'!$BC$6:$BC$10000,"Oct",'Sales Data'!$BD$6:$BD$10000,$O$21) | N28: =SUMIFS('Sales Data'!$E$6:$E$10000,'Sales Data'!$B$6:$B$10000,"Amazon CA",'Sales Data'!$BC$6:$BC$10000,"Nov",'Sales Data'!$BD$6:$BD$10000,$O$21) | O28: =SUMIFS('Sales Data'!$E$6:$E$10000,'Sales Data'!$B$6:$B$10000,"Amazon CA",'Sales Data'!$BC$6:$BC$10000,"Dec",'Sales Data'!$BD$6:$BD$10000,$O$21) | P28: =SUM(D28:O28)
C29: Expenses | D29: =SUMIFS('Main Expenses'!$E$6:$E$10000,'Main Expenses'!$B$6:$B$10000,"Amazon CA",'Main Expenses'!$K$6:$K$10000,"Jan",'Main Expenses'!$L$6:$L$10000,$O$21) | E29: =SUMIFS('Main Expenses'!$E$6:$E$10000,'Main Expenses'!$B$6:$B$10000,"Amazon CA",'Main Expenses'!$K$6:$K$10000,"Feb",'Main Expenses'!$L$6:$L$10000,$O$21) | F29: =SUMIFS('Main Expenses'!$E$6:$E$10000,'Main Expenses'!$B$6:$B$10000,"Amazon CA",'Main Expenses'!$K$6:$K$10000,"Mar",'Main Expenses'!$L$6:$L$10000,$O$21) | G29: =SUMIFS('Main Expenses'!$E$6:$E$10000,'Main Expenses'!$B$6:$B$10000,"Amazon CA",'Main Expenses'!$K$6:$K$10000,"Apr",'Main Expenses'!$L$6:$L$10000,$O$21) | H29: =SUMIFS('Main Expenses'!$E$6:$E$10000,'Main Expenses'!$B$6:$B$10000,"Amazon CA",'Main Expenses'!$K$6:$K$10000,"May",'Main Expenses'!$L$6:$L$10000,$O$21) | I29: =SUMIFS('Main Expenses'!$E$6:$E$10000,'Main Expenses'!$B$6:$B$10000,"Amazon CA",'Main Expenses'!$K$6:$K$10000,"Jun",'Main Expenses'!$L$6:$L$10000,$O$21) | J29: =SUMIFS('Main Expenses'!$E$6:$E$10000,'Main Expenses'!$B$6:$B$10000,"Amazon CA",'Main Expenses'!$K$6:$K$10000,"Jul",'Main Expenses'!$L$6:$L$10000,$O$21) | K29: =SUMIFS('Main Expenses'!$E$6:$E$10000,'Main Expenses'!$B$6:$B$10000,"Amazon CA",'Main Expenses'!$K$6:$K$10000,"Aug",'Main Expenses'!$L$6:$L$10000,$O$21) | L29: =SUMIFS('Main Expenses'!$E$6:$E$10000,'Main Expenses'!$B$6:$B$10000,"Amazon CA",'Main Expenses'!$K$6:$K$10000,"Sep",'Main Expenses'!$L$6:$L$10000,$O$21) | M29: =SUMIFS('Main Expenses'!$E$6:$E$10000,'Main Expenses'!$B$6:$B$10000,"Amazon CA",'Main Expenses'!$K$6:$K$10000,"Oct",'Main Expenses'!$L$6:$L$10000,$O$21) | N29: =SUMIFS('Main Expenses'!$E$6:$E$10000,'Main Expenses'!$B$6:$B$10000,"Amazon CA",'Main Expenses'!$K$6:$K$10000,"Nov",'Main Expenses'!$L$6:$L$10000,$O$21) | O29: =SUMIFS('Main Expenses'!$E$6:$E$10000,'Main Expenses'!$B$6:$B$10000,"Amazon CA",'Main Expenses'!$K$6:$K$10000,"Dec",'Main Expenses'!$L$6:$L$10000,$O$21) | P29: =SUM(D29:O29)
C30: Net Profit | D30: =D28+D29 | E30: =E28+E29 | F30: =F28+F29 | G30: =G28+G29 | H30: =H28+H29 | I30: =I28+I29 | J30: =J28+J29 | K30: =K28+K29 | ... O30: =O28+O29 | P30: =SUM(D30:O30)
C31: Margin % | D31: =IFERROR(D30/D28,0) | E31: =IFERROR(E30/E28,0) | F31: =IFERROR(F30/F28,0) | G31: =IFERROR(G30/G28,0) | H31: =IFERROR(H30/H28,0) | I31: =IFERROR(I30/I28,0) | J31: =IFERROR(J30/J28,0) | K31: =IFERROR(K30/K28,0) | ... P31: =IFERROR(P30/P28,0)
B32: Amazon UK | C32: Sales | D32: =SUMIFS('Sales Data'!$E$6:$E$10000,'Sales Data'!$B$6:$B$10000,"Amazon UK",'Sales Data'!$BC$6:$BC$10000,"Jan",'Sales Data'!$BD$6:$BD$10000,$O$21) | E32: =SUMIFS('Sales Data'!$E$6:$E$10000,'Sales Data'!$B$6:$B$10000,"Amazon UK",'Sales Data'!$BC$6:$BC$10000,"Feb",'Sales Data'!$BD$6:$BD$10000,$O$21) | F32: =SUMIFS('Sales Data'!$E$6:$E$10000,'Sales Data'!$B$6:$B$10000,"Amazon UK",'Sales Data'!$BC$6:$BC$10000,"Mar",'Sales Data'!$BD$6:$BD$10000,$O$21) | G32: =SUMIFS('Sales Data'!$E$6:$E$10000,'Sales Data'!$B$6:$B$10000,"Amazon UK",'Sales Data'!$BC$6:$BC$10000,"Apr",'Sales Data'!$BD$6:$BD$10000,$O$21) | H32: =SUMIFS('Sales Data'!$E$6:$E$10000,'Sales Data'!$B$6:$B$10000,"Amazon UK",'Sales Data'!$BC$6:$BC$10000,"May",'Sales Data'!$BD$6:$BD$10000,$O$21) | I32: =SUMIFS('Sales Data'!$E$6:$E$10000,'Sales Data'!$B$6:$B$10000,"Amazon UK",'Sales Data'!$BC$6:$BC$10000,"Jun",'Sales Data'!$BD$6:$BD$10000,$O$21) | J32: =SUMIFS('Sales Data'!$E$6:$E$10000,'Sales Data'!$B$6:$B$10000,"Amazon UK",'Sales Data'!$BC$6:$BC$10000,"Jul",'Sales Data'!$BD$6:$BD$10000,$O$21) | K32: =SUMIFS('Sales Data'!$E$6:$E$10000,'Sales Data'!$B$6:$B$10000,"Amazon UK",'Sales Data'!$BC$6:$BC$10000,"Aug",'Sales Data'!$BD$6:$BD$10000,$O$21) | L32: =SUMIFS('Sales Data'!$E$6:$E$10000,'Sales Data'!$B$6:$B$10000,"Amazon UK",'Sales Data'!$BC$6:$BC$10000,"Sep",'Sales Data'!$BD$6:$BD$10000,$O$21) | M32: =SUMIFS('Sales Data'!$E$6:$E$10000,'Sales Data'!$B$6:$B$10000,"Amazon UK",'Sales Data'!$BC$6:$BC$10000,"Oct",'Sales Data'!$BD$6:$BD$10000,$O$21) | N32: =SUMIFS('Sales Data'!$E$6:$E$10000,'Sales Data'!$B$6:$B$10000,"Amazon UK",'Sales Data'!$BC$6:$BC$10000,"Nov",'Sales Data'!$BD$6:$BD$10000,$O$21) | O32: =SUMIFS('Sales Data'!$E$6:$E$10000,'Sales Data'!$B$6:$B$10000,"Amazon UK",'Sales Data'!$BC$6:$BC$10000,"Dec",'Sales Data'!$BD$6:$BD$10000,$O$21) | P32: =SUM(D32:O32)
C33: Expenses | D33: =SUMIFS('Main Expenses'!$E$6:$E$10000,'Main Expenses'!$B$6:$B$10000,"Amazon UK",'Main Expenses'!$K$6:$K$10000,"Jan",'Main Expenses'!$L$6:$L$10000,$O$21) | E33: =SUMIFS('Main Expenses'!$E$6:$E$10000,'Main Expenses'!$B$6:$B$10000,"Amazon UK",'Main Expenses'!$K$6:$K$10000,"Feb",'Main Expenses'!$L$6:$L$10000,$O$21) | F33: =SUMIFS('Main Expenses'!$E$6:$E$10000,'Main Expenses'!$B$6:$B$10000,"Amazon UK",'Main Expenses'!$K$6:$K$10000,"Mar",'Main Expenses'!$L$6:$L$10000,$O$21) | G33: =SUMIFS('Main Expenses'!$E$6:$E$10000,'Main Expenses'!$B$6:$B$10000,"Amazon UK",'Main Expenses'!$K$6:$K$10000,"Apr",'Main Expenses'!$L$6:$L$10000,$O$21) | H33: =SUMIFS('Main Expenses'!$E$6:$E$10000,'Main Expenses'!$B$6:$B$10000,"Amazon UK",'Main Expenses'!$K$6:$K$10000,"May",'Main Expenses'!$L$6:$L$10000,$O$21) | I33: =SUMIFS('Main Expenses'!$E$6:$E$10000,'Main Expenses'!$B$6:$B$10000,"Amazon UK",'Main Expenses'!$K$6:$K$10000,"Jun",'Main Expenses'!$L$6:$L$10000,$O$21) | J33: =SUMIFS('Main Expenses'!$E$6:$E$10000,'Main Expenses'!$B$6:$B$10000,"Amazon UK",'Main Expenses'!$K$6:$K$10000,"Jul",'Main Expenses'!$L$6:$L$10000,$O$21) | K33: =SUMIFS('Main Expenses'!$E$6:$E$10000,'Main Expenses'!$B$6:$B$10000,"Amazon UK",'Main Expenses'!$K$6:$K$10000,"Aug",'Main Expenses'!$L$6:$L$10000,$O$21) | L33: =SUMIFS('Main Expenses'!$E$6:$E$10000,'Main Expenses'!$B$6:$B$10000,"Amazon UK",'Main Expenses'!$K$6:$K$10000,"Sep",'Main Expenses'!$L$6:$L$10000,$O$21) | M33: =SUMIFS('Main Expenses'!$E$6:$E$10000,'Main Expenses'!$B$6:$B$10000,"Amazon UK",'Main Expenses'!$K$6:$K$10000,"Oct",'Main Expenses'!$L$6:$L$10000,$O$21) | N33: =SUMIFS('Main Expenses'!$E$6:$E$10000,'Main Expenses'!$B$6:$B$10000,"Amazon UK",'Main Expenses'!$K$6:$K$10000,"Nov",'Main Expenses'!$L$6:$L$10000,$O$21) | O33: =SUMIFS('Main Expenses'!$E$6:$E$10000,'Main Expenses'!$B$6:$B$10000,"Amazon UK",'Main Expenses'!$K$6:$K$10000,"Dec",'Main Expenses'!$L$6:$L$10000,$O$21) | P33: =SUM(D33:O33)
C34: Net Profit | D34: =D32+D33 | E34: =E32+E33 | F34: =F32+F33 | G34: =G32+G33 | H34: =H32+H33 | I34: =I32+I33 | J34: =J32+J33 | K34: =K32+K33 | ... O34: =O32+O33 | P34: =SUM(D34:O34)
C35: Margin % | D35: =IFERROR(D34/D32,0) | E35: =IFERROR(E34/E32,0) | F35: =IFERROR(F34/F32,0) | G35: =IFERROR(G34/G32,0) | H35: =IFERROR(H34/H32,0) | I35: =IFERROR(I34/I32,0) | J35: =IFERROR(J34/J32,0) | K35: =IFERROR(K34/K32,0) | ... P35: =IFERROR(P34/P32,0)
B36: TikTok Shop | C36: Sales | D36: =SUMIFS('Sales Data'!$E$6:$E$10000,'Sales Data'!$B$6:$B$10000,"Tiktok",'Sales Data'!$BC$6:$BC$10000,"Jan",'Sales Data'!$BD$6:$BD$10000,$O$21) | E36: =SUMIFS('Sales Data'!$E$6:$E$10000,'Sales Data'!$B$6:$B$10000,"Tiktok",'Sales Data'!$BC$6:$BC$10000,"Feb",'Sales Data'!$BD$6:$BD$10000,$O$21) | F36: =SUMIFS('Sales Data'!$E$6:$E$10000,'Sales Data'!$B$6:$B$10000,"Tiktok",'Sales Data'!$BC$6:$BC$10000,"Mar",'Sales Data'!$BD$6:$BD$10000,$O$21) | G36: =SUMIFS('Sales Data'!$E$6:$E$10000,'Sales Data'!$B$6:$B$10000,"Tiktok",'Sales Data'!$BC$6:$BC$10000,"Apr",'Sales Data'!$BD$6:$BD$10000,$O$21) | H36: =SUMIFS('Sales Data'!$E$6:$E$10000,'Sales Data'!$B$6:$B$10000,"Tiktok",'Sales Data'!$BC$6:$BC$10000,"May",'Sales Data'!$BD$6:$BD$10000,$O$21) | I36: =SUMIFS('Sales Data'!$E$6:$E$10000,'Sales Data'!$B$6:$B$10000,"Tiktok",'Sales Data'!$BC$6:$BC$10000,"Jun",'Sales Data'!$BD$6:$BD$10000,$O$21) | J36: =SUMIFS('Sales Data'!$E$6:$E$10000,'Sales Data'!$B$6:$B$10000,"Tiktok",'Sales Data'!$BC$6:$BC$10000,"Jul",'Sales Data'!$BD$6:$BD$10000,$O$21) | K36: =SUMIFS('Sales Data'!$E$6:$E$10000,'Sales Data'!$B$6:$B$10000,"Tiktok",'Sales Data'!$BC$6:$BC$10000,"Aug",'Sales Data'!$BD$6:$BD$10000,$O$21) | L36: =SUMIFS('Sales Data'!$E$6:$E$10000,'Sales Data'!$B$6:$B$10000,"Tiktok",'Sales Data'!$BC$6:$BC$10000,"Sep",'Sales Data'!$BD$6:$BD$10000,$O$21) | M36: =SUMIFS('Sales Data'!$E$6:$E$10000,'Sales Data'!$B$6:$B$10000,"Tiktok",'Sales Data'!$BC$6:$BC$10000,"Oct",'Sales Data'!$BD$6:$BD$10000,$O$21) | N36: =SUMIFS('Sales Data'!$E$6:$E$10000,'Sales Data'!$B$6:$B$10000,"Tiktok",'Sales Data'!$BC$6:$BC$10000,"Nov",'Sales Data'!$BD$6:$BD$10000,$O$21) | O36: =SUMIFS('Sales Data'!$E$6:$E$10000,'Sales Data'!$B$6:$B$10000,"Tiktok",'Sales Data'!$BC$6:$BC$10000,"Dec",'Sales Data'!$BD$6:$BD$10000,$O$21) | P36: =SUM(D36:O36)
C37: Expenses | D37: =SUMIFS('Main Expenses'!$E$6:$E$10000,'Main Expenses'!$B$6:$B$10000,"Tiktok",'Main Expenses'!$K$6:$K$10000,"Jan",'Main Expenses'!$L$6:$L$10000,$O$21) | E37: =SUMIFS('Main Expenses'!$E$6:$E$10000,'Main Expenses'!$B$6:$B$10000,"Tiktok",'Main Expenses'!$K$6:$K$10000,"Feb",'Main Expenses'!$L$6:$L$10000,$O$21) | F37: =SUMIFS('Main Expenses'!$E$6:$E$10000,'Main Expenses'!$B$6:$B$10000,"Tiktok",'Main Expenses'!$K$6:$K$10000,"Mar",'Main Expenses'!$L$6:$L$10000,$O$21) | G37: =SUMIFS('Main Expenses'!$E$6:$E$10000,'Main Expenses'!$B$6:$B$10000,"Tiktok",'Main Expenses'!$K$6:$K$10000,"Apr",'Main Expenses'!$L$6:$L$10000,$O$21) | H37: =SUMIFS('Main Expenses'!$E$6:$E$10000,'Main Expenses'!$B$6:$B$10000,"Tiktok",'Main Expenses'!$K$6:$K$10000,"May",'Main Expenses'!$L$6:$L$10000,$O$21) | I37: =SUMIFS('Main Expenses'!$E$6:$E$10000,'Main Expenses'!$B$6:$B$10000,"Tiktok",'Main Expenses'!$K$6:$K$10000,"Jun",'Main Expenses'!$L$6:$L$10000,$O$21) | J37: =SUMIFS('Main Expenses'!$E$6:$E$10000,'Main Expenses'!$B$6:$B$10000,"Tiktok",'Main Expenses'!$K$6:$K$10000,"Jul",'Main Expenses'!$L$6:$L$10000,$O$21) | K37: =SUMIFS('Main Expenses'!$E$6:$E$10000,'Main Expenses'!$B$6:$B$10000,"Tiktok",'Main Expenses'!$K$6:$K$10000,"Aug",'Main Expenses'!$L$6:$L$10000,$O$21) | L37: =SUMIFS('Main Expenses'!$E$6:$E$10000,'Main Expenses'!$B$6:$B$10000,"Tiktok",'Main Expenses'!$K$6:$K$10000,"Sep",'Main Expenses'!$L$6:$L$10000,$O$21) | M37: =SUMIFS('Main Expenses'!$E$6:$E$10000,'Main Expenses'!$B$6:$B$10000,"Tiktok",'Main Expenses'!$K$6:$K$10000,"Oct",'Main Expenses'!$L$6:$L$10000,$O$21) | N37: =SUMIFS('Main Expenses'!$E$6:$E$10000,'Main Expenses'!$B$6:$B$10000,"Tiktok",'Main Expenses'!$K$6:$K$10000,"Nov",'Main Expenses'!$L$6:$L$10000,$O$21) | O37: =SUMIFS('Main Expenses'!$E$6:$E$10000,'Main Expenses'!$B$6:$B$10000,"Tiktok",'Main Expenses'!$K$6:$K$10000,"Dec",'Main Expenses'!$L$6:$L$10000,$O$21) | P37: =SUM(D37:O37)
C38: Net Profit | D38: =D36+D37 | E38: =E36+E37 | F38: =F36+F37 | G38: =G36+G37 | H38: =H36+H37 | I38: =I36+I37 | J38: =J36+J37 | K38: =K36+K37 | ... O38: =O36+O37 | P38: =SUM(D38:O38)
C39: Margin % | D39: =IFERROR(D38/D36,0) | E39: =IFERROR(E38/E36,0) | F39: =IFERROR(F38/F36,0) | G39: =IFERROR(G38/G36,0) | H39: =IFERROR(H38/H36,0) | I39: =IFERROR(I38/I36,0) | J39: =IFERROR(J38/J36,0) | K39: =IFERROR(K38/K36,0) | ... P39: =IFERROR(P38/P36,0)
B40: Shopify & Faire | C40: Sales | D40: =SUMIFS('Sales Data'!$E$6:$E$10000,'Sales Data'!$B$6:$B$10000,"Shopify",'Sales Data'!$BC$6:$BC$10000,"Jan",'Sales Data'!$BD$6:$BD$10000,$O$21) | E40: =SUMIFS('Sales Data'!$E$6:$E$10000,'Sales Data'!$B$6:$B$10000,"Shopify",'Sales Data'!$BC$6:$BC$10000,"Feb",'Sales Data'!$BD$6:$BD$10000,$O$21) | F40: =SUMIFS('Sales Data'!$E$6:$E$10000,'Sales Data'!$B$6:$B$10000,"Shopify",'Sales Data'!$BC$6:$BC$10000,"Mar",'Sales Data'!$BD$6:$BD$10000,$O$21) | G40: =SUMIFS('Sales Data'!$E$6:$E$10000,'Sales Data'!$B$6:$B$10000,"Shopify",'Sales Data'!$BC$6:$BC$10000,"Apr",'Sales Data'!$BD$6:$BD$10000,$O$21) | H40: =SUMIFS('Sales Data'!$E$6:$E$10000,'Sales Data'!$B$6:$B$10000,"Shopify",'Sales Data'!$BC$6:$BC$10000,"May",'Sales Data'!$BD$6:$BD$10000,$O$21) | I40: =SUMIFS('Sales Data'!$E$6:$E$10000,'Sales Data'!$B$6:$B$10000,"Shopify",'Sales Data'!$BC$6:$BC$10000,"Jun",'Sales Data'!$BD$6:$BD$10000,$O$21) | J40: =SUMIFS('Sales Data'!$E$6:$E$10000,'Sales Data'!$B$6:$B$10000,"Shopify",'Sales Data'!$BC$6:$BC$10000,"Jul",'Sales Data'!$BD$6:$BD$10000,$O$21) | K40: =SUMIFS('Sales Data'!$E$6:$E$10000,'Sales Data'!$B$6:$B$10000,"Shopify",'Sales Data'!$BC$6:$BC$10000,"Aug",'Sales Data'!$BD$6:$BD$10000,$O$21) | L40: =SUMIFS('Sales Data'!$E$6:$E$10000,'Sales Data'!$B$6:$B$10000,"Shopify",'Sales Data'!$BC$6:$BC$10000,"Sep",'Sales Data'!$BD$6:$BD$10000,$O$21) | M40: =SUMIFS('Sales Data'!$E$6:$E$10000,'Sales Data'!$B$6:$B$10000,"Shopify",'Sales Data'!$BC$6:$BC$10000,"Oct",'Sales Data'!$BD$6:$BD$10000,$O$21) | N40: =SUMIFS('Sales Data'!$E$6:$E$10000,'Sales Data'!$B$6:$B$10000,"Shopify",'Sales Data'!$BC$6:$BC$10000,"Nov",'Sales Data'!$BD$6:$BD$10000,$O$21) | O40: =SUMIFS('Sales Data'!$E$6:$E$10000,'Sales Data'!$B$6:$B$10000,"Shopify",'Sales Data'!$BC$6:$BC$10000,"Dec",'Sales Data'!$BD$6:$BD$10000,$O$21) | P40: =SUM(D40:O40)
C41: Expenses | D41: =SUMIFS('Main Expenses'!$E$6:$E$10000,'Main Expenses'!$B$6:$B$10000,"Shopify",'Main Expenses'!$K$6:$K$10000,"Jan",'Main Expenses'!$L$6:$L$10000,$O$21) | E41: =SUMIFS('Main Expenses'!$E$6:$E$10000,'Main Expenses'!$B$6:$B$10000,"Shopify",'Main Expenses'!$K$6:$K$10000,"Feb",'Main Expenses'!$L$6:$L$10000,$O$21) | F41: =SUMIFS('Main Expenses'!$E$6:$E$10000,'Main Expenses'!$B$6:$B$10000,"Shopify",'Main Expenses'!$K$6:$K$10000,"Mar",'Main Expenses'!$L$6:$L$10000,$O$21) | G41: =SUMIFS('Main Expenses'!$E$6:$E$10000,'Main Expenses'!$B$6:$B$10000,"Shopify",'Main Expenses'!$K$6:$K$10000,"Apr",'Main Expenses'!$L$6:$L$10000,$O$21) | H41: =SUMIFS('Main Expenses'!$E$6:$E$10000,'Main Expenses'!$B$6:$B$10000,"Shopify",'Main Expenses'!$K$6:$K$10000,"May",'Main Expenses'!$L$6:$L$10000,$O$21) | I41: =SUMIFS('Main Expenses'!$E$6:$E$10000,'Main Expenses'!$B$6:$B$10000,"Shopify",'Main Expenses'!$K$6:$K$10000,"Jun",'Main Expenses'!$L$6:$L$10000,$O$21) | J41: =SUMIFS('Main Expenses'!$E$6:$E$10000,'Main Expenses'!$B$6:$B$10000,"Shopify",'Main Expenses'!$K$6:$K$10000,"Jul",'Main Expenses'!$L$6:$L$10000,$O$21) | K41: =SUMIFS('Main Expenses'!$E$6:$E$10000,'Main Expenses'!$B$6:$B$10000,"Shopify",'Main Expenses'!$K$6:$K$10000,"Aug",'Main Expenses'!$L$6:$L$10000,$O$21) | L41: =SUMIFS('Main Expenses'!$E$6:$E$10000,'Main Expenses'!$B$6:$B$10000,"Shopify",'Main Expenses'!$K$6:$K$10000,"Sep",'Main Expenses'!$L$6:$L$10000,$O$21) | M41: =SUMIFS('Main Expenses'!$E$6:$E$10000,'Main Expenses'!$B$6:$B$10000,"Shopify",'Main Expenses'!$K$6:$K$10000,"Oct",'Main Expenses'!$L$6:$L$10000,$O$21) | N41: =SUMIFS('Main Expenses'!$E$6:$E$10000,'Main Expenses'!$B$6:$B$10000,"Shopify",'Main Expenses'!$K$6:$K$10000,"Nov",'Main Expenses'!$L$6:$L$10000,$O$21) | O41: =SUMIFS('Main Expenses'!$E$6:$E$10000,'Main Expenses'!$B$6:$B$10000,"Shopify",'Main Expenses'!$K$6:$K$10000,"Dec",'Main Expenses'!$L$6:$L$10000,$O$21) | P41: =SUM(D41:O41)
C42: Net Profit | D42: =D40+D41 | E42: =E40+E41 | F42: =F40+F41 | G42: =G40+G41 | H42: =H40+H41 | I42: =I40+I41 | J42: =J40+J41 | K42: =K40+K41 | ... O42: =O40+O41 | P42: =SUM(D42:O42)
C43: Margin % | D43: =IFERROR(D42/D40,0) | E43: =IFERROR(E42/E40,0) | F43: =IFERROR(F42/F40,0) | G43: =IFERROR(G42/G40,0) | H43: =IFERROR(H42/H40,0) | I43: =IFERROR(I42/I40,0) | J43: =IFERROR(J42/J40,0) | K43: =IFERROR(K42/K40,0) | ... P43: =IFERROR(P42/P40,0)
B44: Walmart | C44: Sales | D44: =SUMIFS('Sales Data'!$E$6:$E$10000,'Sales Data'!$B$6:$B$10000,"Walmart",'Sales Data'!$BC$6:$BC$10000,"Jan",'Sales Data'!$BD$6:$BD$10000,$O$21) | E44: =SUMIFS('Sales Data'!$E$6:$E$10000,'Sales Data'!$B$6:$B$10000,"Walmart",'Sales Data'!$BC$6:$BC$10000,"Feb",'Sales Data'!$BD$6:$BD$10000,$O$21) | F44: =SUMIFS('Sales Data'!$E$6:$E$10000,'Sales Data'!$B$6:$B$10000,"Walmart",'Sales Data'!$BC$6:$BC$10000,"Mar",'Sales Data'!$BD$6:$BD$10000,$O$21) | G44: =SUMIFS('Sales Data'!$E$6:$E$10000,'Sales Data'!$B$6:$B$10000,"Walmart",'Sales Data'!$BC$6:$BC$10000,"Apr",'Sales Data'!$BD$6:$BD$10000,$O$21) | H44: =SUMIFS('Sales Data'!$E$6:$E$10000,'Sales Data'!$B$6:$B$10000,"Walmart",'Sales Data'!$BC$6:$BC$10000,"May",'Sales Data'!$BD$6:$BD$10000,$O$21) | I44: =SUMIFS('Sales Data'!$E$6:$E$10000,'Sales Data'!$B$6:$B$10000,"Walmart",'Sales Data'!$BC$6:$BC$10000,"Jun",'Sales Data'!$BD$6:$BD$10000,$O$21) | J44: =SUMIFS('Sales Data'!$E$6:$E$10000,'Sales Data'!$B$6:$B$10000,"Walmart",'Sales Data'!$BC$6:$BC$10000,"Jul",'Sales Data'!$BD$6:$BD$10000,$O$21) | K44: =SUMIFS('Sales Data'!$E$6:$E$10000,'Sales Data'!$B$6:$B$10000,"Walmart",'Sales Data'!$BC$6:$BC$10000,"Aug",'Sales Data'!$BD$6:$BD$10000,$O$21) | L44: =SUMIFS('Sales Data'!$E$6:$E$10000,'Sales Data'!$B$6:$B$10000,"Walmart",'Sales Data'!$BC$6:$BC$10000,"Sep",'Sales Data'!$BD$6:$BD$10000,$O$21) | M44: =SUMIFS('Sales Data'!$E$6:$E$10000,'Sales Data'!$B$6:$B$10000,"Walmart",'Sales Data'!$BC$6:$BC$10000,"Oct",'Sales Data'!$BD$6:$BD$10000,$O$21) | N44: =SUMIFS('Sales Data'!$E$6:$E$10000,'Sales Data'!$B$6:$B$10000,"Walmart",'Sales Data'!$BC$6:$BC$10000,"Nov",'Sales Data'!$BD$6:$BD$10000,$O$21) | O44: =SUMIFS('Sales Data'!$E$6:$E$10000,'Sales Data'!$B$6:$B$10000,"Walmart",'Sales Data'!$BC$6:$BC$10000,"Dec",'Sales Data'!$BD$6:$BD$10000,$O$21) | P44: =SUM(D44:O44)
C45: Expenses | D45: =SUMIFS('Main Expenses'!$E$6:$E$10000,'Main Expenses'!$B$6:$B$10000,"Walmart",'Main Expenses'!$K$6:$K$10000,"Jan",'Main Expenses'!$L$6:$L$10000,$O$21) | E45: =SUMIFS('Main Expenses'!$E$6:$E$10000,'Main Expenses'!$B$6:$B$10000,"Walmart",'Main Expenses'!$K$6:$K$10000,"Feb",'Main Expenses'!$L$6:$L$10000,$O$21) | F45: =SUMIFS('Main Expenses'!$E$6:$E$10000,'Main Expenses'!$B$6:$B$10000,"Walmart",'Main Expenses'!$K$6:$K$10000,"Mar",'Main Expenses'!$L$6:$L$10000,$O$21) | G45: =SUMIFS('Main Expenses'!$E$6:$E$10000,'Main Expenses'!$B$6:$B$10000,"Walmart",'Main Expenses'!$K$6:$K$10000,"Apr",'Main Expenses'!$L$6:$L$10000,$O$21) | H45: =SUMIFS('Main Expenses'!$E$6:$E$10000,'Main Expenses'!$B$6:$B$10000,"Walmart",'Main Expenses'!$K$6:$K$10000,"May",'Main Expenses'!$L$6:$L$10000,$O$21) | I45: =SUMIFS('Main Expenses'!$E$6:$E$10000,'Main Expenses'!$B$6:$B$10000,"Walmart",'Main Expenses'!$K$6:$K$10000,"Jun",'Main Expenses'!$L$6:$L$10000,$O$21) | J45: =SUMIFS('Main Expenses'!$E$6:$E$10000,'Main Expenses'!$B$6:$B$10000,"Walmart",'Main Expenses'!$K$6:$K$10000,"Jul",'Main Expenses'!$L$6:$L$10000,$O$21) | K45: =SUMIFS('Main Expenses'!$E$6:$E$10000,'Main Expenses'!$B$6:$B$10000,"Walmart",'Main Expenses'!$K$6:$K$10000,"Aug",'Main Expenses'!$L$6:$L$10000,$O$21) | L45: =SUMIFS('Main Expenses'!$E$6:$E$10000,'Main Expenses'!$B$6:$B$10000,"Walmart",'Main Expenses'!$K$6:$K$10000,"Sep",'Main Expenses'!$L$6:$L$10000,$O$21) | M45: =SUMIFS('Main Expenses'!$E$6:$E$10000,'Main Expenses'!$B$6:$B$10000,"Walmart",'Main Expenses'!$K$6:$K$10000,"Oct",'Main Expenses'!$L$6:$L$10000,$O$21) | N45: =SUMIFS('Main Expenses'!$E$6:$E$10000,'Main Expenses'!$B$6:$B$10000,"Walmart",'Main Expenses'!$K$6:$K$10000,"Nov",'Main Expenses'!$L$6:$L$10000,$O$21) | O45: =SUMIFS('Main Expenses'!$E$6:$E$10000,'Main Expenses'!$B$6:$B$10000,"Walmart",'Main Expenses'!$K$6:$K$10000,"Dec",'Main Expenses'!$L$6:$L$10000,$O$21) | P45: =SUM(D45:O45)
C46: Net Profit | D46: =D44+D45 | E46: =E44+E45 | F46: =F44+F45 | G46: =G44+G45 | H46: =H44+H45 | I46: =I44+I45 | J46: =J44+J45 | K46: =K44+K45 | ... O46: =O44+O45 | P46: =SUM(D46:O46)
C47: Margin % | D47: =IFERROR(D46/D44,0) | E47: =IFERROR(E46/E44,0) | F47: =IFERROR(F46/F44,0) | G47: =IFERROR(G46/G44,0) | H47: =IFERROR(H46/H44,0) | I47: =IFERROR(I46/I44,0) | J47: =IFERROR(J46/J44,0) | K47: =IFERROR(K46/K44,0) | ... P47: =IFERROR(P46/P44,0)

Sheet Monthly Data
B2: MONTHLY DATA · ALL SALES CHANNELS
B3: One block per month · Sales + Expenses + Net Profit + Margin per marketplace
B6: JAN 2025
B7: Date | C7: Marketplace | D7: Sales (USD) | E7: Expenses (USD) | F7: Net Profit | G7: Margin | H7: Sales %
B8: 45688 | C8: Amazon US | D8: =SUMIFS('Sales Data'!$E$6:$E$10000,'Sales Data'!$B$6:$B$10000,"Amazon US",'Sales Data'!$BC$6:$BC$10000,"Jan",'Sales Data'!$BD$6:$BD$10000,2025) | E8: =SUMIFS('Main Expenses'!$E$6:$E$10000,'Main Expenses'!$B$6:$B$10000,"Amazon US",'Main Expenses'!$K$6:$K$10000,"Jan",'Main Expenses'!$L$6:$L$10000,2025) | F8: =D8+E8 | G8: =IFERROR(F8/D8,0) | H8: =IFERROR(D8/SUMIFS('Sales Data'!$E$6:$E$10000,'Sales Data'!$BC$6:$BC$10000,"Jan",'Sales Data'!$BD$6:$BD$10000,2025),0)
C9: Amazon CA | D9: =SUMIFS('Sales Data'!$E$6:$E$10000,'Sales Data'!$B$6:$B$10000,"Amazon CA",'Sales Data'!$BC$6:$BC$10000,"Jan",'Sales Data'!$BD$6:$BD$10000,2025) | E9: =SUMIFS('Main Expenses'!$E$6:$E$10000,'Main Expenses'!$B$6:$B$10000,"Amazon CA",'Main Expenses'!$K$6:$K$10000,"Jan",'Main Expenses'!$L$6:$L$10000,2025) | F9: =D9+E9 | G9: =IFERROR(F9/D9,0) | H9: =IFERROR(D9/SUMIFS('Sales Data'!$E$6:$E$10000,'Sales Data'!$BC$6:$BC$10000,"Jan",'Sales Data'!$BD$6:$BD$10000,2025),0)
C10: Amazon UK | D10: =SUMIFS('Sales Data'!$E$6:$E$10000,'Sales Data'!$B$6:$B$10000,"Amazon UK",'Sales Data'!$BC$6:$BC$10000,"Jan",'Sales Data'!$BD$6:$BD$10000,2025) | E10: =SUMIFS('Main Expenses'!$E$6:$E$10000,'Main Expenses'!$B$6:$B$10000,"Amazon UK",'Main Expenses'!$K$6:$K$10000,"Jan",'Main Expenses'!$L$6:$L$10000,2025) | F10: =D10+E10 | G10: =IFERROR(F10/D10,0) | H10: =IFERROR(D10/SUMIFS('Sales Data'!$E$6:$E$10000,'Sales Data'!$BC$6:$BC$10000,"Jan",'Sales Data'!$BD$6:$BD$10000,2025),0)
C11: TikTok Shop | D11: =SUMIFS('Sales Data'!$E$6:$E$10000,'Sales Data'!$B$6:$B$10000,"Tiktok",'Sales Data'!$BC$6:$BC$10000,"Jan",'Sales Data'!$BD$6:$BD$10000,2025) | E11: =SUMIFS('Main Expenses'!$E$6:$E$10000,'Main Expenses'!$B$6:$B$10000,"Tiktok",'Main Expenses'!$K$6:$K$10000,"Jan",'Main Expenses'!$L$6:$L$10000,2025) | F11: =D11+E11 | G11: =IFERROR(F11/D11,0) | H11: =IFERROR(D11/SUMIFS('Sales Data'!$E$6:$E$10000,'Sales Data'!$BC$6:$BC$10000,"Jan",'Sales Data'!$BD$6:$BD$10000,2025),0)
C12: Shopify & Faire | D12: =SUMIFS('Sales Data'!$E$6:$E$10000,'Sales Data'!$B$6:$B$10000,"Shopify",'Sales Data'!$BC$6:$BC$10000,"Jan",'Sales Data'!$BD$6:$BD$10000,2025) | E12: =SUMIFS('Main Expenses'!$E$6:$E$10000,'Main Expenses'!$B$6:$B$10000,"Shopify",'Main Expenses'!$K$6:$K$10000,"Jan",'Main Expenses'!$L$6:$L$10000,2025) | F12: =D12+E12 | G12: =IFERROR(F12/D12,0) | H12: =IFERROR(D12/SUMIFS('Sales Data'!$E$6:$E$10000,'Sales Data'!$BC$6:$BC$10000,"Jan",'Sales Data'!$BD$6:$BD$10000,2025),0)
C13: Walmart | D13: =SUMIFS('Sales Data'!$E$6:$E$10000,'Sales Data'!$B$6:$B$10000,"Walmart",'Sales Data'!$BC$6:$BC$10000,"Jan",'Sales Data'!$BD$6:$BD$10000,2025) | E13: =SUMIFS('Main Expenses'!$E$6:$E$10000,'Main Expenses'!$B$6:$B$10000,"Walmart",'Main Expenses'!$K$6:$K$10000,"Jan",'Main Expenses'!$L$6:$L$10000,2025) | F13: =D13+E13 | G13: =IFERROR(F13/D13,0) | H13: =IFERROR(D13/SUMIFS('Sales Data'!$E$6:$E$10000,'Sales Data'!$BC$6:$BC$10000,"Jan",'Sales Data'!$BD$6:$BD$10000,2025),0)
B14: TOTAL: | D14: =SUM(D8:D13) | E14: =SUM(E8:E13) | F14: =SUM(F8:F13) | G14: =IFERROR(F14/D14,0) | H14: 1
B16: FEB 2025
B17: Date | C17: Marketplace | D17: Sales (USD) | E17: Expenses (USD) | F17: Net Profit | G17: Margin | H17: Sales %
B18: 45716 | C18: Amazon US | D18: =SUMIFS('Sales Data'!$E$6:$E$10000,'Sales Data'!$B$6:$B$10000,"Amazon US",'Sales Data'!$BC$6:$BC$10000,"Feb",'Sales Data'!$BD$6:$BD$10000,2025) | E18: =SUMIFS('Main Expenses'!$E$6:$E$10000,'Main Expenses'!$B$6:$B$10000,"Amazon US",'Main Expenses'!$K$6:$K$10000,"Feb",'Main Expenses'!$L$6:$L$10000,2025) | F18: =D18+E18 | G18: =IFERROR(F18/D18,0) | H18: =IFERROR(D18/SUMIFS('Sales Data'!$E$6:$E$10000,'Sales Data'!$BC$6:$BC$10000,"Feb",'Sales Data'!$BD$6:$BD$10000,2025),0)
C19: Amazon CA | D19: =SUMIFS('Sales Data'!$E$6:$E$10000,'Sales Data'!$B$6:$B$10000,"Amazon CA",'Sales Data'!$BC$6:$BC$10000,"Feb",'Sales Data'!$BD$6:$BD$10000,2025) | E19: =SUMIFS('Main Expenses'!$E$6:$E$10000,'Main Expenses'!$B$6:$B$10000,"Amazon CA",'Main Expenses'!$K$6:$K$10000,"Feb",'Main Expenses'!$L$6:$L$10000,2025) | F19: =D19+E19 | G19: =IFERROR(F19/D19,0) | H19: =IFERROR(D19/SUMIFS('Sales Data'!$E$6:$E$10000,'Sales Data'!$BC$6:$BC$10000,"Feb",'Sales Data'!$BD$6:$BD$10000,2025),0)
C20: Amazon UK | D20: =SUMIFS('Sales Data'!$E$6:$E$10000,'Sales Data'!$B$6:$B$10000,"Amazon UK",'Sales Data'!$BC$6:$BC$10000,"Feb",'Sales Data'!$BD$6:$BD$10000,2025) | E20: =SUMIFS('Main Expenses'!$E$6:$E$10000,'Main Expenses'!$B$6:$B$10000,"Amazon UK",'Main Expenses'!$K$6:$K$10000,"Feb",'Main Expenses'!$L$6:$L$10000,2025) | F20: =D20+E20 | G20: =IFERROR(F20/D20,0) | H20: =IFERROR(D20/SUMIFS('Sales Data'!$E$6:$E$10000,'Sales Data'!$BC$6:$BC$10000,"Feb",'Sales Data'!$BD$6:$BD$10000,2025),0)
C21: TikTok Shop | D21: =SUMIFS('Sales Data'!$E$6:$E$10000,'Sales Data'!$B$6:$B$10000,"Tiktok",'Sales Data'!$BC$6:$BC$10000,"Feb",'Sales Data'!$BD$6:$BD$10000,2025) | E21: =SUMIFS('Main Expenses'!$E$6:$E$10000,'Main Expenses'!$B$6:$B$10000,"Tiktok",'Main Expenses'!$K$6:$K$10000,"Feb",'Main Expenses'!$L$6:$L$10000,2025) | F21: =D21+E21 | G21: =IFERROR(F21/D21,0) | H21: =IFERROR(D21/SUMIFS('Sales Data'!$E$6:$E$10000,'Sales Data'!$BC$6:$BC$10000,"Feb",'Sales Data'!$BD$6:$BD$10000,2025),0)
C22: Shopify & Faire | D22: =SUMIFS('Sales Data'!$E$6:$E$10000,'Sales Data'!$B$6:$B$10000,"Shopify",'Sales Data'!$BC$6:$BC$10000,"Feb",'Sales Data'!$BD$6:$BD$10000,2025) | E22: =SUMIFS('Main Expenses'!$E$6:$E$10000,'Main Expenses'!$B$6:$B$10000,"Shopify",'Main Expenses'!$K$6:$K$10000,"Feb",'Main Expenses'!$L$6:$L$10000,2025) | F22: =D22+E22 | G22: =IFERROR(F22/D22,0) | H22: =IFERROR(D22/SUMIFS('Sales Data'!$E$6:$E$10000,'Sales Data'!$BC$6:$BC$10000,"Feb",'Sales Data'!$BD$6:$BD$10000,2025),0)
C23: Walmart | D23: =SUMIFS('Sales Data'!$E$6:$E$10000,'Sales Data'!$B$6:$B$10000,"Walmart",'Sales Data'!$BC$6:$BC$10000,"Feb",'Sales Data'!$BD$6:$BD$10000,2025) | E23: =SUMIFS('Main Expenses'!$E$6:$E$10000,'Main Expenses'!$B$6:$B$10000,"Walmart",'Main Expenses'!$K$6:$K$10000,"Feb",'Main Expenses'!$L$6:$L$10000,2025) | F23: =D23+E23 | G23: =IFERROR(F23/D23,0) | H23: =IFERROR(D23/SUMIFS('Sales Data'!$E$6:$E$10000,'Sales Data'!$BC$6:$BC$10000,"Feb",'Sales Data'!$BD$6:$BD$10000,2025),0)
B24: TOTAL: | D24: =SUM(D18:D23) | E24: =SUM(E18:E23) | F24: =SUM(F18:F23) | G24: =IFERROR(F24/D24,0) | H24: 1
B26: MAR 2025
B27: Date | C27: Marketplace | D27: Sales (USD) | E27: Expenses (USD) | F27: Net Profit | G27: Margin | H27: Sales %
B28: 45747 | C28: Amazon US | D28: =SUMIFS('Sales Data'!$E$6:$E$10000,'Sales Data'!$B$6:$B$10000,"Amazon US",'Sales Data'!$BC$6:$BC$10000,"Mar",'Sales Data'!$BD$6:$BD$10000,2025) | E28: =SUMIFS('Main Expenses'!$E$6:$E$10000,'Main Expenses'!$B$6:$B$10000,"Amazon US",'Main Expenses'!$K$6:$K$10000,"Mar",'Main Expenses'!$L$6:$L$10000,2025) | F28: =D28+E28 | G28: =IFERROR(F28/D28,0) | H28: =IFERROR(D28/SUMIFS('Sales Data'!$E$6:$E$10000,'Sales Data'!$BC$6:$BC$10000,"Mar",'Sales Data'!$BD$6:$BD$10000,2025),0)
C29: Amazon CA | D29: =SUMIFS('Sales Data'!$E$6:$E$10000,'Sales Data'!$B$6:$B$10000,"Amazon CA",'Sales Data'!$BC$6:$BC$10000,"Mar",'Sales Data'!$BD$6:$BD$10000,2025) | E29: =SUMIFS('Main Expenses'!$E$6:$E$10000,'Main Expenses'!$B$6:$B$10000,"Amazon CA",'Main Expenses'!$K$6:$K$10000,"Mar",'Main Expenses'!$L$6:$L$10000,2025) | F29: =D29+E29 | G29: =IFERROR(F29/D29,0) | H29: =IFERROR(D29/SUMIFS('Sales Data'!$E$6:$E$10000,'Sales Data'!$BC$6:$BC$10000,"Mar",'Sales Data'!$BD$6:$BD$10000,2025),0)
C30: Amazon UK | D30: =SUMIFS('Sales Data'!$E$6:$E$10000,'Sales Data'!$B$6:$B$10000,"Amazon UK",'Sales Data'!$BC$6:$BC$10000,"Mar",'Sales Data'!$BD$6:$BD$10000,2025) | E30: =SUMIFS('Main Expenses'!$E$6:$E$10000,'Main Expenses'!$B$6:$B$10000,"Amazon UK",'Main Expenses'!$K$6:$K$10000,"Mar",'Main Expenses'!$L$6:$L$10000,2025) | F30: =D30+E30 | G30: =IFERROR(F30/D30,0) | H30: =IFERROR(D30/SUMIFS('Sales Data'!$E$6:$E$10000,'Sales Data'!$BC$6:$BC$10000,"Mar",'Sales Data'!$BD$6:$BD$10000,2025),0)
C31: TikTok Shop | D31: =SUMIFS('Sales Data'!$E$6:$E$10000,'Sales Data'!$B$6:$B$10000,"Tiktok",'Sales Data'!$BC$6:$BC$10000,"Mar",'Sales Data'!$BD$6:$BD$10000,2025) | E31: =SUMIFS('Main Expenses'!$E$6:$E$10000,'Main Expenses'!$B$6:$B$10000,"Tiktok",'Main Expenses'!$K$6:$K$10000,"Mar",'Main Expenses'!$L$6:$L$10000,2025) | F31: =D31+E31 | G31: =IFERROR(F31/D31,0) | H31: =IFERROR(D31/SUMIFS('Sales Data'!$E$6:$E$10000,'Sales Data'!$BC$6:$BC$10000,"Mar",'Sales Data'!$BD$6:$BD$10000,2025),0)
C32: Shopify & Faire | D32: =SUMIFS('Sales Data'!$E$6:$E$10000,'Sales Data'!$B$6:$B$10000,"Shopify",'Sales Data'!$BC$6:$BC$10000,"Mar",'Sales Data'!$BD$6:$BD$10000,2025) | E32: =SUMIFS('Main Expenses'!$E$6:$E$10000,'Main Expenses'!$B$6:$B$10000,"Shopify",'Main Expenses'!$K$6:$K$10000,"Mar",'Main Expenses'!$L$6:$L$10000,2025) | F32: =D32+E32 | G32: =IFERROR(F32/D32,0) | H32: =IFERROR(D32/SUMIFS('Sales Data'!$E$6:$E$10000,'Sales Data'!$BC$6:$BC$10000,"Mar",'Sales Data'!$BD$6:$BD$10000,2025),0)
C33: Walmart | D33: =SUMIFS('Sales Data'!$E$6:$E$10000,'Sales Data'!$B$6:$B$10000,"Walmart",'Sales Data'!$BC$6:$BC$10000,"Mar",'Sales Data'!$BD$6:$BD$10000,2025) | E33: =SUMIFS('Main Expenses'!$E$6:$E$10000,'Main Expenses'!$B$6:$B$10000,"Walmart",'Main Expenses'!$K$6:$K$10000,"Mar",'Main Expenses'!$L$6:$L$10000,2025) | F33: =D33+E33 | G33: =IFERROR(F33/D33,0) | H33: =IFERROR(D33/SUMIFS('Sales Data'!$E$6:$E$10000,'Sales Data'!$BC$6:$BC$10000,"Mar",'Sales Data'!$BD$6:$BD$10000,2025),0)
B34: TOTAL: | D34: =SUM(D28:D33) | E34: =SUM(E28:E33) | F34: =SUM(F28:F33) | G34: =IFERROR(F34/D34,0) | H34: 1
B36: APR 2025
B37: Date | C37: Marketplace | D37: Sales (USD) | E37: Expenses (USD) | F37: Net Profit | G37: Margin | H37: Sales %
B38: 45777 | C38: Amazon US | D38: =SUMIFS('Sales Data'!$E$6:$E$10000,'Sales Data'!$B$6:$B$10000,"Amazon US",'Sales Data'!$BC$6:$BC$10000,"Apr",'Sales Data'!$BD$6:$BD$10000,2025) | E38: =SUMIFS('Main Expenses'!$E$6:$E$10000,'Main Expenses'!$B$6:$B$10000,"Amazon US",'Main Expenses'!$K$6:$K$10000,"Apr",'Main Expenses'!$L$6:$L$10000,2025) | F38: =D38+E38 | G38: =IFERROR(F38/D38,0) | H38: =IFERROR(D38/SUMIFS('Sales Data'!$E$6:$E$10000,'Sales Data'!$BC$6:$BC$10000,"Apr",'Sales Data'!$BD$6:$BD$10000,2025),0)
C39: Amazon CA | D39: =SUMIFS('Sales Data'!$E$6:$E$10000,'Sales Data'!$B$6:$B$10000,"Amazon CA",'Sales Data'!$BC$6:$BC$10000,"Apr",'Sales Data'!$BD$6:$BD$10000,2025) | E39: =SUMIFS('Main Expenses'!$E$6:$E$10000,'Main Expenses'!$B$6:$B$10000,"Amazon CA",'Main Expenses'!$K$6:$K$10000,"Apr",'Main Expenses'!$L$6:$L$10000,2025) | F39: =D39+E39 | G39: =IFERROR(F39/D39,0) | H39: =IFERROR(D39/SUMIFS('Sales Data'!$E$6:$E$10000,'Sales Data'!$BC$6:$BC$10000,"Apr",'Sales Data'!$BD$6:$BD$10000,2025),0)
C40: Amazon UK | D40: =SUMIFS('Sales Data'!$E$6:$E$10000,'Sales Data'!$B$6:$B$10000,"Amazon UK",'Sales Data'!$BC$6:$BC$10000,"Apr",'Sales Data'!$BD$6:$BD$10000,2025) | E40: =SUMIFS('Main Expenses'!$E$6:$E$10000,'Main Expenses'!$B$6:$B$10000,"Amazon UK",'Main Expenses'!$K$6:$K$10000,"Apr",'Main Expenses'!$L$6:$L$10000,2025) | F40: =D40+E40 | G40: =IFERROR(F40/D40,0) | H40: =IFERROR(D40/SUMIFS('Sales Data'!$E$6:$E$10000,'Sales Data'!$BC$6:$BC$10000,"Apr",'Sales Data'!$BD$6:$BD$10000,2025),0)
C41: TikTok Shop | D41: =SUMIFS('Sales Data'!$E$6:$E$10000,'Sales Data'!$B$6:$B$10000,"Tiktok",'Sales Data'!$BC$6:$BC$10000,"Apr",'Sales Data'!$BD$6:$BD$10000,2025) | E41: =SUMIFS('Main Expenses'!$E$6:$E$10000,'Main Expenses'!$B$6:$B$10000,"Tiktok",'Main Expenses'!$K$6:$K$10000,"Apr",'Main Expenses'!$L$6:$L$10000,2025) | F41: =D41+E41 | G41: =IFERROR(F41/D41,0) | H41: =IFERROR(D41/SUMIFS('Sales Data'!$E$6:$E$10000,'Sales Data'!$BC$6:$BC$10000,"Apr",'Sales Data'!$BD$6:$BD$10000,2025),0)
C42: Shopify & Faire | D42: =SUMIFS('Sales Data'!$E$6:$E$10000,'Sales Data'!$B$6:$B$10000,"Shopify",'Sales Data'!$BC$6:$BC$10000,"Apr",'Sales Data'!$BD$6:$BD$10000,2025) | E42: =SUMIFS('Main Expenses'!$E$6:$E$10000,'Main Expenses'!$B$6:$B$10000,"Shopify",'Main Expenses'!$K$6:$K$10000,"Apr",'Main Expenses'!$L$6:$L$10000,2025) | F42: =D42+E42 | G42: =IFERROR(F42/D42,0) | H42: =IFERROR(D42/SUMIFS('Sales Data'!$E$6:$E$10000,'Sales Data'!$BC$6:$BC$10000,"Apr",'Sales Data'!$BD$6:$BD$10000,2025),0)
C43: Walmart | D43: =SUMIFS('Sales Data'!$E$6:$E$10000,'Sales Data'!$B$6:$B$10000,"Walmart",'Sales Data'!$BC$6:$BC$10000,"Apr",'Sales Data'!$BD$6:$BD$10000,2025) | E43: =SUMIFS('Main Expenses'!$E$6:$E$10000,'Main Expenses'!$B$6:$B$10000,"Walmart",'Main Expenses'!$K$6:$K$10000,"Apr",'Main Expenses'!$L$6:$L$10000,2025) | F43: =D43+E43 | G43: =IFERROR(F43/D43,0) | H43: =IFERROR(D43/SUMIFS('Sales Data'!$E$6:$E$10000,'Sales Data'!$BC$6:$BC$10000,"Apr",'Sales Data'!$BD$6:$BD$10000,2025),0)
B44: TOTAL: | D44: =SUM(D38:D43) | E44: =SUM(E38:E43) | F44: =SUM(F38:F43) | G44: =IFERROR(F44/D44,0) | H44: 1
B46: MAY 2025
B47: Date | C47: Marketplace | D47: Sales (USD) | E47: Expenses (USD) | F47: Net Profit | G47: Margin | H47: Sales %
B48: 45808 | C48: Amazon US | D48: =SUMIFS('Sales Data'!$E$6:$E$10000,'Sales Data'!$B$6:$B$10000,"Amazon US",'Sales Data'!$BC$6:$BC$10000,"May",'Sales Data'!$BD$6:$BD$10000,2025) | E48: =SUMIFS('Main Expenses'!$E$6:$E$10000,'Main Expenses'!$B$6:$B$10000,"Amazon US",'Main Expenses'!$K$6:$K$10000,"May",'Main Expenses'!$L$6:$L$10000,2025) | F48: =D48+E48 | G48: =IFERROR(F48/D48,0) | H48: =IFERROR(D48/SUMIFS('Sales Data'!$E$6:$E$10000,'Sales Data'!$BC$6:$BC$10000,"May",'Sales Data'!$BD$6:$BD$10000,2025),0)
C49: Amazon CA | D49: =SUMIFS('Sales Data'!$E$6:$E$10000,'Sales Data'!$B$6:$B$10000,"Amazon CA",'Sales Data'!$BC$6:$BC$10000,"May",'Sales Data'!$BD$6:$BD$10000,2025) | E49: =SUMIFS('Main Expenses'!$E$6:$E$10000,'Main Expenses'!$B$6:$B$10000,"Amazon CA",'Main Expenses'!$K$6:$K$10000,"May",'Main Expenses'!$L$6:$L$10000,2025) | F49: =D49+E49 | G49: =IFERROR(F49/D49,0) | H49: =IFERROR(D49/SUMIFS('Sales Data'!$E$6:$E$10000,'Sales Data'!$BC$6:$BC$10000,"May",'Sales Data'!$BD$6:$BD$10000,2025),0)
C50: Amazon UK | D50: =SUMIFS('Sales Data'!$E$6:$E$10000,'Sales Data'!$B$6:$B$10000,"Amazon UK",'Sales Data'!$BC$6:$BC$10000,"May",'Sales Data'!$BD$6:$BD$10000,2025) | E50: =SUMIFS('Main Expenses'!$E$6:$E$10000,'Main Expenses'!$B$6:$B$10000,"Amazon UK",'Main Expenses'!$K$6:$K$10000,"May",'Main Expenses'!$L$6:$L$10000,2025) | F50: =D50+E50 | G50: =IFERROR(F50/D50,0) | H50: =IFERROR(D50/SUMIFS('Sales Data'!$E$6:$E$10000,'Sales Data'!$BC$6:$BC$10000,"May",'Sales Data'!$BD$6:$BD$10000,2025),0)
C51: TikTok Shop | D51: =SUMIFS('Sales Data'!$E$6:$E$10000,'Sales Data'!$B$6:$B$10000,"Tiktok",'Sales Data'!$BC$6:$BC$10000,"May",'Sales Data'!$BD$6:$BD$10000,2025) | E51: =SUMIFS('Main Expenses'!$E$6:$E$10000,'Main Expenses'!$B$6:$B$10000,"Tiktok",'Main Expenses'!$K$6:$K$10000,"May",'Main Expenses'!$L$6:$L$10000,2025) | F51: =D51+E51 | G51: =IFERROR(F51/D51,0) | H51: =IFERROR(D51/SUMIFS('Sales Data'!$E$6:$E$10000,'Sales Data'!$BC$6:$BC$10000,"May",'Sales Data'!$BD$6:$BD$10000,2025),0)
C52: Shopify & Faire | D52: =SUMIFS('Sales Data'!$E$6:$E$10000,'Sales Data'!$B$6:$B$10000,"Shopify",'Sales Data'!$BC$6:$BC$10000,"May",'Sales Data'!$BD$6:$BD$10000,2025) | E52: =SUMIFS('Main Expenses'!$E$6:$E$10000,'Main Expenses'!$B$6:$B$10000,"Shopify",'Main Expenses'!$K$6:$K$10000,"May",'Main Expenses'!$L$6:$L$10000,2025) | F52: =D52+E52 | G52: =IFERROR(F52/D52,0) | H52: =IFERROR(D52/SUMIFS('Sales Data'!$E$6:$E$10000,'Sales Data'!$BC$6:$BC$10000,"May",'Sales Data'!$BD$6:$BD$10000,2025),0)
C53: Walmart | D53: =SUMIFS('Sales Data'!$E$6:$E$10000,'Sales Data'!$B$6:$B$10000,"Walmart",'Sales Data'!$BC$6:$BC$10000,"May",'Sales Data'!$BD$6:$BD$10000,2025) | E53: =SUMIFS('Main Expenses'!$E$6:$E$10000,'Main Expenses'!$B$6:$B$10000,"Walmart",'Main Expenses'!$K$6:$K$10000,"May",'Main Expenses'!$L$6:$L$10000,2025) | F53: =D53+E53 | G53: =IFERROR(F53/D53,0) | H53: =IFERROR(D53/SUMIFS('Sales Data'!$E$6:$E$10000,'Sales Data'!$BC$6:$BC$10000,"May",'Sales Data'!$BD$6:$BD$10000,2025),0)
B54: TOTAL: | D54: =SUM(D48:D53) | E54: =SUM(E48:E53) | F54: =SUM(F48:F53) | G54: =IFERROR(F54/D54,0) | H54: 1
B56: JUN 2025
B57: Date | C57: Marketplace | D57: Sales (USD) | E57: Expenses (USD) | F57: Net Profit | G57: Margin | H57: Sales %
B58: 45838 | C58: Amazon US | D58: =SUMIFS('Sales Data'!$E$6:$E$10000,'Sales Data'!$B$6:$B$10000,"Amazon US",'Sales Data'!$BC$6:$BC$10000,"Jun",'Sales Data'!$BD$6:$BD$10000,2025) | E58: =SUMIFS('Main Expenses'!$E$6:$E$10000,'Main Expenses'!$B$6:$B$10000,"Amazon US",'Main Expenses'!$K$6:$K$10000,"Jun",'Main Expenses'!$L$6:$L$10000,2025) | F58: =D58+E58 | G58: =IFERROR(F58/D58,0) | H58: =IFERROR(D58/SUMIFS('Sales Data'!$E$6:$E$10000,'Sales Data'!$BC$6:$BC$10000,"Jun",'Sales Data'!$BD$6:$BD$10000,2025),0)
C59: Amazon CA | D59: =SUMIFS('Sales Data'!$E$6:$E$10000,'Sales Data'!$B$6:$B$10000,"Amazon CA",'Sales Data'!$BC$6:$BC$10000,"Jun",'Sales Data'!$BD$6:$BD$10000,2025) | E59: =SUMIFS('Main Expenses'!$E$6:$E$10000,'Main Expenses'!$B$6:$B$10000,"Amazon CA",'Main Expenses'!$K$6:$K$10000,"Jun",'Main Expenses'!$L$6:$L$10000,2025) | F59: =D59+E59 | G59: =IFERROR(F59/D59,0) | H59: =IFERROR(D59/SUMIFS('Sales Data'!$E$6:$E$10000,'Sales Data'!$BC$6:$BC$10000,"Jun",'Sales Data'!$BD$6:$BD$10000,2025),0)
C60: Amazon UK | D60: =SUMIFS('Sales Data'!$E$6:$E$10000,'Sales Data'!$B$6:$B$10000,"Amazon UK",'Sales Data'!$BC$6:$BC$10000,"Jun",'Sales Data'!$BD$6:$BD$10000,2025) | E60: =SUMIFS('Main Expenses'!$E$6:$E$10000,'Main Expenses'!$B$6:$B$10000,"Amazon UK",'Main Expenses'!$K$6:$K$10000,"Jun",'Main Expenses'!$L$6:$L$10000,2025) | F60: =D60+E60 | G60: =IFERROR(F60/D60,0) | H60: =IFERROR(D60/SUMIFS('Sales Data'!$E$6:$E$10000,'Sales Data'!$BC$6:$BC$10000,"Jun",'Sales Data'!$BD$6:$BD$10000,2025),0)
C61: TikTok Shop | D61: =SUMIFS('Sales Data'!$E$6:$E$10000,'Sales Data'!$B$6:$B$10000,"Tiktok",'Sales Data'!$BC$6:$BC$10000,"Jun",'Sales Data'!$BD$6:$BD$10000,2025) | E61: =SUMIFS('Main Expenses'!$E$6:$E$10000,'Main Expenses'!$B$6:$B$10000,"Tiktok",'Main Expenses'!$K$6:$K$10000,"Jun",'Main Expenses'!$L$6:$L$10000,2025) | F61: =D61+E61 | G61: =IFERROR(F61/D61,0) | H61: =IFERROR(D61/SUMIFS('Sales Data'!$E$6:$E$10000,'Sales Data'!$BC$6:$BC$10000,"Jun",'Sales Data'!$BD$6:$BD$10000,2025),0)
C62: Shopify & Faire | D62: =SUMIFS('Sales Data'!$E$6:$E$10000,'Sales Data'!$B$6:$B$10000,"Shopify",'Sales Data'!$BC$6:$BC$10000,"Jun",'Sales Data'!$BD$6:$BD$10000,2025) | E62: =SUMIFS('Main Expenses'!$E$6:$E$10000,'Main Expenses'!$B$6:$B$10000,"Shopify",'Main Expenses'!$K$6:$K$10000,"Jun",'Main Expenses'!$L$6:$L$10000,2025) | F62: =D62+E62 | G62: =IFERROR(F62/D62,0) | H62: =IFERROR(D62/SUMIFS('Sales Data'!$E$6:$E$10000,'Sales Data'!$BC$6:$BC$10000,"Jun",'Sales Data'!$BD$6:$BD$10000,2025),0)
C63: Walmart | D63: =SUMIFS('Sales Data'!$E$6:$E$10000,'Sales Data'!$B$6:$B$10000,"Walmart",'Sales Data'!$BC$6:$BC$10000,"Jun",'Sales Data'!$BD$6:$BD$10000,2025) | E63: =SUMIFS('Main Expenses'!$E$6:$E$10000,'Main Expenses'!$B$6:$B$10000,"Walmart",'Main Expenses'!$K$6:$K$10000,"Jun",'Main Expenses'!$L$6:$L$10000,2025) | F63: =D63+E63 | G63: =IFERROR(F63/D63,0) | H63: =IFERROR(D63/SUMIFS('Sales Data'!$E$6:$E$10000,'Sales Data'!$BC$6:$BC$10000,"Jun",'Sales Data'!$BD$6:$BD$10000,2025),0)
B64: TOTAL: | D64: =SUM(D58:D63) | E64: =SUM(E58:E63) | F64: =SUM(F58:F63) | G64: =IFERROR(F64/D64,0) | H64: 1
B66: JUL 2025
B67: Date | C67: Marketplace | D67: Sales (USD) | E67: Expenses (USD) | F67: Net Profit | G67: Margin | H67: Sales %
B68: 45869 | C68: Amazon US | D68: =SUMIFS('Sales Data'!$E$6:$E$10000,'Sales Data'!$B$6:$B$10000,"Amazon US",'Sales Data'!$BC$6:$BC$10000,"Jul",'Sales Data'!$BD$6:$BD$10000,2025) | E68: =SUMIFS('Main Expenses'!$E$6:$E$10000,'Main Expenses'!$B$6:$B$10000,"Amazon US",'Main Expenses'!$K$6:$K$10000,"Jul",'Main Expenses'!$L$6:$L$10000,2025) | F68: =D68+E68 | G68: =IFERROR(F68/D68,0) | H68: =IFERROR(D68/SUMIFS('Sales Data'!$E$6:$E$10000,'Sales Data'!$BC$6:$BC$10000,"Jul",'Sales Data'!$BD$6:$BD$10000,2025),0)
C69: Amazon CA | D69: =SUMIFS('Sales Data'!$E$6:$E$10000,'Sales Data'!$B$6:$B$10000,"Amazon CA",'Sales Data'!$BC$6:$BC$10000,"Jul",'Sales Data'!$BD$6:$BD$10000,2025) | E69: =SUMIFS('Main Expenses'!$E$6:$E$10000,'Main Expenses'!$B$6:$B$10000,"Amazon CA",'Main Expenses'!$K$6:$K$10000,"Jul",'Main Expenses'!$L$6:$L$10000,2025) | F69: =D69+E69 | G69: =IFERROR(F69/D69,0) | H69: =IFERROR(D69/SUMIFS('Sales Data'!$E$6:$E$10000,'Sales Data'!$BC$6:$BC$10000,"Jul",'Sales Data'!$BD$6:$BD$10000,2025),0)
C70: Amazon UK | D70: =SUMIFS('Sales Data'!$E$6:$E$10000,'Sales Data'!$B$6:$B$10000,"Amazon UK",'Sales Data'!$BC$6:$BC$10000,"Jul",'Sales Data'!$BD$6:$BD$10000,2025) | E70: =SUMIFS('Main Expenses'!$E$6:$E$10000,'Main Expenses'!$B$6:$B$10000,"Amazon UK",'Main Expenses'!$K$6:$K$10000,"Jul",'Main Expenses'!$L$6:$L$10000,2025) | F70: =D70+E70 | G70: =IFERROR(F70/D70,0) | H70: =IFERROR(D70/SUMIFS('Sales Data'!$E$6:$E$10000,'Sales Data'!$BC$6:$BC$10000,"Jul",'Sales Data'!$BD$6:$BD$10000,2025),0)
C71: TikTok Shop | D71: =SUMIFS('Sales Data'!$E$6:$E$10000,'Sales Data'!$B$6:$B$10000,"Tiktok",'Sales Data'!$BC$6:$BC$10000,"Jul",'Sales Data'!$BD$6:$BD$10000,2025) | E71: =SUMIFS('Main Expenses'!$E$6:$E$10000,'Main Expenses'!$B$6:$B$10000,"Tiktok",'Main Expenses'!$K$6:$K$10000,"Jul",'Main Expenses'!$L$6:$L$10000,2025) | F71: =D71+E71 | G71: =IFERROR(F71/D71,0) | H71: =IFERROR(D71/SUMIFS('Sales Data'!$E$6:$E$10000,'Sales Data'!$BC$6:$BC$10000,"Jul",'Sales Data'!$BD$6:$BD$10000,2025),0)
C72: Shopify & Faire | D72: =SUMIFS('Sales Data'!$E$6:$E$10000,'Sales Data'!$B$6:$B$10000,"Shopify",'Sales Data'!$BC$6:$BC$10000,"Jul",'Sales Data'!$BD$6:$BD$10000,2025) | E72: =SUMIFS('Main Expenses'!$E$6:$E$10000,'Main Expenses'!$B$6:$B$10000,"Shopify",'Main Expenses'!$K$6:$K$10000,"Jul",'Main Expenses'!$L$6:$L$10000,2025) | F72: =D72+E72 | G72: =IFERROR(F72/D72,0) | H72: =IFERROR(D72/SUMIFS('Sales Data'!$E$6:$E$10000,'Sales Data'!$BC$6:$BC$10000,"Jul",'Sales Data'!$BD$6:$BD$10000,2025),0)
C73: Walmart | D73: =SUMIFS('Sales Data'!$E$6:$E$10000,'Sales Data'!$B$6:$B$10000,"Walmart",'Sales Data'!$BC$6:$BC$10000,"Jul",'Sales Data'!$BD$6:$BD$10000,2025) | E73: =SUMIFS('Main Expenses'!$E$6:$E$10000,'Main Expenses'!$B$6:$B$10000,"Walmart",'Main Expenses'!$K$6:$K$10000,"Jul",'Main Expenses'!$L$6:$L$10000,2025) | F73: =D73+E73 | G73: =IFERROR(F73/D73,0) | H73: =IFERROR(D73/SUMIFS('Sales Data'!$E$6:$E$10000,'Sales Data'!$BC$6:$BC$10000,"Jul",'Sales Data'!$BD$6:$BD$10000,2025),0)
B74: TOTAL: | D74: =SUM(D68:D73) | E74: =SUM(E68:E73) | F74: =SUM(F68:F73) | G74: =IFERROR(F74/D74,0) | H74: 1
B76: AUG 2025
B77: Date | C77: Marketplace | D77: Sales (USD) | E77: Expenses (USD) | F77: Net Profit | G77: Margin | H77: Sales %
B78: 45900 | C78: Amazon US | D78: =SUMIFS('Sales Data'!$E$6:$E$10000,'Sales Data'!$B$6:$B$10000,"Amazon US",'Sales Data'!$BC$6:$BC$10000,"Aug",'Sales Data'!$BD$6:$BD$10000,2025) | E78: =SUMIFS('Main Expenses'!$E$6:$E$10000,'Main Expenses'!$B$6:$B$10000,"Amazon US",'Main Expenses'!$K$6:$K$10000,"Aug",'Main Expenses'!$L$6:$L$10000,2025) | F78: =D78+E78 | G78: =IFERROR(F78/D78,0) | H78: =IFERROR(D78/SUMIFS('Sales Data'!$E$6:$E$10000,'Sales Data'!$BC$6:$BC$10000,"Aug",'Sales Data'!$BD$6:$BD$10000,2025),0)
C79: Amazon CA | D79: =SUMIFS('Sales Data'!$E$6:$E$10000,'Sales Data'!$B$6:$B$10000,"Amazon CA",'Sales Data'!$BC$6:$BC$10000,"Aug",'Sales Data'!$BD$6:$BD$10000,2025) | E79: =SUMIFS('Main Expenses'!$E$6:$E$10000,'Main Expenses'!$B$6:$B$10000,"Amazon CA",'Main Expenses'!$K$6:$K$10000,"Aug",'Main Expenses'!$L$6:$L$10000,2025) | F79: =D79+E79 | G79: =IFERROR(F79/D79,0) | H79: =IFERROR(D79/SUMIFS('Sales Data'!$E$6:$E$10000,'Sales Data'!$BC$6:$BC$10000,"Aug",'Sales Data'!$BD$6:$BD$10000,2025),0)
C80: Amazon UK | D80: =SUMIFS('Sales Data'!$E$6:$E$10000,'Sales Data'!$B$6:$B$10000,"Amazon UK",'Sales Data'!$BC$6:$BC$10000,"Aug",'Sales Data'!$BD$6:$BD$10000,2025) | E80: =SUMIFS('Main Expenses'!$E$6:$E$10000,'Main Expenses'!$B$6:$B$10000,"Amazon UK",'Main Expenses'!$K$6:$K$10000,"Aug",'Main Expenses'!$L$6:$L$10000,2025) | F80: =D80+E80 | G80: =IFERROR(F80/D80,0) | H80: =IFERROR(D80/SUMIFS('Sales Data'!$E$6:$E$10000,'Sales Data'!$BC$6:$BC$10000,"Aug",'Sales Data'!$BD$6:$BD$10000,2025),0)
C81: TikTok Shop | D81: =SUMIFS('Sales Data'!$E$6:$E$10000,'Sales Data'!$B$6:$B$10000,"Tiktok",'Sales Data'!$BC$6:$BC$10000,"Aug",'Sales Data'!$BD$6:$BD$10000,2025) | E81: =SUMIFS('Main Expenses'!$E$6:$E$10000,'Main Expenses'!$B$6:$B$10000,"Tiktok",'Main Expenses'!$K$6:$K$10000,"Aug",'Main Expenses'!$L$6:$L$10000,2025) | F81: =D81+E81 | G81: =IFERROR(F81/D81,0) | H81: =IFERROR(D81/SUMIFS('Sales Data'!$E$6:$E$10000,'Sales Data'!$BC$6:$BC$10000,"Aug",'Sales Data'!$BD$6:$BD$10000,2025),0)
C82: Shopify & Faire | D82: =SUMIFS('Sales Data'!$E$6:$E$10000,'Sales Data'!$B$6:$B$10000,"Shopify",'Sales Data'!$BC$6:$BC$10000,"Aug",'Sales Data'!$BD$6:$BD$10000,2025) | E82: =SUMIFS('Main Expenses'!$E$6:$E$10000,'Main Expenses'!$B$6:$B$10000,"Shopify",'Main Expenses'!$K$6:$K$10000,"Aug",'Main Expenses'!$L$6:$L$10000,2025) | F82: =D82+E82 | G82: =IFERROR(F82/D82,0) | H82: =IFERROR(D82/SUMIFS('Sales Data'!$E$6:$E$10000,'Sales Data'!$BC$6:$BC$10000,"Aug",'Sales Data'!$BD$6:$BD$10000,2025),0)
C83: Walmart | D83: =SUMIFS('Sales Data'!$E$6:$E$10000,'Sales Data'!$B$6:$B$10000,"Walmart",'Sales Data'!$BC$6:$BC$10000,"Aug",'Sales Data'!$BD$6:$BD$10000,2025) | E83: =SUMIFS('Main Expenses'!$E$6:$E$10000,'Main Expenses'!$B$6:$B$10000,"Walmart",'Main Expenses'!$K$6:$K$10000,"Aug",'Main Expenses'!$L$6:$L$10000,2025) | F83: =D83+E83 | G83: =IFERROR(F83/D83,0) | H83: =IFERROR(D83/SUMIFS('Sales Data'!$E$6:$E$10000,'Sales Data'!$BC$6:$BC$10000,"Aug",'Sales Data'!$BD$6:$BD$10000,2025),0)
B84: TOTAL: | D84: =SUM(D78:D83) | E84: =SUM(E78:E83) | F84: =SUM(F78:F83) | G84: =IFERROR(F84/D84,0) | H84: 1
B86: SEP 2025
B87: Date | C87: Marketplace | D87: Sales (USD) | E87: Expenses (USD) | F87: Net Profit | G87: Margin | H87: Sales %
B88: 45930 | C88: Amazon US | D88: =SUMIFS('Sales Data'!$E$6:$E$10000,'Sales Data'!$B$6:$B$10000,"Amazon US",'Sales Data'!$BC$6:$BC$10000,"Sep",'Sales Data'!$BD$6:$BD$10000,2025) | E88: =SUMIFS('Main Expenses'!$E$6:$E$10000,'Main Expenses'!$B$6:$B$10000,"Amazon US",'Main Expenses'!$K$6:$K$10000,"Sep",'Main Expenses'!$L$6:$L$10000,2025) | F88: =D88+E88 | G88: =IFERROR(F88/D88,0) | H88: =IFERROR(D88/SUMIFS('Sales Data'!$E$6:$E$10000,'Sales Data'!$BC$6:$BC$10000,"Sep",'Sales Data'!$BD$6:$BD$10000,2025),0)
C89: Amazon CA | D89: =SUMIFS('Sales Data'!$E$6:$E$10000,'Sales Data'!$B$6:$B$10000,"Amazon CA",'Sales Data'!$BC$6:$BC$10000,"Sep",'Sales Data'!$BD$6:$BD$10000,2025) | E89: =SUMIFS('Main Expenses'!$E$6:$E$10000,'Main Expenses'!$B$6:$B$10000,"Amazon CA",'Main Expenses'!$K$6:$K$10000,"Sep",'Main Expenses'!$L$6:$L$10000,2025) | F89: =D89+E89 | G89: =IFERROR(F89/D89,0) | H89: =IFERROR(D89/SUMIFS('Sales Data'!$E$6:$E$10000,'Sales Data'!$BC$6:$BC$10000,"Sep",'Sales Data'!$BD$6:$BD$10000,2025),0)
C90: Amazon UK | D90: =SUMIFS('Sales Data'!$E$6:$E$10000,'Sales Data'!$B$6:$B$10000,"Amazon UK",'Sales Data'!$BC$6:$BC$10000,"Sep",'Sales Data'!$BD$6:$BD$10000,2025) | E90: =SUMIFS('Main Expenses'!$E$6:$E$10000,'Main Expenses'!$B$6:$B$10000,"Amazon UK",'Main Expenses'!$K$6:$K$10000,"Sep",'Main Expenses'!$L$6:$L$10000,2025) | F90: =D90+E90 | G90: =IFERROR(F90/D90,0) | H90: =IFERROR(D90/SUMIFS('Sales Data'!$E$6:$E$10000,'Sales Data'!$BC$6:$BC$10000,"Sep",'Sales Data'!$BD$6:$BD$10000,2025),0)
C91: TikTok Shop | D91: =SUMIFS('Sales Data'!$E$6:$E$10000,'Sales Data'!$B$6:$B$10000,"Tiktok",'Sales Data'!$BC$6:$BC$10000,"Sep",'Sales Data'!$BD$6:$BD$10000,2025) | E91: =SUMIFS('Main Expenses'!$E$6:$E$10000,'Main Expenses'!$B$6:$B$10000,"Tiktok",'Main Expenses'!$K$6:$K$10000,"Sep",'Main Expenses'!$L$6:$L$10000,2025) | F91: =D91+E91 | G91: =IFERROR(F91/D91,0) | H91: =IFERROR(D91/SUMIFS('Sales Data'!$E$6:$E$10000,'Sales Data'!$BC$6:$BC$10000,"Sep",'Sales Data'!$BD$6:$BD$10000,2025),0)
C92: Shopify & Faire | D92: =SUMIFS('Sales Data'!$E$6:$E$10000,'Sales Data'!$B$6:$B$10000,"Shopify",'Sales Data'!$BC$6:$BC$10000,"Sep",'Sales Data'!$BD$6:$BD$10000,2025) | E92: =SUMIFS('Main Expenses'!$E$6:$E$10000,'Main Expenses'!$B$6:$B$10000,"Shopify",'Main Expenses'!$K$6:$K$10000,"Sep",'Main Expenses'!$L$6:$L$10000,2025) | F92: =D92+E92 | G92: =IFERROR(F92/D92,0) | H92: =IFERROR(D92/SUMIFS('Sales Data'!$E$6:$E$10000,'Sales Data'!$BC$6:$BC$10000,"Sep",'Sales Data'!$BD$6:$BD$10000,2025),0)
C93: Walmart | D93: =SUMIFS('Sales Data'!$E$6:$E$10000,'Sales Data'!$B$6:$B$10000,"Walmart",'Sales Data'!$BC$6:$BC$10000,"Sep",'Sales Data'!$BD$6:$BD$10000,2025) | E93: =SUMIFS('Main Expenses'!$E$6:$E$10000,'Main Expenses'!$B$6:$B$10000,"Walmart",'Main Expenses'!$K$6:$K$10000,"Sep",'Main Expenses'!$L$6:$L$10000,2025) | F93: =D93+E93 | G93: =IFERROR(F93/D93,0) | H93: =IFERROR(D93/SUMIFS('Sales Data'!$E$6:$E$10000,'Sales Data'!$BC$6:$BC$10000,"Sep",'Sales Data'!$BD$6:$BD$10000,2025),0)
B94: TOTAL: | D94: =SUM(D88:D93) | E94: =SUM(E88:E93) | F94: =SUM(F88:F93) | G94: =IFERROR(F94/D94,0) | H94: 1
B96: OCT 2025
B97: Date | C97: Marketplace | D97: Sales (USD) | E97: Expenses (USD) | F97: Net Profit | G97: Margin | H97: Sales %
B98: 45961 | C98: Amazon US | D98: =SUMIFS('Sales Data'!$E$6:$E$10000,'Sales Data'!$B$6:$B$10000,"Amazon US",'Sales Data'!$BC$6:$BC$10000,"Oct",'Sales Data'!$BD$6:$BD$10000,2025) | E98: =SUMIFS('Main Expenses'!$E$6:$E$10000,'Main Expenses'!$B$6:$B$10000,"Amazon US",'Main Expenses'!$K$6:$K$10000,"Oct",'Main Expenses'!$L$6:$L$10000,2025) | F98: =D98+E98 | G98: =IFERROR(F98/D98,0) | H98: =IFERROR(D98/SUMIFS('Sales Data'!$E$6:$E$10000,'Sales Data'!$BC$6:$BC$10000,"Oct",'Sales Data'!$BD$6:$BD$10000,2025),0)
C99: Amazon CA | D99: =SUMIFS('Sales Data'!$E$6:$E$10000,'Sales Data'!$B$6:$B$10000,"Amazon CA",'Sales Data'!$BC$6:$BC$10000,"Oct",'Sales Data'!$BD$6:$BD$10000,2025) | E99: =SUMIFS('Main Expenses'!$E$6:$E$10000,'Main Expenses'!$B$6:$B$10000,"Amazon CA",'Main Expenses'!$K$6:$K$10000,"Oct",'Main Expenses'!$L$6:$L$10000,2025) | F99: =D99+E99 | G99: =IFERROR(F99/D99,0) | H99: =IFERROR(D99/SUMIFS('Sales Data'!$E$6:$E$10000,'Sales Data'!$BC$6:$BC$10000,"Oct",'Sales Data'!$BD$6:$BD$10000,2025),0)
C100: Amazon UK | D100: =SUMIFS('Sales Data'!$E$6:$E$10000,'Sales Data'!$B$6:$B$10000,"Amazon UK",'Sales Data'!$BC$6:$BC$10000,"Oct",'Sales Data'!$BD$6:$BD$10000,2025) | E100: =SUMIFS('Main Expenses'!$E$6:$E$10000,'Main Expenses'!$B$6:$B$10000,"Amazon UK",'Main Expenses'!$K$6:$K$10000,"Oct",'Main Expenses'!$L$6:$L$10000,2025) | F100: =D100+E100 | G100: =IFERROR(F100/D100,0) | H100: =IFERROR(D100/SUMIFS('Sales Data'!$E$6:$E$10000,'Sales Data'!$BC$6:$BC$10000,"Oct",'Sales Data'!$BD$6:$BD$10000,2025),0)
C101: TikTok Shop | D101: =SUMIFS('Sales Data'!$E$6:$E$10000,'Sales Data'!$B$6:$B$10000,"Tiktok",'Sales Data'!$BC$6:$BC$10000,"Oct",'Sales Data'!$BD$6:$BD$10000,2025) | E101: =SUMIFS('Main Expenses'!$E$6:$E$10000,'Main Expenses'!$B$6:$B$10000,"Tiktok",'Main Expenses'!$K$6:$K$10000,"Oct",'Main Expenses'!$L$6:$L$10000,2025) | F101: =D101+E101 | G101: =IFERROR(F101/D101,0) | H101: =IFERROR(D101/SUMIFS('Sales Data'!$E$6:$E$10000,'Sales Data'!$BC$6:$BC$10000,"Oct",'Sales Data'!$BD$6:$BD$10000,2025),0)
C102: Shopify & Faire | D102: =SUMIFS('Sales Data'!$E$6:$E$10000,'Sales Data'!$B$6:$B$10000,"Shopify",'Sales Data'!$BC$6:$BC$10000,"Oct",'Sales Data'!$BD$6:$BD$10000,2025) | E102: =SUMIFS('Main Expenses'!$E$6:$E$10000,'Main Expenses'!$B$6:$B$10000,"Shopify",'Main Expenses'!$K$6:$K$10000,"Oct",'Main Expenses'!$L$6:$L$10000,2025) | F102: =D102+E102 | G102: =IFERROR(F102/D102,0) | H102: =IFERROR(D102/SUMIFS('Sales Data'!$E$6:$E$10000,'Sales Data'!$BC$6:$BC$10000,"Oct",'Sales Data'!$BD$6:$BD$10000,2025),0)
C103: Walmart | D103: =SUMIFS('Sales Data'!$E$6:$E$10000,'Sales Data'!$B$6:$B$10000,"Walmart",'Sales Data'!$BC$6:$BC$10000,"Oct",'Sales Data'!$BD$6:$BD$10000,2025) | E103: =SUMIFS('Main Expenses'!$E$6:$E$10000,'Main Expenses'!$B$6:$B$10000,"Walmart",'Main Expenses'!$K$6:$K$10000,"Oct",'Main Expenses'!$L$6:$L$10000,2025) | F103: =D103+E103 | G103: =IFERROR(F103/D103,0) | H103: =IFERROR(D103/SUMIFS('Sales Data'!$E$6:$E$10000,'Sales Data'!$BC$6:$BC$10000,"Oct",'Sales Data'!$BD$6:$BD$10000,2025),0)
B104: TOTAL: | D104: =SUM(D98:D103) | E104: =SUM(E98:E103) | F104: =SUM(F98:F103) | G104: =IFERROR(F104/D104,0) | H104: 1
B106: NOV 2025
B107: Date | C107: Marketplace | D107: Sales (USD) | E107: Expenses (USD) | F107: Net Profit | G107: Margin | H107: Sales %
B108: 45991 | C108: Amazon US | D108: =SUMIFS('Sales Data'!$E$6:$E$10000,'Sales Data'!$B$6:$B$10000,"Amazon US",'Sales Data'!$BC$6:$BC$10000,"Nov",'Sales Data'!$BD$6:$BD$10000,2025) | E108: =SUMIFS('Main Expenses'!$E$6:$E$10000,'Main Expenses'!$B$6:$B$10000,"Amazon US",'Main Expenses'!$K$6:$K$10000,"Nov",'Main Expenses'!$L$6:$L$10000,2025) | F108: =D108+E108 | G108: =IFERROR(F108/D108,0) | H108: =IFERROR(D108/SUMIFS('Sales Data'!$E$6:$E$10000,'Sales Data'!$BC$6:$BC$10000,"Nov",'Sales Data'!$BD$6:$BD$10000,2025),0)
C109: Amazon CA | D109: =SUMIFS('Sales Data'!$E$6:$E$10000,'Sales Data'!$B$6:$B$10000,"Amazon CA",'Sales Data'!$BC$6:$BC$10000,"Nov",'Sales Data'!$BD$6:$BD$10000,2025) | E109: =SUMIFS('Main Expenses'!$E$6:$E$10000,'Main Expenses'!$B$6:$B$10000,"Amazon CA",'Main Expenses'!$K$6:$K$10000,"Nov",'Main Expenses'!$L$6:$L$10000,2025) | F109: =D109+E109 | G109: =IFERROR(F109/D109,0) | H109: =IFERROR(D109/SUMIFS('Sales Data'!$E$6:$E$10000,'Sales Data'!$BC$6:$BC$10000,"Nov",'Sales Data'!$BD$6:$BD$10000,2025),0)
C110: Amazon UK | D110: =SUMIFS('Sales Data'!$E$6:$E$10000,'Sales Data'!$B$6:$B$10000,"Amazon UK",'Sales Data'!$BC$6:$BC$10000,"Nov",'Sales Data'!$BD$6:$BD$10000,2025) | E110: =SUMIFS('Main Expenses'!$E$6:$E$10000,'Main Expenses'!$B$6:$B$10000,"Amazon UK",'Main Expenses'!$K$6:$K$10000,"Nov",'Main Expenses'!$L$6:$L$10000,2025) | F110: =D110+E110 | G110: =IFERROR(F110/D110,0) | H110: =IFERROR(D110/SUMIFS('Sales Data'!$E$6:$E$10000,'Sales Data'!$BC$6:$BC$10000,"Nov",'Sales Data'!$BD$6:$BD$10000,2025),0)
C111: TikTok Shop | D111: =SUMIFS('Sales Data'!$E$6:$E$10000,'Sales Data'!$B$6:$B$10000,"Tiktok",'Sales Data'!$BC$6:$BC$10000,"Nov",'Sales Data'!$BD$6:$BD$10000,2025) | E111: =SUMIFS('Main Expenses'!$E$6:$E$10000,'Main Expenses'!$B$6:$B$10000,"Tiktok",'Main Expenses'!$K$6:$K$10000,"Nov",'Main Expenses'!$L$6:$L$10000,2025) | F111: =D111+E111 | G111: =IFERROR(F111/D111,0) | H111: =IFERROR(D111/SUMIFS('Sales Data'!$E$6:$E$10000,'Sales Data'!$BC$6:$BC$10000,"Nov",'Sales Data'!$BD$6:$BD$10000,2025),0)
C112: Shopify & Faire | D112: =SUMIFS('Sales Data'!$E$6:$E$10000,'Sales Data'!$B$6:$B$10000,"Shopify",'Sales Data'!$BC$6:$BC$10000,"Nov",'Sales Data'!$BD$6:$BD$10000,2025) | E112: =SUMIFS('Main Expenses'!$E$6:$E$10000,'Main Expenses'!$B$6:$B$10000,"Shopify",'Main Expenses'!$K$6:$K$10000,"Nov",'Main Expenses'!$L$6:$L$10000,2025) | F112: =D112+E112 | G112: =IFERROR(F112/D112,0) | H112: =IFERROR(D112/SUMIFS('Sales Data'!$E$6:$E$10000,'Sales Data'!$BC$6:$BC$10000,"Nov",'Sales Data'!$BD$6:$BD$10000,2025),0)
C113: Walmart | D113: =SUMIFS('Sales Data'!$E$6:$E$10000,'Sales Data'!$B$6:$B$10000,"Walmart",'Sales Data'!$BC$6:$BC$10000,"Nov",'Sales Data'!$BD$6:$BD$10000,2025) | E113: =SUMIFS('Main Expenses'!$E$6:$E$10000,'Main Expenses'!$B$6:$B$10000,"Walmart",'Main Expenses'!$K$6:$K$10000,"Nov",'Main Expenses'!$L$6:$L$10000,2025) | F113: =D113+E113 | G113: =IFERROR(F113/D113,0) | H113: =IFERROR(D113/SUMIFS('Sales Data'!$E$6:$E$10000,'Sales Data'!$BC$6:$BC$10000,"Nov",'Sales Data'!$BD$6:$BD$10000,2025),0)
...

Sheet Amazon Dashboard
B2: AMAZON DASHBOARD
B3: Click the + symbol on the left margin to expand sub-categories · all KPIs update live via SUMIFS formulas.
B6: MONTH | C6: YEAR | D6: MARKETPLACE | E6: CATEGORY
B7: Mar | C7: 2026 | D7: Amazon US | E7: All Categories
B9: KEY METRICS
B11: SALES | D11: =SUMIFS('Sales Data'!$E$6:$E$10000,'Sales Data'!$B$6:$B$10000,$D$7,'Sales Data'!$BC$6:$BC$10000,$B$7,'Sales Data'!$BD$6:$BD$10000,$C$7)
B12: EXPENSES | D12: =SUMIFS('Main Expenses'!$E$6:$E$10000,'Main Expenses'!$B$6:$B$10000,$D$7,'Main Expenses'!$K$6:$K$10000,$B$7,'Main Expenses'!$L$6:$L$10000,$C$7)
B13: UNIT SALES | D13: =SUMIFS('Sales Data'!$G$6:$G$10000,'Sales Data'!$B$6:$B$10000,$D$7,'Sales Data'!$BC$6:$BC$10000,$B$7,'Sales Data'!$BD$6:$BD$10000,$C$7)
B14: VAT | D14: =SUMIFS('Sales Data'!$J$6:$J$10000,'Sales Data'!$B$6:$B$10000,$D$7,'Sales Data'!$BC$6:$BC$10000,$B$7,'Sales Data'!$BD$6:$BD$10000,$C$7)
B15: NET PROFIT | D15: =SUMIFS('Sales Data'!$L$6:$L$10000,'Sales Data'!$B$6:$B$10000,$D$7,'Sales Data'!$BC$6:$BC$10000,$B$7,'Sales Data'!$BD$6:$BD$10000,$C$7)
B16: TACOS | D16: =SUMIFS('Sales Data'!$M$6:$M$10000,'Sales Data'!$B$6:$B$10000,$D$7,'Sales Data'!$BC$6:$BC$10000,$B$7,'Sales Data'!$BD$6:$BD$10000,$C$7)
B17: % REFUNDS | D17: =SUMIFS('Sales Data'!$N$6:$N$10000,'Sales Data'!$B$6:$B$10000,$D$7,'Sales Data'!$BC$6:$BC$10000,$B$7,'Sales Data'!$BD$6:$BD$10000,$C$7)
B18: SELLABLE RETURNS % | D18: =SUMIFS('Sales Data'!$O$6:$O$10000,'Sales Data'!$B$6:$B$10000,$D$7,'Sales Data'!$BC$6:$BC$10000,$B$7,'Sales Data'!$BD$6:$BD$10000,$C$7)
B19: MARGIN | D19: =SUMIFS('Sales Data'!$P$6:$P$10000,'Sales Data'!$B$6:$B$10000,$D$7,'Sales Data'!$BC$6:$BC$10000,$B$7,'Sales Data'!$BD$6:$BD$10000,$C$7)
B20: ROI | D20: =SUMIFS('Sales Data'!$Q$6:$Q$10000,'Sales Data'!$B$6:$B$10000,$D$7,'Sales Data'!$BC$6:$BC$10000,$B$7,'Sales Data'!$BD$6:$BD$10000,$C$7)
B23: MONTHLY TREND | I23: Trend Year: | J23: 2026
B25: METRIC | C25: Jan | D25: Feb | E25: Mar | F25: Apr | G25: May | H25: Jun | I25: Jul | J25: Aug | K25: Sep | L25: Oct | M25: Nov | N25: Dec | O25: YEAR TOTAL
B26: Sales (USD) | C26: =SUMIFS('Sales Data'!$E$6:$E$10000,'Sales Data'!$B$6:$B$10000,$D$7,'Sales Data'!$BC$6:$BC$10000,"Jan",'Sales Data'!$BD$6:$BD$10000,$J$23) | D26: =SUMIFS('Sales Data'!$E$6:$E$10000,'Sales Data'!$B$6:$B$10000,$D$7,'Sales Data'!$BC$6:$BC$10000,"Feb",'Sales Data'!$BD$6:$BD$10000,$J$23) | E26: =SUMIFS('Sales Data'!$E$6:$E$10000,'Sales Data'!$B$6:$B$10000,$D$7,'Sales Data'!$BC$6:$BC$10000,"Mar",'Sales Data'!$BD$6:$BD$10000,$J$23) | F26: =SUMIFS('Sales Data'!$E$6:$E$10000,'Sales Data'!$B$6:$B$10000,$D$7,'Sales Data'!$BC$6:$BC$10000,"Apr",'Sales Data'!$BD$6:$BD$10000,$J$23) | G26: =SUMIFS('Sales Data'!$E$6:$E$10000,'Sales Data'!$B$6:$B$10000,$D$7,'Sales Data'!$BC$6:$BC$10000,"May",'Sales Data'!$BD$6:$BD$10000,$J$23) | H26: =SUMIFS('Sales Data'!$E$6:$E$10000,'Sales Data'!$B$6:$B$10000,$D$7,'Sales Data'!$BC$6:$BC$10000,"Jun",'Sales Data'!$BD$6:$BD$10000,$J$23) | I26: =SUMIFS('Sales Data'!$E$6:$E$10000,'Sales Data'!$B$6:$B$10000,$D$7,'Sales Data'!$BC$6:$BC$10000,"Jul",'Sales Data'!$BD$6:$BD$10000,$J$23) | J26: =SUMIFS('Sales Data'!$E$6:$E$10000,'Sales Data'!$B$6:$B$10000,$D$7,'Sales Data'!$BC$6:$BC$10000,"Aug",'Sales Data'!$BD$6:$BD$10000,$J$23) | K26: =SUMIFS('Sales Data'!$E$6:$E$10000,'Sales Data'!$B$6:$B$10000,$D$7,'Sales Data'!$BC$6:$BC$10000,"Sep",'Sales Data'!$BD$6:$BD$10000,$J$23) | L26: =SUMIFS('Sales Data'!$E$6:$E$10000,'Sales Data'!$B$6:$B$10000,$D$7,'Sales Data'!$BC$6:$BC$10000,"Oct",'Sales Data'!$BD$6:$BD$10000,$J$23) | M26: =SUMIFS('Sales Data'!$E$6:$E$10000,'Sales Data'!$B$6:$B$10000,$D$7,'Sales Data'!$BC$6:$BC$10000,"Nov",'Sales Data'!$BD$6:$BD$10000,$J$23) | N26: =SUMIFS('Sales Data'!$E$6:$E$10000,'Sales Data'!$B$6:$B$10000,$D$7,'Sales Data'!$BC$6:$BC$10000,"Dec",'Sales Data'!$BD$6:$BD$10000,$J$23) | O26: =SUM(C26:N26)
B27: Units | C27: =SUMIFS('Sales Data'!$G$6:$G$10000,'Sales Data'!$B$6:$B$10000,$D$7,'Sales Data'!$BC$6:$BC$10000,"Jan",'Sales Data'!$BD$6:$BD$10000,$J$23) | D27: =SUMIFS('Sales Data'!$G$6:$G$10000,'Sales Data'!$B$6:$B$10000,$D$7,'Sales Data'!$BC$6:$BC$10000,"Feb",'Sales Data'!$BD$6:$BD$10000,$J$23) | E27: =SUMIFS('Sales Data'!$G$6:$G$10000,'Sales Data'!$B$6:$B$10000,$D$7,'Sales Data'!$BC$6:$BC$10000,"Mar",'Sales Data'!$BD$6:$BD$10000,$J$23) | F27: =SUMIFS('Sales Data'!$G$6:$G$10000,'Sales Data'!$B$6:$B$10000,$D$7,'Sales Data'!$BC$6:$BC$10000,"Apr",'Sales Data'!$BD$6:$BD$10000,$J$23) | G27: =SUMIFS('Sales Data'!$G$6:$G$10000,'Sales Data'!$B$6:$B$10000,$D$7,'Sales Data'!$BC$6:$BC$10000,"May",'Sales Data'!$BD$6:$BD$10000,$J$23) | H27: =SUMIFS('Sales Data'!$G$6:$G$10000,'Sales Data'!$B$6:$B$10000,$D$7,'Sales Data'!$BC$6:$BC$10000,"Jun",'Sales Data'!$BD$6:$BD$10000,$J$23) | I27: =SUMIFS('Sales Data'!$G$6:$G$10000,'Sales Data'!$B$6:$B$10000,$D$7,'Sales Data'!$BC$6:$BC$10000,"Jul",'Sales Data'!$BD$6:$BD$10000,$J$23) | J27: =SUMIFS('Sales Data'!$G$6:$G$10000,'Sales Data'!$B$6:$B$10000,$D$7,'Sales Data'!$BC$6:$BC$10000,"Aug",'Sales Data'!$BD$6:$BD$10000,$J$23) | K27: =SUMIFS('Sales Data'!$G$6:$G$10000,'Sales Data'!$B$6:$B$10000,$D$7,'Sales Data'!$BC$6:$BC$10000,"Sep",'Sales Data'!$BD$6:$BD$10000,$J$23) | L27: =SUMIFS('Sales Data'!$G$6:$G$10000,'Sales Data'!$B$6:$B$10000,$D$7,'Sales Data'!$BC$6:$BC$10000,"Oct",'Sales Data'!$BD$6:$BD$10000,$J$23) | M27: =SUMIFS('Sales Data'!$G$6:$G$10000,'Sales Data'!$B$6:$B$10000,$D$7,'Sales Data'!$BC$6:$BC$10000,"Nov",'Sales Data'!$BD$6:$BD$10000,$J$23) | N27: =SUMIFS('Sales Data'!$G$6:$G$10000,'Sales Data'!$B$6:$B$10000,$D$7,'Sales Data'!$BC$6:$BC$10000,"Dec",'Sales Data'!$BD$6:$BD$10000,$J$23) | O27: =SUM(C27:N27)
B28: Net Profit | C28: =SUMIFS('Sales Data'!$L$6:$L$10000,'Sales Data'!$B$6:$B$10000,$D$7,'Sales Data'!$BC$6:$BC$10000,"Jan",'Sales Data'!$BD$6:$BD$10000,$J$23) | D28: =SUMIFS('Sales Data'!$L$6:$L$10000,'Sales Data'!$B$6:$B$10000,$D$7,'Sales Data'!$BC$6:$BC$10000,"Feb",'Sales Data'!$BD$6:$BD$10000,$J$23) | E28: =SUMIFS('Sales Data'!$L$6:$L$10000,'Sales Data'!$B$6:$B$10000,$D$7,'Sales Data'!$BC$6:$BC$10000,"Mar",'Sales Data'!$BD$6:$BD$10000,$J$23) | F28: =SUMIFS('Sales Data'!$L$6:$L$10000,'Sales Data'!$B$6:$B$10000,$D$7,'Sales Data'!$BC$6:$BC$10000,"Apr",'Sales Data'!$BD$6:$BD$10000,$J$23) | G28: =SUMIFS('Sales Data'!$L$6:$L$10000,'Sales Data'!$B$6:$B$10000,$D$7,'Sales Data'!$BC$6:$BC$10000,"May",'Sales Data'!$BD$6:$BD$10000,$J$23) | H28: =SUMIFS('Sales Data'!$L$6:$L$10000,'Sales Data'!$B$6:$B$10000,$D$7,'Sales Data'!$BC$6:$BC$10000,"Jun",'Sales Data'!$BD$6:$BD$10000,$J$23) | I28: =SUMIFS('Sales Data'!$L$6:$L$10000,'Sales Data'!$B$6:$B$10000,$D$7,'Sales Data'!$BC$6:$BC$10000,"Jul",'Sales Data'!$BD$6:$BD$10000,$J$23) | J28: =SUMIFS('Sales Data'!$L$6:$L$10000,'Sales Data'!$B$6:$B$10000,$D$7,'Sales Data'!$BC$6:$BC$10000,"Aug",'Sales Data'!$BD$6:$BD$10000,$J$23) | K28: =SUMIFS('Sales Data'!$L$6:$L$10000,'Sales Data'!$B$6:$B$10000,$D$7,'Sales Data'!$BC$6:$BC$10000,"Sep",'Sales Data'!$BD$6:$BD$10000,$J$23) | L28: =SUMIFS('Sales Data'!$L$6:$L$10000,'Sales Data'!$B$6:$B$10000,$D$7,'Sales Data'!$BC$6:$BC$10000,"Oct",'Sales Data'!$BD$6:$BD$10000,$J$23) | M28: =SUMIFS('Sales Data'!$L$6:$L$10000,'Sales Data'!$B$6:$B$10000,$D$7,'Sales Data'!$BC$6:$BC$10000,"Nov",'Sales Data'!$BD$6:$BD$10000,$J$23) | N28: =SUMIFS('Sales Data'!$L$6:$L$10000,'Sales Data'!$B$6:$B$10000,$D$7,'Sales Data'!$BC$6:$BC$10000,"Dec",'Sales Data'!$BD$6:$BD$10000,$J$23) | O28: =SUM(C28:N28)
B29: TACOS | C29: =SUMIFS('Sales Data'!$M$6:$M$10000,'Sales Data'!$B$6:$B$10000,$D$7,'Sales Data'!$BC$6:$BC$10000,"Jan",'Sales Data'!$BD$6:$BD$10000,$J$23) | D29: =SUMIFS('Sales Data'!$M$6:$M$10000,'Sales Data'!$B$6:$B$10000,$D$7,'Sales Data'!$BC$6:$BC$10000,"Feb",'Sales Data'!$BD$6:$BD$10000,$J$23) | E29: =SUMIFS('Sales Data'!$M$6:$M$10000,'Sales Data'!$B$6:$B$10000,$D$7,'Sales Data'!$BC$6:$BC$10000,"Mar",'Sales Data'!$BD$6:$BD$10000,$J$23) | F29: =SUMIFS('Sales Data'!$M$6:$M$10000,'Sales Data'!$B$6:$B$10000,$D$7,'Sales Data'!$BC$6:$BC$10000,"Apr",'Sales Data'!$BD$6:$BD$10000,$J$23) | G29: =SUMIFS('Sales Data'!$M$6:$M$10000,'Sales Data'!$B$6:$B$10000,$D$7,'Sales Data'!$BC$6:$BC$10000,"May",'Sales Data'!$BD$6:$BD$10000,$J$23) | H29: =SUMIFS('Sales Data'!$M$6:$M$10000,'Sales Data'!$B$6:$B$10000,$D$7,'Sales Data'!$BC$6:$BC$10000,"Jun",'Sales Data'!$BD$6:$BD$10000,$J$23) | I29: =SUMIFS('Sales Data'!$M$6:$M$10000,'Sales Data'!$B$6:$B$10000,$D$7,'Sales Data'!$BC$6:$BC$10000,"Jul",'Sales Data'!$BD$6:$BD$10000,$J$23) | J29: =SUMIFS('Sales Data'!$M$6:$M$10000,'Sales Data'!$B$6:$B$10000,$D$7,'Sales Data'!$BC$6:$BC$10000,"Aug",'Sales Data'!$BD$6:$BD$10000,$J$23) | K29: =SUMIFS('Sales Data'!$M$6:$M$10000,'Sales Data'!$B$6:$B$10000,$D$7,'Sales Data'!$BC$6:$BC$10000,"Sep",'Sales Data'!$BD$6:$BD$10000,$J$23) | L29: =SUMIFS('Sales Data'!$M$6:$M$10000,'Sales Data'!$B$6:$B$10000,$D$7,'Sales Data'!$BC$6:$BC$10000,"Oct",'Sales Data'!$BD$6:$BD$10000,$J$23) | M29: =SUMIFS('Sales Data'!$M$6:$M$10000,'Sales Data'!$B$6:$B$10000,$D$7,'Sales Data'!$BC$6:$BC$10000,"Nov",'Sales Data'!$BD$6:$BD$10000,$J$23) | N29: =SUMIFS('Sales Data'!$M$6:$M$10000,'Sales Data'!$B$6:$B$10000,$D$7,'Sales Data'!$BC$6:$BC$10000,"Dec",'Sales Data'!$BD$6:$BD$10000,$J$23) | O29: =IFERROR(AVERAGE(C29:N29),0)
B30: Margin | C30: =SUMIFS('Sales Data'!$P$6:$P$10000,'Sales Data'!$B$6:$B$10000,$D$7,'Sales Data'!$BC$6:$BC$10000,"Jan",'Sales Data'!$BD$6:$BD$10000,$J$23) | D30: =SUMIFS('Sales Data'!$P$6:$P$10000,'Sales Data'!$B$6:$B$10000,$D$7,'Sales Data'!$BC$6:$BC$10000,"Feb",'Sales Data'!$BD$6:$BD$10000,$J$23) | E30: =SUMIFS('Sales Data'!$P$6:$P$10000,'Sales Data'!$B$6:$B$10000,$D$7,'Sales Data'!$BC$6:$BC$10000,"Mar",'Sales Data'!$BD$6:$BD$10000,$J$23) | F30: =SUMIFS('Sales Data'!$P$6:$P$10000,'Sales Data'!$B$6:$B$10000,$D$7,'Sales Data'!$BC$6:$BC$10000,"Apr",'Sales Data'!$BD$6:$BD$10000,$J$23) | G30: =SUMIFS('Sales Data'!$P$6:$P$10000,'Sales Data'!$B$6:$B$10000,$D$7,'Sales Data'!$BC$6:$BC$10000,"May",'Sales Data'!$BD$6:$BD$10000,$J$23) | H30: =SUMIFS('Sales Data'!$P$6:$P$10000,'Sales Data'!$B$6:$B$10000,$D$7,'Sales Data'!$BC$6:$BC$10000,"Jun",'Sales Data'!$BD$6:$BD$10000,$J$23) | I30: =SUMIFS('Sales Data'!$P$6:$P$10000,'Sales Data'!$B$6:$B$10000,$D$7,'Sales Data'!$BC$6:$BC$10000,"Jul",'Sales Data'!$BD$6:$BD$10000,$J$23) | J30: =SUMIFS('Sales Data'!$P$6:$P$10000,'Sales Data'!$B$6:$B$10000,$D$7,'Sales Data'!$BC$6:$BC$10000,"Aug",'Sales Data'!$BD$6:$BD$10000,$J$23) | K30: =SUMIFS('Sales Data'!$P$6:$P$10000,'Sales Data'!$B$6:$B$10000,$D$7,'Sales Data'!$BC$6:$BC$10000,"Sep",'Sales Data'!$BD$6:$BD$10000,$J$23) | L30: =SUMIFS('Sales Data'!$P$6:$P$10000,'Sales Data'!$B$6:$B$10000,$D$7,'Sales Data'!$BC$6:$BC$10000,"Oct",'Sales Data'!$BD$6:$BD$10000,$J$23) | M30: =SUMIFS('Sales Data'!$P$6:$P$10000,'Sales Data'!$B$6:$B$10000,$D$7,'Sales Data'!$BC$6:$BC$10000,"Nov",'Sales Data'!$BD$6:$BD$10000,$J$23) | N30: =SUMIFS('Sales Data'!$P$6:$P$10000,'Sales Data'!$B$6:$B$10000,$D$7,'Sales Data'!$BC$6:$BC$10000,"Dec",'Sales Data'!$BD$6:$BD$10000,$J$23) | O30: =IFERROR(AVERAGE(C30:N30),0)
B33: EXPENSE BREAKDOWN · MAIN & SUB CATEGORY | J33: SALES BREAKDOWN · SUB-CATEGORY
B34: CATEGORY | C34: AMOUNT | D34: % OF EXPENSES | J34: SUB CATEGORY | K34: SALES AMOUNT | L34: % OF SALES
B35: Promo | C35: =IFERROR(SUMIFS('Main Expenses'!$E$6:$E$10000,'Main Expenses'!$B$6:$B$10000,$D$7,'Main Expenses'!$D$6:$D$10000,"Promo",'Main Expenses'!$K$6:$K$10000,$B$7,'Main Expenses'!$L$6:$L$10000,$C$7),0) | D35: =IFERROR(C35/SUMIFS('Main Expenses'!$E$6:$E$10000,'Main Expenses'!$B$6:$B$10000,$D$7,'Main Expenses'!$K$6:$K$10000,$B$7,'Main Expenses'!$L$6:$L$10000,$C$7),0) | J35: Organic | K35: =IFERROR(SUMIFS('Sales Data'!$E$6:$E$10000,'Sales Data'!$B$6:$B$10000,$D$7,'Sales Data'!$D$6:$D$10000,"Organic",'Sales Data'!$BC$6:$BC$10000,$B$7,'Sales Data'!$BD$6:$BD$10000,$C$7),0) | L35: =IFERROR(K35/SUMIFS('Sales Data'!$E$6:$E$10000,'Sales Data'!$B$6:$B$10000,$D$7,'Sales Data'!$BC$6:$BC$10000,$B$7,'Sales Data'!$BD$6:$BD$10000,$C$7),0)
B36: Advertising cost | C36: =IFERROR(SUMIFS('Main Expenses'!$E$6:$E$10000,'Main Expenses'!$B$6:$B$10000,$D$7,'Main Expenses'!$D$6:$D$10000,"Advertising cost",'Main Expenses'!$K$6:$K$10000,$B$7,'Main Expenses'!$L$6:$L$10000,$C$7),0) | D36: =IFERROR(C36/SUMIFS('Main Expenses'!$E$6:$E$10000,'Main Expenses'!$B$6:$B$10000,$D$7,'Main Expenses'!$K$6:$K$10000,$B$7,'Main Expenses'!$L$6:$L$10000,$C$7),0) | J36: Sponsored Products (same day) | K36: =IFERROR(SUMIFS('Sales Data'!$E$6:$E$10000,'Sales Data'!$B$6:$B$10000,$D$7,'Sales Data'!$D$6:$D$10000,"Sponsored Products (same day)",'Sales Data'!$BC$6:$BC$10000,$B$7,'Sales Data'!$BD$6:$BD$10000,$C$7),0) | L36: =IFERROR(K36/SUMIFS('Sales Data'!$E$6:$E$10000,'Sales Data'!$B$6:$B$10000,$D$7,'Sales Data'!$BC$6:$BC$10000,$B$7,'Sales Data'!$BD$6:$BD$10000,$C$7),0)
B37: ↳ Sponsored Brands | C37: =IFERROR(SUMIFS('Sub Expenses'!$E$6:$E$10000,'Sub Expenses'!$B$6:$B$10000,$D$7,'Sub Expenses'!$C$6:$C$10000,"Advertising cost",'Sub Expenses'!$D$6:$D$10000,"Sponsored Brands",'Sub Expenses'!$J$6:$J$10000,$B$7,'Sub Expenses'!$K$6:$K$10000,$C$7),0) | D37: =IFERROR(C37/SUMIFS('Main Expenses'!$E$6:$E$10000,'Main Expenses'!$B$6:$B$10000,$D$7,'Main Expenses'!$K$6:$K$10000,$B$7,'Main Expenses'!$L$6:$L$10000,$C$7),0) | J37: Sponsored Display (same day) | K37: =IFERROR(SUMIFS('Sales Data'!$E$6:$E$10000,'Sales Data'!$B$6:$B$10000,$D$7,'Sales Data'!$D$6:$D$10000,"Sponsored Display (same day)",'Sales Data'!$BC$6:$BC$10000,$B$7,'Sales Data'!$BD$6:$BD$10000,$C$7),0) | L37: =IFERROR(K37/SUMIFS('Sales Data'!$E$6:$E$10000,'Sales Data'!$B$6:$B$10000,$D$7,'Sales Data'!$BC$6:$BC$10000,$B$7,'Sales Data'!$BD$6:$BD$10000,$C$7),0)
B38: ↳ Sponsored Brands Video | C38: =IFERROR(SUMIFS('Sub Expenses'!$E$6:$E$10000,'Sub Expenses'!$B$6:$B$10000,$D$7,'Sub Expenses'!$C$6:$C$10000,"Advertising cost",'Sub Expenses'!$D$6:$D$10000,"Sponsored Brands Video",'Sub Expenses'!$J$6:$J$10000,$B$7,'Sub Expenses'!$K$6:$K$10000,$C$7),0) | D38: =IFERROR(C38/SUMIFS('Main Expenses'!$E$6:$E$10000,'Main Expenses'!$B$6:$B$10000,$D$7,'Main Expenses'!$K$6:$K$10000,$B$7,'Main Expenses'!$L$6:$L$10000,$C$7),0)
B39: ↳ Sponsored Display | C39: =IFERROR(SUMIFS('Sub Expenses'!$E$6:$E$10000,'Sub Expenses'!$B$6:$B$10000,$D$7,'Sub Expenses'!$C$6:$C$10000,"Advertising cost",'Sub Expenses'!$D$6:$D$10000,"Sponsored Display",'Sub Expenses'!$J$6:$J$10000,$B$7,'Sub Expenses'!$K$6:$K$10000,$C$7),0) | D39: =IFERROR(C39/SUMIFS('Main Expenses'!$E$6:$E$10000,'Main Expenses'!$B$6:$B$10000,$D$7,'Main Expenses'!$K$6:$K$10000,$B$7,'Main Expenses'!$L$6:$L$10000,$C$7),0)
B40: ↳ Sponsored Products | C40: =IFERROR(SUMIFS('Sub Expenses'!$E$6:$E$10000,'Sub Expenses'!$B$6:$B$10000,$D$7,'Sub Expenses'!$C$6:$C$10000,"Advertising cost",'Sub Expenses'!$D$6:$D$10000,"Sponsored Products",'Sub Expenses'!$J$6:$J$10000,$B$7,'Sub Expenses'!$K$6:$K$10000,$C$7),0) | D40: =IFERROR(C40/SUMIFS('Main Expenses'!$E$6:$E$10000,'Main Expenses'!$B$6:$B$10000,$D$7,'Main Expenses'!$K$6:$K$10000,$B$7,'Main Expenses'!$L$6:$L$10000,$C$7),0)
B41: Refund cost | C41: =IFERROR(SUMIFS('Main Expenses'!$E$6:$E$10000,'Main Expenses'!$B$6:$B$10000,$D$7,'Main Expenses'!$D$6:$D$10000,"Refund cost",'Main Expenses'!$K$6:$K$10000,$B$7,'Main Expenses'!$L$6:$L$10000,$C$7),0) | D41: =IFERROR(C41/SUMIFS('Main Expenses'!$E$6:$E$10000,'Main Expenses'!$B$6:$B$10000,$D$7,'Main Expenses'!$K$6:$K$10000,$B$7,'Main Expenses'!$L$6:$L$10000,$C$7),0)
B42: ↳ Promotion | C42: =IFERROR(SUMIFS('Sub Expenses'!$E$6:$E$10000,'Sub Expenses'!$B$6:$B$10000,$D$7,'Sub Expenses'!$C$6:$C$10000,"Refund cost",'Sub Expenses'!$D$6:$D$10000,"Promotion",'Sub Expenses'!$J$6:$J$10000,$B$7,'Sub Expenses'!$K$6:$K$10000,$C$7),0) | D42: =IFERROR(C42/SUMIFS('Main Expenses'!$E$6:$E$10000,'Main Expenses'!$B$6:$B$10000,$D$7,'Main Expenses'!$K$6:$K$10000,$B$7,'Main Expenses'!$L$6:$L$10000,$C$7),0)
B43: ↳ Refund commission | C43: =IFERROR(SUMIFS('Sub Expenses'!$E$6:$E$10000,'Sub Expenses'!$B$6:$B$10000,$D$7,'Sub Expenses'!$C$6:$C$10000,"Refund cost",'Sub Expenses'!$D$6:$D$10000,"Refund commission",'Sub Expenses'!$J$6:$J$10000,$B$7,'Sub Expenses'!$K$6:$K$10000,$C$7),0) | D43: =IFERROR(C43/SUMIFS('Main Expenses'!$E$6:$E$10000,'Main Expenses'!$B$6:$B$10000,$D$7,'Main Expenses'!$K$6:$K$10000,$B$7,'Main Expenses'!$L$6:$L$10000,$C$7),0)
B44: ↳ Refunded amount | C44: =IFERROR(SUMIFS('Sub Expenses'!$E$6:$E$10000,'Sub Expenses'!$B$6:$B$10000,$D$7,'Sub Expenses'!$C$6:$C$10000,"Refund cost",'Sub Expenses'!$D$6:$D$10000,"Refunded amount",'Sub Expenses'!$J$6:$J$10000,$B$7,'Sub Expenses'!$K$6:$K$10000,$C$7),0) | D44: =IFERROR(C44/SUMIFS('Main Expenses'!$E$6:$E$10000,'Main Expenses'!$B$6:$B$10000,$D$7,'Main Expenses'!$K$6:$K$10000,$B$7,'Main Expenses'!$L$6:$L$10000,$C$7),0)
B45: ↳ Refunded referral fee | C45: =IFERROR(SUMIFS('Sub Expenses'!$E$6:$E$10000,'Sub Expenses'!$B$6:$B$10000,$D$7,'Sub Expenses'!$C$6:$C$10000,"Refund cost",'Sub Expenses'!$D$6:$D$10000,"Refunded referral fee",'Sub Expenses'!$J$6:$J$10000,$B$7,'Sub Expenses'!$K$6:$K$10000,$C$7),0) | D45: =IFERROR(C45/SUMIFS('Main Expenses'!$E$6:$E$10000,'Main Expenses'!$B$6:$B$10000,$D$7,'Main Expenses'!$K$6:$K$10000,$B$7,'Main Expenses'!$L$6:$L$10000,$C$7),0)
B46: ↳ Restocking Deduction Principal | C46: =IFERROR(SUMIFS('Sub Expenses'!$E$6:$E$10000,'Sub Expenses'!$B$6:$B$10000,$D$7,'Sub Expenses'!$C$6:$C$10000,"Refund cost",'Sub Expenses'!$D$6:$D$10000,"Restocking Deduction Principal",'Sub Expenses'!$J$6:$J$10000,$B$7,'Sub Expenses'!$K$6:$K$10000,$C$7),0) | D46: =IFERROR(C46/SUMIFS('Main Expenses'!$E$6:$E$10000,'Main Expenses'!$B$6:$B$10000,$D$7,'Main Expenses'!$K$6:$K$10000,$B$7,'Main Expenses'!$L$6:$L$10000,$C$7),0)
B47: ↳ Value of returned items | C47: =IFERROR(SUMIFS('Sub Expenses'!$E$6:$E$10000,'Sub Expenses'!$B$6:$B$10000,$D$7,'Sub Expenses'!$C$6:$C$10000,"Refund cost",'Sub Expenses'!$D$6:$D$10000,"Value of returned items",'Sub Expenses'!$J$6:$J$10000,$B$7,'Sub Expenses'!$K$6:$K$10000,$C$7),0) | D47: =IFERROR(C47/SUMIFS('Main Expenses'!$E$6:$E$10000,'Main Expenses'!$B$6:$B$10000,$D$7,'Main Expenses'!$K$6:$K$10000,$B$7,'Main Expenses'!$L$6:$L$10000,$C$7),0)
B48: Amazon fees | C48: =IFERROR(SUMIFS('Main Expenses'!$E$6:$E$10000,'Main Expenses'!$B$6:$B$10000,$D$7,'Main Expenses'!$D$6:$D$10000,"Amazon fees",'Main Expenses'!$K$6:$K$10000,$B$7,'Main Expenses'!$L$6:$L$10000,$C$7),0) | D48: =IFERROR(C48/SUMIFS('Main Expenses'!$E$6:$E$10000,'Main Expenses'!$B$6:$B$10000,$D$7,'Main Expenses'!$K$6:$K$10000,$B$7,'Main Expenses'!$L$6:$L$10000,$C$7),0)
B49: ↳ AWD processing fee | C49: =IFERROR(SUMIFS('Sub Expenses'!$E$6:$E$10000,'Sub Expenses'!$B$6:$B$10000,$D$7,'Sub Expenses'!$C$6:$C$10000,"Amazon fees",'Sub Expenses'!$D$6:$D$10000,"AWD processing fee",'Sub Expenses'!$J$6:$J$10000,$B$7,'Sub Expenses'!$K$6:$K$10000,$C$7),0) | D49: =IFERROR(C49/SUMIFS('Main Expenses'!$E$6:$E$10000,'Main Expenses'!$B$6:$B$10000,$D$7,'Main Expenses'!$K$6:$K$10000,$B$7,'Main Expenses'!$L$6:$L$10000,$C$7),0)
B50: ↳ AWD storage fees | C50: =IFERROR(SUMIFS('Sub Expenses'!$E$6:$E$10000,'Sub Expenses'!$B$6:$B$10000,$D$7,'Sub Expenses'!$C$6:$C$10000,"Amazon fees",'Sub Expenses'!$D$6:$D$10000,"AWD storage fees",'Sub Expenses'!$J$6:$J$10000,$B$7,'Sub Expenses'!$K$6:$K$10000,$C$7),0) | D50: =IFERROR(C50/SUMIFS('Main Expenses'!$E$6:$E$10000,'Main Expenses'!$B$6:$B$10000,$D$7,'Main Expenses'!$K$6:$K$10000,$B$7,'Main Expenses'!$L$6:$L$10000,$C$7),0)
B51: ↳ AWD transportation fee | C51: =IFERROR(SUMIFS('Sub Expenses'!$E$6:$E$10000,'Sub Expenses'!$B$6:$B$10000,$D$7,'Sub Expenses'!$C$6:$C$10000,"Amazon fees",'Sub Expenses'!$D$6:$D$10000,"AWD transportation fee",'Sub Expenses'!$J$6:$J$10000,$B$7,'Sub Expenses'!$K$6:$K$10000,$C$7),0) | D51: =IFERROR(C51/SUMIFS('Main Expenses'!$E$6:$E$10000,'Main Expenses'!$B$6:$B$10000,$D$7,'Main Expenses'!$K$6:$K$10000,$B$7,'Main Expenses'!$L$6:$L$10000,$C$7),0)
B52: ↳ Adjustment FBA per unit fulfillment fee | C52: =IFERROR(SUMIFS('Sub Expenses'!$E$6:$E$10000,'Sub Expenses'!$B$6:$B$10000,$D$7,'Sub Expenses'!$C$6:$C$10000,"Amazon fees",'Sub Expenses'!$D$6:$D$10000,"Adjustment FBA per unit fulfillment fee ",'Sub Expenses'!$J$6:$J$10000,$B$7,'Sub Expenses'!$K$6:$K$10000,$C$7),0) | D52: =IFERROR(C52/SUMIFS('Main Expenses'!$E$6:$E$10000,'Main Expenses'!$B$6:$B$10000,$D$7,'Main Expenses'!$K$6:$K$10000,$B$7,'Main Expenses'!$L$6:$L$10000,$C$7),0)
B53: ↳ Compensated clawback | C53: =IFERROR(SUMIFS('Sub Expenses'!$E$6:$E$10000,'Sub Expenses'!$B$6:$B$10000,$D$7,'Sub Expenses'!$C$6:$C$10000,"Amazon fees",'Sub Expenses'!$D$6:$D$10000,"Compensated clawback",'Sub Expenses'!$J$6:$J$10000,$B$7,'Sub Expenses'!$K$6:$K$10000,$C$7),0) | D53: =IFERROR(C53/SUMIFS('Main Expenses'!$E$6:$E$10000,'Main Expenses'!$B$6:$B$10000,$D$7,'Main Expenses'!$K$6:$K$10000,$B$7,'Main Expenses'!$L$6:$L$10000,$C$7),0)
B54: ↳ Coupon participation fee rollup | C54: =IFERROR(SUMIFS('Sub Expenses'!$E$6:$E$10000,'Sub Expenses'!$B$6:$B$10000,$D$7,'Sub Expenses'!$C$6:$C$10000,"Amazon fees",'Sub Expenses'!$D$6:$D$10000,"Coupon participation fee rollup",'Sub Expenses'!$J$6:$J$10000,$B$7,'Sub Expenses'!$K$6:$K$10000,$C$7),0) | D54: =IFERROR(C54/SUMIFS('Main Expenses'!$E$6:$E$10000,'Main Expenses'!$B$6:$B$10000,$D$7,'Main Expenses'!$K$6:$K$10000,$B$7,'Main Expenses'!$L$6:$L$10000,$C$7),0)
B55: ↳ Coupon performance fee rollup | C55: =IFERROR(SUMIFS('Sub Expenses'!$E$6:$E$10000,'Sub Expenses'!$B$6:$B$10000,$D$7,'Sub Expenses'!$C$6:$C$10000,"Amazon fees",'Sub Expenses'!$D$6:$D$10000,"Coupon performance fee rollup",'Sub Expenses'!$J$6:$J$10000,$B$7,'Sub Expenses'!$K$6:$K$10000,$C$7),0) | D55: =IFERROR(C55/SUMIFS('Main Expenses'!$E$6:$E$10000,'Main Expenses'!$B$6:$B$10000,$D$7,'Main Expenses'!$K$6:$K$10000,$B$7,'Main Expenses'!$L$6:$L$10000,$C$7),0)
B56: ↳ Customer Return HRR Unit Fee | C56: =IFERROR(SUMIFS('Sub Expenses'!$E$6:$E$10000,'Sub Expenses'!$B$6:$B$10000,$D$7,'Sub Expenses'!$C$6:$C$10000,"Amazon fees",'Sub Expenses'!$D$6:$D$10000,"Customer Return HRR Unit Fee",'Sub Expenses'!$J$6:$J$10000,$B$7,'Sub Expenses'!$K$6:$K$10000,$C$7),0) | D56: =IFERROR(C56/SUMIFS('Main Expenses'!$E$6:$E$10000,'Main Expenses'!$B$6:$B$10000,$D$7,'Main Expenses'!$K$6:$K$10000,$B$7,'Main Expenses'!$L$6:$L$10000,$C$7),0)
B57: ↳ Deal participation fee rollup | C57: =IFERROR(SUMIFS('Sub Expenses'!$E$6:$E$10000,'Sub Expenses'!$B$6:$B$10000,$D$7,'Sub Expenses'!$C$6:$C$10000,"Amazon fees",'Sub Expenses'!$D$6:$D$10000,"Deal participation fee rollup ",'Sub Expenses'!$J$6:$J$10000,$B$7,'Sub Expenses'!$K$6:$K$10000,$C$7),0) | D57: =IFERROR(C57/SUMIFS('Main Expenses'!$E$6:$E$10000,'Main Expenses'!$B$6:$B$10000,$D$7,'Main Expenses'!$K$6:$K$10000,$B$7,'Main Expenses'!$L$6:$L$10000,$C$7),0)
B58: ↳ FBA disposal fee | C58: =IFERROR(SUMIFS('Sub Expenses'!$E$6:$E$10000,'Sub Expenses'!$B$6:$B$10000,$D$7,'Sub Expenses'!$C$6:$C$10000,"Amazon fees",'Sub Expenses'!$D$6:$D$10000,"FBA disposal fee",'Sub Expenses'!$J$6:$J$10000,$B$7,'Sub Expenses'!$K$6:$K$10000,$C$7),0) | D58: =IFERROR(C58/SUMIFS('Main Expenses'!$E$6:$E$10000,'Main Expenses'!$B$6:$B$10000,$D$7,'Main Expenses'!$K$6:$K$10000,$B$7,'Main Expenses'!$L$6:$L$10000,$C$7),0)
B59: ↳ FBA inbound convenience fee | C59: =IFERROR(SUMIFS('Sub Expenses'!$E$6:$E$10000,'Sub Expenses'!$B$6:$B$10000,$D$7,'Sub Expenses'!$C$6:$C$10000,"Amazon fees",'Sub Expenses'!$D$6:$D$10000,"FBA inbound convenience fee",'Sub Expenses'!$J$6:$J$10000,$B$7,'Sub Expenses'!$K$6:$K$10000,$C$7),0) | D59: =IFERROR(C59/SUMIFS('Main Expenses'!$E$6:$E$10000,'Main Expenses'!$B$6:$B$10000,$D$7,'Main Expenses'!$K$6:$K$10000,$B$7,'Main Expenses'!$L$6:$L$10000,$C$7),0)
B60: ↳ FBA inbound defect fee | C60: =IFERROR(SUMIFS('Sub Expenses'!$E$6:$E$10000,'Sub Expenses'!$B$6:$B$10000,$D$7,'Sub Expenses'!$C$6:$C$10000,"Amazon fees",'Sub Expenses'!$D$6:$D$10000,"FBA inbound defect fee",'Sub Expenses'!$J$6:$J$10000,$B$7,'Sub Expenses'!$K$6:$K$10000,$C$7),0) | D60: =IFERROR(C60/SUMIFS('Main Expenses'!$E$6:$E$10000,'Main Expenses'!$B$6:$B$10000,$D$7,'Main Expenses'!$K$6:$K$10000,$B$7,'Main Expenses'!$L$6:$L$10000,$C$7),0)
B61: ↳ FBA per unit fulfilment fee | C61: =IFERROR(SUMIFS('Sub Expenses'!$E$6:$E$10000,'Sub Expenses'!$B$6:$B$10000,$D$7,'Sub Expenses'!$C$6:$C$10000,"Amazon fees",'Sub Expenses'!$D$6:$D$10000,"FBA per unit fulfilment fee",'Sub Expenses'!$J$6:$J$10000,$B$7,'Sub Expenses'!$K$6:$K$10000,$C$7),0) | D61: =IFERROR(C61/SUMIFS('Main Expenses'!$E$6:$E$10000,'Main Expenses'!$B$6:$B$10000,$D$7,'Main Expenses'!$K$6:$K$10000,$B$7,'Main Expenses'!$L$6:$L$10000,$C$7),0)
B62: ↳ FBA removal fee | C62: =IFERROR(SUMIFS('Sub Expenses'!$E$6:$E$10000,'Sub Expenses'!$B$6:$B$10000,$D$7,'Sub Expenses'!$C$6:$C$10000,"Amazon fees",'Sub Expenses'!$D$6:$D$10000,"FBA removal fee",'Sub Expenses'!$J$6:$J$10000,$B$7,'Sub Expenses'!$K$6:$K$10000,$C$7),0) | D62: =IFERROR(C62/SUMIFS('Main Expenses'!$E$6:$E$10000,'Main Expenses'!$B$6:$B$10000,$D$7,'Main Expenses'!$K$6:$K$10000,$B$7,'Main Expenses'!$L$6:$L$10000,$C$7),0)
B63: ↳ FBA storage fee | C63: =IFERROR(SUMIFS('Sub Expenses'!$E$6:$E$10000,'Sub Expenses'!$B$6:$B$10000,$D$7,'Sub Expenses'!$C$6:$C$10000,"Amazon fees",'Sub Expenses'!$D$6:$D$10000,"FBA storage fee",'Sub Expenses'!$J$6:$J$10000,$B$7,'Sub Expenses'!$K$6:$K$10000,$C$7),0) | D63: =IFERROR(C63/SUMIFS('Main Expenses'!$E$6:$E$10000,'Main Expenses'!$B$6:$B$10000,$D$7,'Main Expenses'!$K$6:$K$10000,$B$7,'Main Expenses'!$L$6:$L$10000,$C$7),0)
B64: ↳ Free replacement refund items | C64: =IFERROR(SUMIFS('Sub Expenses'!$E$6:$E$10000,'Sub Expenses'!$B$6:$B$10000,$D$7,'Sub Expenses'!$C$6:$C$10000,"Amazon fees",'Sub Expenses'!$D$6:$D$10000,"Free replacement refund items",'Sub Expenses'!$J$6:$J$10000,$B$7,'Sub Expenses'!$K$6:$K$10000,$C$7),0) | D64: =IFERROR(C64/SUMIFS('Main Expenses'!$E$6:$E$10000,'Main Expenses'!$B$6:$B$10000,$D$7,'Main Expenses'!$K$6:$K$10000,$B$7,'Main Expenses'!$L$6:$L$10000,$C$7),0)
B65: ↳ Get paid faster fee | C65: =IFERROR(SUMIFS('Sub Expenses'!$E$6:$E$10000,'Sub Expenses'!$B$6:$B$10000,$D$7,'Sub Expenses'!$C$6:$C$10000,"Amazon fees",'Sub Expenses'!$D$6:$D$10000,"Get paid faster fee",'Sub Expenses'!$J$6:$J$10000,$B$7,'Sub Expenses'!$K$6:$K$10000,$C$7),0) | D65: =IFERROR(C65/SUMIFS('Main Expenses'!$E$6:$E$10000,'Main Expenses'!$B$6:$B$10000,$D$7,'Main Expenses'!$K$6:$K$10000,$B$7,'Main Expenses'!$L$6:$L$10000,$C$7),0)
B66: ↳ Hrr non apparel rollup | C66: =IFERROR(SUMIFS('Sub Expenses'!$E$6:$E$10000,'Sub Expenses'!$B$6:$B$10000,$D$7,'Sub Expenses'!$C$6:$C$10000,"Amazon fees",'Sub Expenses'!$D$6:$D$10000,"Hrr non apparel rollup",'Sub Expenses'!$J$6:$J$10000,$B$7,'Sub Expenses'!$K$6:$K$10000,$C$7),0) | D66: =IFERROR(C66/SUMIFS('Main Expenses'!$E$6:$E$10000,'Main Expenses'!$B$6:$B$10000,$D$7,'Main Expenses'!$K$6:$K$10000,$B$7,'Main Expenses'!$L$6:$L$10000,$C$7),0)
B67: ↳ Inbound transportation | C67: =IFERROR(SUMIFS('Sub Expenses'!$E$6:$E$10000,'Sub Expenses'!$B$6:$B$10000,$D$7,'Sub Expenses'!$C$6:$C$10000,"Amazon fees",'Sub Expenses'!$D$6:$D$10000,"Inbound transportation ",'Sub Expenses'!$J$6:$J$10000,$B$7,'Sub Expenses'!$K$6:$K$10000,$C$7),0) | D67: =IFERROR(C67/SUMIFS('Main Expenses'!$E$6:$E$10000,'Main Expenses'!$B$6:$B$10000,$D$7,'Main Expenses'!$K$6:$K$10000,$B$7,'Main Expenses'!$L$6:$L$10000,$C$7),0)
B68: ↳ Labeling fee | C68: =IFERROR(SUMIFS('Sub Expenses'!$E$6:$E$10000,'Sub Expenses'!$B$6:$B$10000,$D$7,'Sub Expenses'!$C$6:$C$10000,"Amazon fees",'Sub Expenses'!$D$6:$D$10000,"Labeling fee ",'Sub Expenses'!$J$6:$J$10000,$B$7,'Sub Expenses'!$K$6:$K$10000,$C$7),0) | D68: =IFERROR(C68/SUMIFS('Main Expenses'!$E$6:$E$10000,'Main Expenses'!$B$6:$B$10000,$D$7,'Main Expenses'!$K$6:$K$10000,$B$7,'Main Expenses'!$L$6:$L$10000,$C$7),0)
B69: ↳ Liquidations brokerage fee | C69: =IFERROR(SUMIFS('Sub Expenses'!$E$6:$E$10000,'Sub Expenses'!$B$6:$B$10000,$D$7,'Sub Expenses'!$C$6:$C$10000,"Amazon fees",'Sub Expenses'!$D$6:$D$10000,"Liquidations brokerage fee",'Sub Expenses'!$J$6:$J$10000,$B$7,'Sub Expenses'!$K$6:$K$10000,$C$7),0) | D69: =IFERROR(C69/SUMIFS('Main Expenses'!$E$6:$E$10000,'Main Expenses'!$B$6:$B$10000,$D$7,'Main Expenses'!$K$6:$K$10000,$B$7,'Main Expenses'!$L$6:$L$10000,$C$7),0)
B70: ↳ Liquidations revenue | C70: =IFERROR(SUMIFS('Sub Expenses'!$E$6:$E$10000,'Sub Expenses'!$B$6:$B$10000,$D$7,'Sub Expenses'!$C$6:$C$10000,"Amazon fees",'Sub Expenses'!$D$6:$D$10000,"Liquidations revenue",'Sub Expenses'!$J$6:$J$10000,$B$7,'Sub Expenses'!$K$6:$K$10000,$C$7),0) | D70: =IFERROR(C70/SUMIFS('Main Expenses'!$E$6:$E$10000,'Main Expenses'!$B$6:$B$10000,$D$7,'Main Expenses'!$K$6:$K$10000,$B$7,'Main Expenses'!$L$6:$L$10000,$C$7),0)
B71: ↳ Liquidations revenue adjustment | C71: =IFERROR(SUMIFS('Sub Expenses'!$E$6:$E$10000,'Sub Expenses'!$B$6:$B$10000,$D$7,'Sub Expenses'!$C$6:$C$10000,"Amazon fees",'Sub Expenses'!$D$6:$D$10000,"Liquidations revenue adjustment",'Sub Expenses'!$J$6:$J$10000,$B$7,'Sub Expenses'!$K$6:$K$10000,$C$7),0) | D71: =IFERROR(C71/SUMIFS('Main Expenses'!$E$6:$E$10000,'Main Expenses'!$B$6:$B$10000,$D$7,'Main Expenses'!$K$6:$K$10000,$B$7,'Main Expenses'!$L$6:$L$10000,$C$7),0)
B72: ↳ Long term storage fee | C72: =IFERROR(SUMIFS('Sub Expenses'!$E$6:$E$10000,'Sub Expenses'!$B$6:$B$10000,$D$7,'Sub Expenses'!$C$6:$C$10000,"Amazon fees",'Sub Expenses'!$D$6:$D$10000,"Long term storage fee",'Sub Expenses'!$J$6:$J$10000,$B$7,'Sub Expenses'!$K$6:$K$10000,$C$7),0) | D72: =IFERROR(C72/SUMIFS('Main Expenses'!$E$6:$E$10000,'Main Expenses'!$B$6:$B$10000,$D$7,'Main Expenses'!$K$6:$K$10000,$B$7,'Main Expenses'!$L$6:$L$10000,$C$7),0)
B73: ↳ Missing from inbound | C73: =IFERROR(SUMIFS('Sub Expenses'!$E$6:$E$10000,'Sub Expenses'!$B$6:$B$10000,$D$7,'Sub Expenses'!$C$6:$C$10000,"Amazon fees",'Sub Expenses'!$D$6:$D$10000,"Missing from inbound",'Sub Expenses'!$J$6:$J$10000,$B$7,'Sub Expenses'!$K$6:$K$10000,$C$7),0) | D73: =IFERROR(C73/SUMIFS('Main Expenses'!$E$6:$E$10000,'Main Expenses'!$B$6:$B$10000,$D$7,'Main Expenses'!$K$6:$K$10000,$B$7,'Main Expenses'!$L$6:$L$10000,$C$7),0)
B74: ↳ Missing from inbound clawback | C74: =IFERROR(SUMIFS('Sub Expenses'!$E$6:$E$10000,'Sub Expenses'!$B$6:$B$10000,$D$7,'Sub Expenses'!$C$6:$C$10000,"Amazon fees",'Sub Expenses'!$D$6:$D$10000,"Missing from inbound clawback",'Sub Expenses'!$J$6:$J$10000,$B$7,'Sub Expenses'!$K$6:$K$10000,$C$7),0) | D74: =IFERROR(C74/SUMIFS('Main Expenses'!$E$6:$E$10000,'Main Expenses'!$B$6:$B$10000,$D$7,'Main Expenses'!$K$6:$K$10000,$B$7,'Main Expenses'!$L$6:$L$10000,$C$7),0)
B75: ↳ Re commerce grading and listing charge | C75: =IFERROR(SUMIFS('Sub Expenses'!$E$6:$E$10000,'Sub Expenses'!$B$6:$B$10000,$D$7,'Sub Expenses'!$C$6:$C$10000,"Amazon fees",'Sub Expenses'!$D$6:$D$10000,"Re commerce grading and listing charge",'Sub Expenses'!$J$6:$J$10000,$B$7,'Sub Expenses'!$K$6:$K$10000,$C$7),0) | D75: =IFERROR(C75/SUMIFS('Main Expenses'!$E$6:$E$10000,'Main Expenses'!$B$6:$B$10000,$D$7,'Main Expenses'!$K$6:$K$10000,$B$7,'Main Expenses'!$L$6:$L$10000,$C$7),0)
B76: ↳ Re-evaluation | C76: =IFERROR(SUMIFS('Sub Expenses'!$E$6:$E$10000,'Sub Expenses'!$B$6:$B$10000,$D$7,'Sub Expenses'!$C$6:$C$10000,"Amazon fees",'Sub Expenses'!$D$6:$D$10000,"Re-evaluation",'Sub Expenses'!$J$6:$J$10000,$B$7,'Sub Expenses'!$K$6:$K$10000,$C$7),0) | D76: =IFERROR(C76/SUMIFS('Main Expenses'!$E$6:$E$10000,'Main Expenses'!$B$6:$B$10000,$D$7,'Main Expenses'!$K$6:$K$10000,$B$7,'Main Expenses'!$L$6:$L$10000,$C$7),0)
B77: ↳ Referral fee | C77: =IFERROR(SUMIFS('Sub Expenses'!$E$6:$E$10000,'Sub Expenses'!$B$6:$B$10000,$D$7,'Sub Expenses'!$C$6:$C$10000,"Amazon fees",'Sub Expenses'!$D$6:$D$10000,"Referral fee",'Sub Expenses'!$J$6:$J$10000,$B$7,'Sub Expenses'!$K$6:$K$10000,$C$7),0) | D77: =IFERROR(C77/SUMIFS('Main Expenses'!$E$6:$E$10000,'Main Expenses'!$B$6:$B$10000,$D$7,'Main Expenses'!$K$6:$K$10000,$B$7,'Main Expenses'!$L$6:$L$10000,$C$7),0)
B78: ↳ Reversal reimbursement | C78: =IFERROR(SUMIFS('Sub Expenses'!$E$6:$E$10000,'Sub Expenses'!$B$6:$B$10000,$D$7,'Sub Expenses'!$C$6:$C$10000,"Amazon fees",'Sub Expenses'!$D$6:$D$10000,"Reversal reimbursement",'Sub Expenses'!$J$6:$J$10000,$B$7,'Sub Expenses'!$K$6:$K$10000,$C$7),0) | D78: =IFERROR(C78/SUMIFS('Main Expenses'!$E$6:$E$10000,'Main Expenses'!$B$6:$B$10000,$D$7,'Main Expenses'!$K$6:$K$10000,$B$7,'Main Expenses'!$L$6:$L$10000,$C$7),0)
B79: ↳ Sponsored Products | C79: =IFERROR(SUMIFS('Sub Expenses'!$E$6:$E$10000,'Sub Expenses'!$B$6:$B$10000,$D$7,'Sub Expenses'!$C$6:$C$10000,"Amazon fees",'Sub Expenses'!$D$6:$D$10000,"Sponsored Products",'Sub Expenses'!$J$6:$J$10000,$B$7,'Sub Expenses'!$K$6:$K$10000,$C$7),0) | D79: =IFERROR(C79/SUMIFS('Main Expenses'!$E$6:$E$10000,'Main Expenses'!$B$6:$B$10000,$D$7,'Main Expenses'!$K$6:$K$10000,$B$7,'Main Expenses'!$L$6:$L$10000,$C$7),0)
B80: ↳ Star storage fee | C80: =IFERROR(SUMIFS('Sub Expenses'!$E$6:$E$10000,'Sub Expenses'!$B$6:$B$10000,$D$7,'Sub Expenses'!$C$6:$C$10000,"Amazon fees",'Sub Expenses'!$D$6:$D$10000,"Star storage fee",'Sub Expenses'!$J$6:$J$10000,$B$7,'Sub Expenses'!$K$6:$K$10000,$C$7),0) | D80: =IFERROR(C80/SUMIFS('Main Expenses'!$E$6:$E$10000,'Main Expenses'!$B$6:$B$10000,$D$7,'Main Expenses'!$K$6:$K$10000,$B$7,'Main Expenses'!$L$6:$L$10000,$C$7),0)
B81: ↳ Subscription | C81: =IFERROR(SUMIFS('Sub Expenses'!$E$6:$E$10000,'Sub Expenses'!$B$6:$B$10000,$D$7,'Sub Expenses'!$C$6:$C$10000,"Amazon fees",'Sub Expenses'!$D$6:$D$10000,"Subscription",'Sub Expenses'!$J$6:$J$10000,$B$7,'Sub Expenses'!$K$6:$K$10000,$C$7),0) | D81: =IFERROR(C81/SUMIFS('Main Expenses'!$E$6:$E$10000,'Main Expenses'!$B$6:$B$10000,$D$7,'Main Expenses'!$K$6:$K$10000,$B$7,'Main Expenses'!$L$6:$L$10000,$C$7),0)
B82: ↳ Vine Fee | C82: =IFERROR(SUMIFS('Sub Expenses'!$E$6:$E$10000,'Sub Expenses'!$B$6:$B$10000,$D$7,'Sub Expenses'!$C$6:$C$10000,"Amazon fees",'Sub Expenses'!$D$6:$D$10000,"Vine Fee",'Sub Expenses'!$J$6:$J$10000,$B$7,'Sub Expenses'!$K$6:$K$10000,$C$7),0) | D82: =IFERROR(C82/SUMIFS('Main Expenses'!$E$6:$E$10000,'Main Expenses'!$B$6:$B$10000,$D$7,'Main Expenses'!$K$6:$K$10000,$B$7,'Main Expenses'!$L$6:$L$10000,$C$7),0)
B83: ↳ Warehouse damage | C83: =IFERROR(SUMIFS('Sub Expenses'!$E$6:$E$10000,'Sub Expenses'!$B$6:$B$10000,$D$7,'Sub Expenses'!$C$6:$C$10000,"Amazon fees",'Sub Expenses'!$D$6:$D$10000,"Warehouse damage",'Sub Expenses'!$J$6:$J$10000,$B$7,'Sub Expenses'!$K$6:$K$10000,$C$7),0) | D83: =IFERROR(C83/SUMIFS('Main Expenses'!$E$6:$E$10000,'Main Expenses'!$B$6:$B$10000,$D$7,'Main Expenses'!$K$6:$K$10000,$B$7,'Main Expenses'!$L$6:$L$10000,$C$7),0)
B84: ↳ Warehouse damage exception | C84: =IFERROR(SUMIFS('Sub Expenses'!$E$6:$E$10000,'Sub Expenses'!$B$6:$B$10000,$D$7,'Sub Expenses'!$C$6:$C$10000,"Amazon fees",'Sub Expenses'!$D$6:$D$10000,"Warehouse damage exception",'Sub Expenses'!$J$6:$J$10000,$B$7,'Sub Expenses'!$K$6:$K$10000,$C$7),0) | D84: =IFERROR(C84/SUMIFS('Main Expenses'!$E$6:$E$10000,'Main Expenses'!$B$6:$B$10000,$D$7,'Main Expenses'!$K$6:$K$10000,$B$7,'Main Expenses'!$L$6:$L$10000,$C$7),0)
B85: ↳ Warehouse lost | C85: =IFERROR(SUMIFS('Sub Expenses'!$E$6:$E$10000,'Sub Expenses'!$B$6:$B$10000,$D$7,'Sub Expenses'!$C$6:$C$10000,"Amazon fees",'Sub Expenses'!$D$6:$D$10000,"Warehouse lost",'Sub Expenses'!$J$6:$J$10000,$B$7,'Sub Expenses'!$K$6:$K$10000,$C$7),0) | D85: =IFERROR(C85/SUMIFS('Main Expenses'!$E$6:$E$10000,'Main Expenses'!$B$6:$B$10000,$D$7,'Main Expenses'!$K$6:$K$10000,$B$7,'Main Expenses'!$L$6:$L$10000,$C$7),0)
B86: Cost of goods | C86: =IFERROR(SUMIFS('Main Expenses'!$E$6:$E$10000,'Main Expenses'!$B$6:$B$10000,$D$7,'Main Expenses'!$D$6:$D$10000,"Cost of goods",'Main Expenses'!$K$6:$K$10000,$B$7,'Main Expenses'!$L$6:$L$10000,$C$7),0) | D86: =IFERROR(C86/SUMIFS('Main Expenses'!$E$6:$E$10000,'Main Expenses'!$B$6:$B$10000,$D$7,'Main Expenses'!$K$6:$K$10000,$B$7,'Main Expenses'!$L$6:$L$10000,$C$7),0)
B87: ↳ Cost of goods sold | C87: =IFERROR(SUMIFS('Sub Expenses'!$E$6:$E$10000,'Sub Expenses'!$B$6:$B$10000,$D$7,'Sub Expenses'!$C$6:$C$10000,"Cost of goods",'Sub Expenses'!$D$6:$D$10000,"Cost of goods sold",'Sub Expenses'!$J$6:$J$10000,$B$7,'Sub Expenses'!$K$6:$K$10000,$C$7),0) | D87: =IFERROR(C87/SUMIFS('Main Expenses'!$E$6:$E$10000,'Main Expenses'!$B$6:$B$10000,$D$7,'Main Expenses'!$K$6:$K$10000,$B$7,'Main Expenses'!$L$6:$L$10000,$C$7),0)
B88: ↳ Lost/damaged by Amazon | C88: =IFERROR(SUMIFS('Sub Expenses'!$E$6:$E$10000,'Sub Expenses'!$B$6:$B$10000,$D$7,'Sub Expenses'!$C$6:$C$10000,"Cost of goods",'Sub Expenses'!$D$6:$D$10000,"Lost/damaged by Amazon",'Sub Expenses'!$J$6:$J$10000,$B$7,'Sub Expenses'!$K$6:$K$10000,$C$7),0) | D88: =IFERROR(C88/SUMIFS('Main Expenses'!$E$6:$E$10000,'Main Expenses'!$B$6:$B$10000,$D$7,'Main Expenses'!$K$6:$K$10000,$B$7,'Main Expenses'!$L$6:$L$10000,$C$7),0)
B89: TOTAL EXPENSES | C89: =SUMIFS('Main Expenses'!$E$6:$E$10000,'Main Expenses'!$B$6:$B$10000,$D$7,'Main Expenses'!$K$6:$K$10000,$B$7,'Main Expenses'!$L$6:$L$10000,$C$7) | D89: 1 | J89: TOTAL SALES | K89: =SUMIFS('Sales Data'!$E$6:$E$10000,'Sales Data'!$B$6:$B$10000,$D$7,'Sales Data'!$BC$6:$BC$10000,$B$7,'Sales Data'!$BD$6:$BD$10000,$C$7) | L89: 1

Sheet TikTok Dashboard
B2: TIKTOK SHOP DASHBOARD
B3: Click the + symbol on the left margin to expand sub-categories · all KPIs update live via SUMIFS formulas.
B6: MONTH | C6: YEAR | D6: CATEGORY
B7: Mar | C7: 2026 | D7: All Categories
B9: KEY METRICS
B11: NET SALES | D11: =SUMIFS('Sales Data'!$R$6:$R$10000,'Sales Data'!$B$6:$B$10000,"Tiktok",'Sales Data'!$BC$6:$BC$10000,$B$7,'Sales Data'!$BD$6:$BD$10000,$C$7)
B12: UNIT SALES | D12: =SUMIFS('Sales Data'!$G$6:$G$10000,'Sales Data'!$B$6:$B$10000,"Tiktok",'Sales Data'!$BC$6:$BC$10000,$B$7,'Sales Data'!$BD$6:$BD$10000,$C$7)
B13: TIKTOK SHIPPING | D13: =SUMIFS('Sales Data'!$S$6:$S$10000,'Sales Data'!$B$6:$B$10000,"Tiktok",'Sales Data'!$BC$6:$BC$10000,$B$7,'Sales Data'!$BD$6:$BD$10000,$C$7)
B14: MCF SHIPPING FEES | D14: =SUMIFS('Sales Data'!$U$6:$U$10000,'Sales Data'!$B$6:$B$10000,"Tiktok",'Sales Data'!$BC$6:$BC$10000,$B$7,'Sales Data'!$BD$6:$BD$10000,$C$7)
B15: 3PL LABEL COST | D15: =SUMIFS('Sales Data'!$T$6:$T$10000,'Sales Data'!$B$6:$B$10000,"Tiktok",'Sales Data'!$BC$6:$BC$10000,$B$7,'Sales Data'!$BD$6:$BD$10000,$C$7)
B16: FEES | D16: =SUMIFS('Sales Data'!$V$6:$V$10000,'Sales Data'!$B$6:$B$10000,"Tiktok",'Sales Data'!$BC$6:$BC$10000,$B$7,'Sales Data'!$BD$6:$BD$10000,$C$7)
B17: REFERRAL FEE | D17: =SUMIFS('Sales Data'!$W$6:$W$10000,'Sales Data'!$B$6:$B$10000,"Tiktok",'Sales Data'!$BC$6:$BC$10000,$B$7,'Sales Data'!$BD$6:$BD$10000,$C$7)
B18: AFFILIATE COMMISSION | D18: =SUMIFS('Sales Data'!$X$6:$X$10000,'Sales Data'!$B$6:$B$10000,"Tiktok",'Sales Data'!$BC$6:$BC$10000,$B$7,'Sales Data'!$BD$6:$BD$10000,$C$7)
B19: ADJUSTMENTS | D19: =SUMIFS('Sales Data'!$Y$6:$Y$10000,'Sales Data'!$B$6:$B$10000,"Tiktok",'Sales Data'!$BC$6:$BC$10000,$B$7,'Sales Data'!$BD$6:$BD$10000,$C$7)
B20: COGS | D20: =SUMIFS('Sales Data'!$Z$6:$Z$10000,'Sales Data'!$B$6:$B$10000,"Tiktok",'Sales Data'!$BC$6:$BC$10000,$B$7,'Sales Data'!$BD$6:$BD$10000,$C$7)
B21: ADVERTISING COST | D21: =SUMIFS('Sales Data'!$AA$6:$AA$10000,'Sales Data'!$B$6:$B$10000,"Tiktok",'Sales Data'!$BC$6:$BC$10000,$B$7,'Sales Data'!$BD$6:$BD$10000,$C$7)
B22: NET PROFIT | D22: =SUMIFS('Sales Data'!$AB$6:$AB$10000,'Sales Data'!$B$6:$B$10000,"Tiktok",'Sales Data'!$BC$6:$BC$10000,$B$7,'Sales Data'!$BD$6:$BD$10000,$C$7)
B23: TACOS | D23: =SUMIFS('Sales Data'!$M$6:$M$10000,'Sales Data'!$B$6:$B$10000,"Tiktok",'Sales Data'!$BC$6:$BC$10000,$B$7,'Sales Data'!$BD$6:$BD$10000,$C$7)
B24: % REFUNDS | D24: =SUMIFS('Sales Data'!$N$6:$N$10000,'Sales Data'!$B$6:$B$10000,"Tiktok",'Sales Data'!$BC$6:$BC$10000,$B$7,'Sales Data'!$BD$6:$BD$10000,$C$7)
B25: MARGIN | D25: =SUMIFS('Sales Data'!$AC$6:$AC$10000,'Sales Data'!$B$6:$B$10000,"Tiktok",'Sales Data'!$BC$6:$BC$10000,$B$7,'Sales Data'!$BD$6:$BD$10000,$C$7)
B28: MONTHLY TREND | I28: Trend Year: | J28: 2026
B30: METRIC | C30: Jan | D30: Feb | E30: Mar | F30: Apr | G30: May | H30: Jun | I30: Jul | J30: Aug | K30: Sep | L30: Oct | M30: Nov | N30: Dec | O30: YEAR TOTAL
B31: Net Sales (USD) | C31: =SUMIFS('Sales Data'!$R$6:$R$10000,'Sales Data'!$B$6:$B$10000,"Tiktok",'Sales Data'!$BC$6:$BC$10000,"Jan",'Sales Data'!$BD$6:$BD$10000,$J$28) | D31: =SUMIFS('Sales Data'!$R$6:$R$10000,'Sales Data'!$B$6:$B$10000,"Tiktok",'Sales Data'!$BC$6:$BC$10000,"Feb",'Sales Data'!$BD$6:$BD$10000,$J$28) | E31: =SUMIFS('Sales Data'!$R$6:$R$10000,'Sales Data'!$B$6:$B$10000,"Tiktok",'Sales Data'!$BC$6:$BC$10000,"Mar",'Sales Data'!$BD$6:$BD$10000,$J$28) | F31: =SUMIFS('Sales Data'!$R$6:$R$10000,'Sales Data'!$B$6:$B$10000,"Tiktok",'Sales Data'!$BC$6:$BC$10000,"Apr",'Sales Data'!$BD$6:$BD$10000,$J$28) | G31: =SUMIFS('Sales Data'!$R$6:$R$10000,'Sales Data'!$B$6:$B$10000,"Tiktok",'Sales Data'!$BC$6:$BC$10000,"May",'Sales Data'!$BD$6:$BD$10000,$J$28) | H31: =SUMIFS('Sales Data'!$R$6:$R$10000,'Sales Data'!$B$6:$B$10000,"Tiktok",'Sales Data'!$BC$6:$BC$10000,"Jun",'Sales Data'!$BD$6:$BD$10000,$J$28) | I31: =SUMIFS('Sales Data'!$R$6:$R$10000,'Sales Data'!$B$6:$B$10000,"Tiktok",'Sales Data'!$BC$6:$BC$10000,"Jul",'Sales Data'!$BD$6:$BD$10000,$J$28) | J31: =SUMIFS('Sales Data'!$R$6:$R$10000,'Sales Data'!$B$6:$B$10000,"Tiktok",'Sales Data'!$BC$6:$BC$10000,"Aug",'Sales Data'!$BD$6:$BD$10000,$J$28) | K31: =SUMIFS('Sales Data'!$R$6:$R$10000,'Sales Data'!$B$6:$B$10000,"Tiktok",'Sales Data'!$BC$6:$BC$10000,"Sep",'Sales Data'!$BD$6:$BD$10000,$J$28) | L31: =SUMIFS('Sales Data'!$R$6:$R$10000,'Sales Data'!$B$6:$B$10000,"Tiktok",'Sales Data'!$BC$6:$BC$10000,"Oct",'Sales Data'!$BD$6:$BD$10000,$J$28) | M31: =SUMIFS('Sales Data'!$R$6:$R$10000,'Sales Data'!$B$6:$B$10000,"Tiktok",'Sales Data'!$BC$6:$BC$10000,"Nov",'Sales Data'!$BD$6:$BD$10000,$J$28) | N31: =SUMIFS('Sales Data'!$R$6:$R$10000,'Sales Data'!$B$6:$B$10000,"Tiktok",'Sales Data'!$BC$6:$BC$10000,"Dec",'Sales Data'!$BD$6:$BD$10000,$J$28) | O31: =SUM(C31:N31)
B32: Units | C32: =SUMIFS('Sales Data'!$G$6:$G$10000,'Sales Data'!$B$6:$B$10000,"Tiktok",'Sales Data'!$BC$6:$BC$10000,"Jan",'Sales Data'!$BD$6:$BD$10000,$J$28) | D32: =SUMIFS('Sales Data'!$G$6:$G$10000,'Sales Data'!$B$6:$B$10000,"Tiktok",'Sales Data'!$BC$6:$BC$10000,"Feb",'Sales Data'!$BD$6:$BD$10000,$J$28) | E32: =SUMIFS('Sales Data'!$G$6:$G$10000,'Sales Data'!$B$6:$B$10000,"Tiktok",'Sales Data'!$BC$6:$BC$10000,"Mar",'Sales Data'!$BD$6:$BD$10000,$J$28) | F32: =SUMIFS('Sales Data'!$G$6:$G$10000,'Sales Data'!$B$6:$B$10000,"Tiktok",'Sales Data'!$BC$6:$BC$10000,"Apr",'Sales Data'!$BD$6:$BD$10000,$J$28) | G32: =SUMIFS('Sales Data'!$G$6:$G$10000,'Sales Data'!$B$6:$B$10000,"Tiktok",'Sales Data'!$BC$6:$BC$10000,"May",'Sales Data'!$BD$6:$BD$10000,$J$28) | H32: =SUMIFS('Sales Data'!$G$6:$G$10000,'Sales Data'!$B$6:$B$10000,"Tiktok",'Sales Data'!$BC$6:$BC$10000,"Jun",'Sales Data'!$BD$6:$BD$10000,$J$28) | I32: =SUMIFS('Sales Data'!$G$6:$G$10000,'Sales Data'!$B$6:$B$10000,"Tiktok",'Sales Data'!$BC$6:$BC$10000,"Jul",'Sales Data'!$BD$6:$BD$10000,$J$28) | J32: =SUMIFS('Sales Data'!$G$6:$G$10000,'Sales Data'!$B$6:$B$10000,"Tiktok",'Sales Data'!$BC$6:$BC$10000,"Aug",'Sales Data'!$BD$6:$BD$10000,$J$28) | K32: =SUMIFS('Sales Data'!$G$6:$G$10000,'Sales Data'!$B$6:$B$10000,"Tiktok",'Sales Data'!$BC$6:$BC$10000,"Sep",'Sales Data'!$BD$6:$BD$10000,$J$28) | L32: =SUMIFS('Sales Data'!$G$6:$G$10000,'Sales Data'!$B$6:$B$10000,"Tiktok",'Sales Data'!$BC$6:$BC$10000,"Oct",'Sales Data'!$BD$6:$BD$10000,$J$28) | M32: =SUMIFS('Sales Data'!$G$6:$G$10000,'Sales Data'!$B$6:$B$10000,"Tiktok",'Sales Data'!$BC$6:$BC$10000,"Nov",'Sales Data'!$BD$6:$BD$10000,$J$28) | N32: =SUMIFS('Sales Data'!$G$6:$G$10000,'Sales Data'!$B$6:$B$10000,"Tiktok",'Sales Data'!$BC$6:$BC$10000,"Dec",'Sales Data'!$BD$6:$BD$10000,$J$28) | O32: =SUM(C32:N32)
B33: COGS | C33: =SUMIFS('Sales Data'!$Z$6:$Z$10000,'Sales Data'!$B$6:$B$10000,"Tiktok",'Sales Data'!$BC$6:$BC$10000,"Jan",'Sales Data'!$BD$6:$BD$10000,$J$28) | D33: =SUMIFS('Sales Data'!$Z$6:$Z$10000,'Sales Data'!$B$6:$B$10000,"Tiktok",'Sales Data'!$BC$6:$BC$10000,"Feb",'Sales Data'!$BD$6:$BD$10000,$J$28) | E33: =SUMIFS('Sales Data'!$Z$6:$Z$10000,'Sales Data'!$B$6:$B$10000,"Tiktok",'Sales Data'!$BC$6:$BC$10000,"Mar",'Sales Data'!$BD$6:$BD$10000,$J$28) | F33: =SUMIFS('Sales Data'!$Z$6:$Z$10000,'Sales Data'!$B$6:$B$10000,"Tiktok",'Sales Data'!$BC$6:$BC$10000,"Apr",'Sales Data'!$BD$6:$BD$10000,$J$28) | G33: =SUMIFS('Sales Data'!$Z$6:$Z$10000,'Sales Data'!$B$6:$B$10000,"Tiktok",'Sales Data'!$BC$6:$BC$10000,"May",'Sales Data'!$BD$6:$BD$10000,$J$28) | H33: =SUMIFS('Sales Data'!$Z$6:$Z$10000,'Sales Data'!$B$6:$B$10000,"Tiktok",'Sales Data'!$BC$6:$BC$10000,"Jun",'Sales Data'!$BD$6:$BD$10000,$J$28) | I33: =SUMIFS('Sales Data'!$Z$6:$Z$10000,'Sales Data'!$B$6:$B$10000,"Tiktok",'Sales Data'!$BC$6:$BC$10000,"Jul",'Sales Data'!$BD$6:$BD$10000,$J$28) | J33: =SUMIFS('Sales Data'!$Z$6:$Z$10000,'Sales Data'!$B$6:$B$10000,"Tiktok",'Sales Data'!$BC$6:$BC$10000,"Aug",'Sales Data'!$BD$6:$BD$10000,$J$28) | K33: =SUMIFS('Sales Data'!$Z$6:$Z$10000,'Sales Data'!$B$6:$B$10000,"Tiktok",'Sales Data'!$BC$6:$BC$10000,"Sep",'Sales Data'!$BD$6:$BD$10000,$J$28) | L33: =SUMIFS('Sales Data'!$Z$6:$Z$10000,'Sales Data'!$B$6:$B$10000,"Tiktok",'Sales Data'!$BC$6:$BC$10000,"Oct",'Sales Data'!$BD$6:$BD$10000,$J$28) | M33: =SUMIFS('Sales Data'!$Z$6:$Z$10000,'Sales Data'!$B$6:$B$10000,"Tiktok",'Sales Data'!$BC$6:$BC$10000,"Nov",'Sales Data'!$BD$6:$BD$10000,$J$28) | N33: =SUMIFS('Sales Data'!$Z$6:$Z$10000,'Sales Data'!$B$6:$B$10000,"Tiktok",'Sales Data'!$BC$6:$BC$10000,"Dec",'Sales Data'!$BD$6:$BD$10000,$J$28) | O33: =SUM(C33:N33)
B34: Ad Cost | C34: =SUMIFS('Sales Data'!$AA$6:$AA$10000,'Sales Data'!$B$6:$B$10000,"Tiktok",'Sales Data'!$BC$6:$BC$10000,"Jan",'Sales Data'!$BD$6:$BD$10000,$J$28) | D34: =SUMIFS('Sales Data'!$AA$6:$AA$10000,'Sales Data'!$B$6:$B$10000,"Tiktok",'Sales Data'!$BC$6:$BC$10000,"Feb",'Sales Data'!$BD$6:$BD$10000,$J$28) | E34: =SUMIFS('Sales Data'!$AA$6:$AA$10000,'Sales Data'!$B$6:$B$10000,"Tiktok",'Sales Data'!$BC$6:$BC$10000,"Mar",'Sales Data'!$BD$6:$BD$10000,$J$28) | F34: =SUMIFS('Sales Data'!$AA$6:$AA$10000,'Sales Data'!$B$6:$B$10000,"Tiktok",'Sales Data'!$BC$6:$BC$10000,"Apr",'Sales Data'!$BD$6:$BD$10000,$J$28) | G34: =SUMIFS('Sales Data'!$AA$6:$AA$10000,'Sales Data'!$B$6:$B$10000,"Tiktok",'Sales Data'!$BC$6:$BC$10000,"May",'Sales Data'!$BD$6:$BD$10000,$J$28) | H34: =SUMIFS('Sales Data'!$AA$6:$AA$10000,'Sales Data'!$B$6:$B$10000,"Tiktok",'Sales Data'!$BC$6:$BC$10000,"Jun",'Sales Data'!$BD$6:$BD$10000,$J$28) | I34: =SUMIFS('Sales Data'!$AA$6:$AA$10000,'Sales Data'!$B$6:$B$10000,"Tiktok",'Sales Data'!$BC$6:$BC$10000,"Jul",'Sales Data'!$BD$6:$BD$10000,$J$28) | J34: =SUMIFS('Sales Data'!$AA$6:$AA$10000,'Sales Data'!$B$6:$B$10000,"Tiktok",'Sales Data'!$BC$6:$BC$10000,"Aug",'Sales Data'!$BD$6:$BD$10000,$J$28) | K34: =SUMIFS('Sales Data'!$AA$6:$AA$10000,'Sales Data'!$B$6:$B$10000,"Tiktok",'Sales Data'!$BC$6:$BC$10000,"Sep",'Sales Data'!$BD$6:$BD$10000,$J$28) | L34: =SUMIFS('Sales Data'!$AA$6:$AA$10000,'Sales Data'!$B$6:$B$10000,"Tiktok",'Sales Data'!$BC$6:$BC$10000,"Oct",'Sales Data'!$BD$6:$BD$10000,$J$28) | M34: =SUMIFS('Sales Data'!$AA$6:$AA$10000,'Sales Data'!$B$6:$B$10000,"Tiktok",'Sales Data'!$BC$6:$BC$10000,"Nov",'Sales Data'!$BD$6:$BD$10000,$J$28) | N34: =SUMIFS('Sales Data'!$AA$6:$AA$10000,'Sales Data'!$B$6:$B$10000,"Tiktok",'Sales Data'!$BC$6:$BC$10000,"Dec",'Sales Data'!$BD$6:$BD$10000,$J$28) | O34: =SUM(C34:N34)
B35: Net Profit | C35: =SUMIFS('Sales Data'!$AB$6:$AB$10000,'Sales Data'!$B$6:$B$10000,"Tiktok",'Sales Data'!$BC$6:$BC$10000,"Jan",'Sales Data'!$BD$6:$BD$10000,$J$28) | D35: =SUMIFS('Sales Data'!$AB$6:$AB$10000,'Sales Data'!$B$6:$B$10000,"Tiktok",'Sales Data'!$BC$6:$BC$10000,"Feb",'Sales Data'!$BD$6:$BD$10000,$J$28) | E35: =SUMIFS('Sales Data'!$AB$6:$AB$10000,'Sales Data'!$B$6:$B$10000,"Tiktok",'Sales Data'!$BC$6:$BC$10000,"Mar",'Sales Data'!$BD$6:$BD$10000,$J$28) | F35: =SUMIFS('Sales Data'!$AB$6:$AB$10000,'Sales Data'!$B$6:$B$10000,"Tiktok",'Sales Data'!$BC$6:$BC$10000,"Apr",'Sales Data'!$BD$6:$BD$10000,$J$28) | G35: =SUMIFS('Sales Data'!$AB$6:$AB$10000,'Sales Data'!$B$6:$B$10000,"Tiktok",'Sales Data'!$BC$6:$BC$10000,"May",'Sales Data'!$BD$6:$BD$10000,$J$28) | H35: =SUMIFS('Sales Data'!$AB$6:$AB$10000,'Sales Data'!$B$6:$B$10000,"Tiktok",'Sales Data'!$BC$6:$BC$10000,"Jun",'Sales Data'!$BD$6:$BD$10000,$J$28) | I35: =SUMIFS('Sales Data'!$AB$6:$AB$10000,'Sales Data'!$B$6:$B$10000,"Tiktok",'Sales Data'!$BC$6:$BC$10000,"Jul",'Sales Data'!$BD$6:$BD$10000,$J$28) | J35: =SUMIFS('Sales Data'!$AB$6:$AB$10000,'Sales Data'!$B$6:$B$10000,"Tiktok",'Sales Data'!$BC$6:$BC$10000,"Aug",'Sales Data'!$BD$6:$BD$10000,$J$28) | K35: =SUMIFS('Sales Data'!$AB$6:$AB$10000,'Sales Data'!$B$6:$B$10000,"Tiktok",'Sales Data'!$BC$6:$BC$10000,"Sep",'Sales Data'!$BD$6:$BD$10000,$J$28) | L35: =SUMIFS('Sales Data'!$AB$6:$AB$10000,'Sales Data'!$B$6:$B$10000,"Tiktok",'Sales Data'!$BC$6:$BC$10000,"Oct",'Sales Data'!$BD$6:$BD$10000,$J$28) | M35: =SUMIFS('Sales Data'!$AB$6:$AB$10000,'Sales Data'!$B$6:$B$10000,"Tiktok",'Sales Data'!$BC$6:$BC$10000,"Nov",'Sales Data'!$BD$6:$BD$10000,$J$28) | N35: =SUMIFS('Sales Data'!$AB$6:$AB$10000,'Sales Data'!$B$6:$B$10000,"Tiktok",'Sales Data'!$BC$6:$BC$10000,"Dec",'Sales Data'!$BD$6:$BD$10000,$J$28) | O35: =SUM(C35:N35)
B36: TACOS | C36: =SUMIFS('Sales Data'!$M$6:$M$10000,'Sales Data'!$B$6:$B$10000,"Tiktok",'Sales Data'!$BC$6:$BC$10000,"Jan",'Sales Data'!$BD$6:$BD$10000,$J$28) | D36: =SUMIFS('Sales Data'!$M$6:$M$10000,'Sales Data'!$B$6:$B$10000,"Tiktok",'Sales Data'!$BC$6:$BC$10000,"Feb",'Sales Data'!$BD$6:$BD$10000,$J$28) | E36: =SUMIFS('Sales Data'!$M$6:$M$10000,'Sales Data'!$B$6:$B$10000,"Tiktok",'Sales Data'!$BC$6:$BC$10000,"Mar",'Sales Data'!$BD$6:$BD$10000,$J$28) | F36: =SUMIFS('Sales Data'!$M$6:$M$10000,'Sales Data'!$B$6:$B$10000,"Tiktok",'Sales Data'!$BC$6:$BC$10000,"Apr",'Sales Data'!$BD$6:$BD$10000,$J$28) | G36: =SUMIFS('Sales Data'!$M$6:$M$10000,'Sales Data'!$B$6:$B$10000,"Tiktok",'Sales Data'!$BC$6:$BC$10000,"May",'Sales Data'!$BD$6:$BD$10000,$J$28) | H36: =SUMIFS('Sales Data'!$M$6:$M$10000,'Sales Data'!$B$6:$B$10000,"Tiktok",'Sales Data'!$BC$6:$BC$10000,"Jun",'Sales Data'!$BD$6:$BD$10000,$J$28) | I36: =SUMIFS('Sales Data'!$M$6:$M$10000,'Sales Data'!$B$6:$B$10000,"Tiktok",'Sales Data'!$BC$6:$BC$10000,"Jul",'Sales Data'!$BD$6:$BD$10000,$J$28) | J36: =SUMIFS('Sales Data'!$M$6:$M$10000,'Sales Data'!$B$6:$B$10000,"Tiktok",'Sales Data'!$BC$6:$BC$10000,"Aug",'Sales Data'!$BD$6:$BD$10000,$J$28) | K36: =SUMIFS('Sales Data'!$M$6:$M$10000,'Sales Data'!$B$6:$B$10000,"Tiktok",'Sales Data'!$BC$6:$BC$10000,"Sep",'Sales Data'!$BD$6:$BD$10000,$J$28) | L36: =SUMIFS('Sales Data'!$M$6:$M$10000,'Sales Data'!$B$6:$B$10000,"Tiktok",'Sales Data'!$BC$6:$BC$10000,"Oct",'Sales Data'!$BD$6:$BD$10000,$J$28) | M36: =SUMIFS('Sales Data'!$M$6:$M$10000,'Sales Data'!$B$6:$B$10000,"Tiktok",'Sales Data'!$BC$6:$BC$10000,"Nov",'Sales Data'!$BD$6:$BD$10000,$J$28) | N36: =SUMIFS('Sales Data'!$M$6:$M$10000,'Sales Data'!$B$6:$B$10000,"Tiktok",'Sales Data'!$BC$6:$BC$10000,"Dec",'Sales Data'!$BD$6:$BD$10000,$J$28) | O36: =IFERROR(AVERAGE(C36:N36),0)
B37: Margin | C37: =SUMIFS('Sales Data'!$AC$6:$AC$10000,'Sales Data'!$B$6:$B$10000,"Tiktok",'Sales Data'!$BC$6:$BC$10000,"Jan",'Sales Data'!$BD$6:$BD$10000,$J$28) | D37: =SUMIFS('Sales Data'!$AC$6:$AC$10000,'Sales Data'!$B$6:$B$10000,"Tiktok",'Sales Data'!$BC$6:$BC$10000,"Feb",'Sales Data'!$BD$6:$BD$10000,$J$28) | E37: =SUMIFS('Sales Data'!$AC$6:$AC$10000,'Sales Data'!$B$6:$B$10000,"Tiktok",'Sales Data'!$BC$6:$BC$10000,"Mar",'Sales Data'!$BD$6:$BD$10000,$J$28) | F37: =SUMIFS('Sales Data'!$AC$6:$AC$10000,'Sales Data'!$B$6:$B$10000,"Tiktok",'Sales Data'!$BC$6:$BC$10000,"Apr",'Sales Data'!$BD$6:$BD$10000,$J$28) | G37: =SUMIFS('Sales Data'!$AC$6:$AC$10000,'Sales Data'!$B$6:$B$10000,"Tiktok",'Sales Data'!$BC$6:$BC$10000,"May",'Sales Data'!$BD$6:$BD$10000,$J$28) | H37: =SUMIFS('Sales Data'!$AC$6:$AC$10000,'Sales Data'!$B$6:$B$10000,"Tiktok",'Sales Data'!$BC$6:$BC$10000,"Jun",'Sales Data'!$BD$6:$BD$10000,$J$28) | I37: =SUMIFS('Sales Data'!$AC$6:$AC$10000,'Sales Data'!$B$6:$B$10000,"Tiktok",'Sales Data'!$BC$6:$BC$10000,"Jul",'Sales Data'!$BD$6:$BD$10000,$J$28) | J37: =SUMIFS('Sales Data'!$AC$6:$AC$10000,'Sales Data'!$B$6:$B$10000,"Tiktok",'Sales Data'!$BC$6:$BC$10000,"Aug",'Sales Data'!$BD$6:$BD$10000,$J$28) | K37: =SUMIFS('Sales Data'!$AC$6:$AC$10000,'Sales Data'!$B$6:$B$10000,"Tiktok",'Sales Data'!$BC$6:$BC$10000,"Sep",'Sales Data'!$BD$6:$BD$10000,$J$28) | L37: =SUMIFS('Sales Data'!$AC$6:$AC$10000,'Sales Data'!$B$6:$B$10000,"Tiktok",'Sales Data'!$BC$6:$BC$10000,"Oct",'Sales Data'!$BD$6:$BD$10000,$J$28) | M37: =SUMIFS('Sales Data'!$AC$6:$AC$10000,'Sales Data'!$B$6:$B$10000,"Tiktok",'Sales Data'!$BC$6:$BC$10000,"Nov",'Sales Data'!$BD$6:$BD$10000,$J$28) | N37: =SUMIFS('Sales Data'!$AC$6:$AC$10000,'Sales Data'!$B$6:$B$10000,"Tiktok",'Sales Data'!$BC$6:$BC$10000,"Dec",'Sales Data'!$BD$6:$BD$10000,$J$28) | O37: =IFERROR(AVERAGE(C37:N37),0)
B40: EXPENSE BREAKDOWN · MAIN & SUB CATEGORY | J40: SALES BREAKDOWN · SUB-CATEGORY
B41: CATEGORY | C41: AMOUNT | D41: % OF EXPENSES | J41: SUB CATEGORY | K41: SALES AMOUNT | L41: % OF SALES
B42: Tiktok Shipping | C42: =IFERROR(SUMIFS('Main Expenses'!$E$6:$E$10000,'Main Expenses'!$B$6:$B$10000,"Tiktok",'Main Expenses'!$D$6:$D$10000,"Tiktok Shipping",'Main Expenses'!$K$6:$K$10000,$B$7,'Main Expenses'!$L$6:$L$10000,$C$7),0) | D42: =IFERROR(C42/SUMIFS('Main Expenses'!$E$6:$E$10000,'Main Expenses'!$B$6:$B$10000,"Tiktok",'Main Expenses'!$K$6:$K$10000,$B$7,'Main Expenses'!$L$6:$L$10000,$C$7),0) | J42: Gross sales | K42: =IFERROR(SUMIFS('Sales Data'!$E$6:$E$10000,'Sales Data'!$B$6:$B$10000,"Tiktok",'Sales Data'!$D$6:$D$10000,"Gross sales",'Sales Data'!$BC$6:$BC$10000,$B$7,'Sales Data'!$BD$6:$BD$10000,$C$7),0) | L42: =IFERROR(K42/SUMIFS('Sales Data'!$E$6:$E$10000,'Sales Data'!$B$6:$B$10000,"Tiktok",'Sales Data'!$BC$6:$BC$10000,$B$7,'Sales Data'!$BD$6:$BD$10000,$C$7),0)
B43: ↳ Co-funded free shipping reimbursement | C43: =IFERROR(SUMIFS('Sub Expenses'!$E$6:$E$10000,'Sub Expenses'!$B$6:$B$10000,"Tiktok",'Sub Expenses'!$C$6:$C$10000,"Tiktok Shipping",'Sub Expenses'!$D$6:$D$10000,"Co-funded free shipping reimbursement",'Sub Expenses'!$J$6:$J$10000,$B$7,'Sub Expenses'!$K$6:$K$10000,$C$7),0) | D43: =IFERROR(C43/SUMIFS('Main Expenses'!$E$6:$E$10000,'Main Expenses'!$B$6:$B$10000,"Tiktok",'Main Expenses'!$K$6:$K$10000,$B$7,'Main Expenses'!$L$6:$L$10000,$C$7),0) | J43: Gross sales refund | K43: =IFERROR(SUMIFS('Sales Data'!$E$6:$E$10000,'Sales Data'!$B$6:$B$10000,"Tiktok",'Sales Data'!$D$6:$D$10000,"Gross sales refund",'Sales Data'!$BC$6:$BC$10000,$B$7,'Sales Data'!$BD$6:$BD$10000,$C$7),0) | L43: =IFERROR(K43/SUMIFS('Sales Data'!$E$6:$E$10000,'Sales Data'!$B$6:$B$10000,"Tiktok",'Sales Data'!$BC$6:$BC$10000,$B$7,'Sales Data'!$BD$6:$BD$10000,$C$7),0)
B44: ↳ Customer shipping fee offset | C44: =IFERROR(SUMIFS('Sub Expenses'!$E$6:$E$10000,'Sub Expenses'!$B$6:$B$10000,"Tiktok",'Sub Expenses'!$C$6:$C$10000,"Tiktok Shipping",'Sub Expenses'!$D$6:$D$10000,"Customer shipping fee offset",'Sub Expenses'!$J$6:$J$10000,$B$7,'Sub Expenses'!$K$6:$K$10000,$C$7),0) | D44: =IFERROR(C44/SUMIFS('Main Expenses'!$E$6:$E$10000,'Main Expenses'!$B$6:$B$10000,"Tiktok",'Main Expenses'!$K$6:$K$10000,$B$7,'Main Expenses'!$L$6:$L$10000,$C$7),0) | J44: Seller discount | K44: =IFERROR(SUMIFS('Sales Data'!$E$6:$E$10000,'Sales Data'!$B$6:$B$10000,"Tiktok",'Sales Data'!$D$6:$D$10000,"Seller discount",'Sales Data'!$BC$6:$BC$10000,$B$7,'Sales Data'!$BD$6:$BD$10000,$C$7),0) | L44: =IFERROR(K44/SUMIFS('Sales Data'!$E$6:$E$10000,'Sales Data'!$B$6:$B$10000,"Tiktok",'Sales Data'!$BC$6:$BC$10000,$B$7,'Sales Data'!$BD$6:$BD$10000,$C$7),0)
B45: ↳ Customer-paid shipping fee | C45: =IFERROR(SUMIFS('Sub Expenses'!$E$6:$E$10000,'Sub Expenses'!$B$6:$B$10000,"Tiktok",'Sub Expenses'!$C$6:$C$10000,"Tiktok Shipping",'Sub Expenses'!$D$6:$D$10000,"Customer-paid shipping fee",'Sub Expenses'!$J$6:$J$10000,$B$7,'Sub Expenses'!$K$6:$K$10000,$C$7),0) | D45: =IFERROR(C45/SUMIFS('Main Expenses'!$E$6:$E$10000,'Main Expenses'!$B$6:$B$10000,"Tiktok",'Main Expenses'!$K$6:$K$10000,$B$7,'Main Expenses'!$L$6:$L$10000,$C$7),0) | J45: Seller discount refund | K45: =IFERROR(SUMIFS('Sales Data'!$E$6:$E$10000,'Sales Data'!$B$6:$B$10000,"Tiktok",'Sales Data'!$D$6:$D$10000,"Seller discount refund",'Sales Data'!$BC$6:$BC$10000,$B$7,'Sales Data'!$BD$6:$BD$10000,$C$7),0) | L45: =IFERROR(K45/SUMIFS('Sales Data'!$E$6:$E$10000,'Sales Data'!$B$6:$B$10000,"Tiktok",'Sales Data'!$BC$6:$BC$10000,$B$7,'Sales Data'!$BD$6:$BD$10000,$C$7),0)
B46: ↳ Customer-paid shipping fee refund | C46: =IFERROR(SUMIFS('Sub Expenses'!$E$6:$E$10000,'Sub Expenses'!$B$6:$B$10000,"Tiktok",'Sub Expenses'!$C$6:$C$10000,"Tiktok Shipping",'Sub Expenses'!$D$6:$D$10000,"Customer-paid shipping fee refund",'Sub Expenses'!$J$6:$J$10000,$B$7,'Sub Expenses'!$K$6:$K$10000,$C$7),0) | D46: =IFERROR(C46/SUMIFS('Main Expenses'!$E$6:$E$10000,'Main Expenses'!$B$6:$B$10000,"Tiktok",'Main Expenses'!$K$6:$K$10000,$B$7,'Main Expenses'!$L$6:$L$10000,$C$7),0)
B47: ↳ FBT fulfillment fee | C47: =IFERROR(SUMIFS('Sub Expenses'!$E$6:$E$10000,'Sub Expenses'!$B$6:$B$10000,"Tiktok",'Sub Expenses'!$C$6:$C$10000,"Tiktok Shipping",'Sub Expenses'!$D$6:$D$10000,"FBT fulfillment fee",'Sub Expenses'!$J$6:$J$10000,$B$7,'Sub Expenses'!$K$6:$K$10000,$C$7),0) | D47: =IFERROR(C47/SUMIFS('Main Expenses'!$E$6:$E$10000,'Main Expenses'!$B$6:$B$10000,"Tiktok",'Main Expenses'!$K$6:$K$10000,$B$7,'Main Expenses'!$L$6:$L$10000,$C$7),0)
B48: ↳ Fulfilled by TikTok Shop (FBT) shipping fee | C48: =IFERROR(SUMIFS('Sub Expenses'!$E$6:$E$10000,'Sub Expenses'!$B$6:$B$10000,"Tiktok",'Sub Expenses'!$C$6:$C$10000,"Tiktok Shipping",'Sub Expenses'!$D$6:$D$10000,"Fulfilled by TikTok Shop (FBT) shipping fee",'Sub Expenses'!$J$6:$J$10000,$B$7,'Sub Expenses'!$K$6:$K$10000,$C$7),0) | D48: =IFERROR(C48/SUMIFS('Main Expenses'!$E$6:$E$10000,'Main Expenses'!$B$6:$B$10000,"Tiktok",'Main Expenses'!$K$6:$K$10000,$B$7,'Main Expenses'!$L$6:$L$10000,$C$7),0)
B49: ↳ Return shipping fee | C49: =IFERROR(SUMIFS('Sub Expenses'!$E$6:$E$10000,'Sub Expenses'!$B$6:$B$10000,"Tiktok",'Sub Expenses'!$C$6:$C$10000,"Tiktok Shipping",'Sub Expenses'!$D$6:$D$10000,"Return shipping fee",'Sub Expenses'!$J$6:$J$10000,$B$7,'Sub Expenses'!$K$6:$K$10000,$C$7),0) | D49: =IFERROR(C49/SUMIFS('Main Expenses'!$E$6:$E$10000,'Main Expenses'!$B$6:$B$10000,"Tiktok",'Main Expenses'!$K$6:$K$10000,$B$7,'Main Expenses'!$L$6:$L$10000,$C$7),0)
B50: ↳ Return shipping fee reimbursement | C50: =IFERROR(SUMIFS('Sub Expenses'!$E$6:$E$10000,'Sub Expenses'!$B$6:$B$10000,"Tiktok",'Sub Expenses'!$C$6:$C$10000,"Tiktok Shipping",'Sub Expenses'!$D$6:$D$10000,"Return shipping fee reimbursement",'Sub Expenses'!$J$6:$J$10000,$B$7,'Sub Expenses'!$K$6:$K$10000,$C$7),0) | D50: =IFERROR(C50/SUMIFS('Main Expenses'!$E$6:$E$10000,'Main Expenses'!$B$6:$B$10000,"Tiktok",'Main Expenses'!$K$6:$K$10000,$B$7,'Main Expenses'!$L$6:$L$10000,$C$7),0)
B51: ↳ Shipping fee subsidy | C51: =IFERROR(SUMIFS('Sub Expenses'!$E$6:$E$10000,'Sub Expenses'!$B$6:$B$10000,"Tiktok",'Sub Expenses'!$C$6:$C$10000,"Tiktok Shipping",'Sub Expenses'!$D$6:$D$10000,"Shipping fee subsidy",'Sub Expenses'!$J$6:$J$10000,$B$7,'Sub Expenses'!$K$6:$K$10000,$C$7),0) | D51: =IFERROR(C51/SUMIFS('Main Expenses'!$E$6:$E$10000,'Main Expenses'!$B$6:$B$10000,"Tiktok",'Main Expenses'!$K$6:$K$10000,$B$7,'Main Expenses'!$L$6:$L$10000,$C$7),0)
B52: ↳ Shipping insurance fee | C52: =IFERROR(SUMIFS('Sub Expenses'!$E$6:$E$10000,'Sub Expenses'!$B$6:$B$10000,"Tiktok",'Sub Expenses'!$C$6:$C$10000,"Tiktok Shipping",'Sub Expenses'!$D$6:$D$10000,"Shipping insurance fee",'Sub Expenses'!$J$6:$J$10000,$B$7,'Sub Expenses'!$K$6:$K$10000,$C$7),0) | D52: =IFERROR(C52/SUMIFS('Main Expenses'!$E$6:$E$10000,'Main Expenses'!$B$6:$B$10000,"Tiktok",'Main Expenses'!$K$6:$K$10000,$B$7,'Main Expenses'!$L$6:$L$10000,$C$7),0)
B53: ↳ Signature confirmation service fee | C53: =IFERROR(SUMIFS('Sub Expenses'!$E$6:$E$10000,'Sub Expenses'!$B$6:$B$10000,"Tiktok",'Sub Expenses'!$C$6:$C$10000,"Tiktok Shipping",'Sub Expenses'!$D$6:$D$10000,"Signature confirmation service fee",'Sub Expenses'!$J$6:$J$10000,$B$7,'Sub Expenses'!$K$6:$K$10000,$C$7),0) | D53: =IFERROR(C53/SUMIFS('Main Expenses'!$E$6:$E$10000,'Main Expenses'!$B$6:$B$10000,"Tiktok",'Main Expenses'!$K$6:$K$10000,$B$7,'Main Expenses'!$L$6:$L$10000,$C$7),0)
B54: ↳ TikTok Shop shipping fee | C54: =IFERROR(SUMIFS('Sub Expenses'!$E$6:$E$10000,'Sub Expenses'!$B$6:$B$10000,"Tiktok",'Sub Expenses'!$C$6:$C$10000,"Tiktok Shipping",'Sub Expenses'!$D$6:$D$10000,"TikTok Shop shipping fee",'Sub Expenses'!$J$6:$J$10000,$B$7,'Sub Expenses'!$K$6:$K$10000,$C$7),0) | D54: =IFERROR(C54/SUMIFS('Main Expenses'!$E$6:$E$10000,'Main Expenses'!$B$6:$B$10000,"Tiktok",'Main Expenses'!$K$6:$K$10000,$B$7,'Main Expenses'!$L$6:$L$10000,$C$7),0)
B55: ↳ TikTok Shop shipping incentive | C55: =IFERROR(SUMIFS('Sub Expenses'!$E$6:$E$10000,'Sub Expenses'!$B$6:$B$10000,"Tiktok",'Sub Expenses'!$C$6:$C$10000,"Tiktok Shipping",'Sub Expenses'!$D$6:$D$10000,"TikTok Shop shipping incentive",'Sub Expenses'!$J$6:$J$10000,$B$7,'Sub Expenses'!$K$6:$K$10000,$C$7),0) | D55: =IFERROR(C55/SUMIFS('Main Expenses'!$E$6:$E$10000,'Main Expenses'!$B$6:$B$10000,"Tiktok",'Main Expenses'!$K$6:$K$10000,$B$7,'Main Expenses'!$L$6:$L$10000,$C$7),0)
B56: ↳ TikTok Shop shipping incentive refund | C56: =IFERROR(SUMIFS('Sub Expenses'!$E$6:$E$10000,'Sub Expenses'!$B$6:$B$10000,"Tiktok",'Sub Expenses'!$C$6:$C$10000,"Tiktok Shipping",'Sub Expenses'!$D$6:$D$10000,"TikTok Shop shipping incentive refund",'Sub Expenses'!$J$6:$J$10000,$B$7,'Sub Expenses'!$K$6:$K$10000,$C$7),0) | D56: =IFERROR(C56/SUMIFS('Main Expenses'!$E$6:$E$10000,'Main Expenses'!$B$6:$B$10000,"Tiktok",'Main Expenses'!$K$6:$K$10000,$B$7,'Main Expenses'!$L$6:$L$10000,$C$7),0)
B57: MCF Shipping fees | C57: =IFERROR(SUMIFS('Main Expenses'!$E$6:$E$10000,'Main Expenses'!$B$6:$B$10000,"Tiktok",'Main Expenses'!$D$6:$D$10000,"MCF Shipping fees",'Main Expenses'!$K$6:$K$10000,$B$7,'Main Expenses'!$L$6:$L$10000,$C$7),0) | D57: =IFERROR(C57/SUMIFS('Main Expenses'!$E$6:$E$10000,'Main Expenses'!$B$6:$B$10000,"Tiktok",'Main Expenses'!$K$6:$K$10000,$B$7,'Main Expenses'!$L$6:$L$10000,$C$7),0)
B58: ↳ MCF Shipping fees | C58: =IFERROR(SUMIFS('Sub Expenses'!$E$6:$E$10000,'Sub Expenses'!$B$6:$B$10000,"Tiktok",'Sub Expenses'!$C$6:$C$10000,"MCF Shipping fees",'Sub Expenses'!$D$6:$D$10000,"MCF Shipping fees",'Sub Expenses'!$J$6:$J$10000,$B$7,'Sub Expenses'!$K$6:$K$10000,$C$7),0) | D58: =IFERROR(C58/SUMIFS('Main Expenses'!$E$6:$E$10000,'Main Expenses'!$B$6:$B$10000,"Tiktok",'Main Expenses'!$K$6:$K$10000,$B$7,'Main Expenses'!$L$6:$L$10000,$C$7),0)
B59: Fees | C59: =IFERROR(SUMIFS('Main Expenses'!$E$6:$E$10000,'Main Expenses'!$B$6:$B$10000,"Tiktok",'Main Expenses'!$D$6:$D$10000,"Fees",'Main Expenses'!$K$6:$K$10000,$B$7,'Main Expenses'!$L$6:$L$10000,$C$7),0) | D59: =IFERROR(C59/SUMIFS('Main Expenses'!$E$6:$E$10000,'Main Expenses'!$B$6:$B$10000,"Tiktok",'Main Expenses'!$K$6:$K$10000,$B$7,'Main Expenses'!$L$6:$L$10000,$C$7),0)
B60: ↳ Affiliate Shop Ads commission | C60: =IFERROR(SUMIFS('Sub Expenses'!$E$6:$E$10000,'Sub Expenses'!$B$6:$B$10000,"Tiktok",'Sub Expenses'!$C$6:$C$10000,"Fees",'Sub Expenses'!$D$6:$D$10000,"Affiliate Shop Ads commission",'Sub Expenses'!$J$6:$J$10000,$B$7,'Sub Expenses'!$K$6:$K$10000,$C$7),0) | D60: =IFERROR(C60/SUMIFS('Main Expenses'!$E$6:$E$10000,'Main Expenses'!$B$6:$B$10000,"Tiktok",'Main Expenses'!$K$6:$K$10000,$B$7,'Main Expenses'!$L$6:$L$10000,$C$7),0)
B61: ↳ Affiliate commission | C61: =IFERROR(SUMIFS('Sub Expenses'!$E$6:$E$10000,'Sub Expenses'!$B$6:$B$10000,"Tiktok",'Sub Expenses'!$C$6:$C$10000,"Fees",'Sub Expenses'!$D$6:$D$10000,"Affiliate commission",'Sub Expenses'!$J$6:$J$10000,$B$7,'Sub Expenses'!$K$6:$K$10000,$C$7),0) | D61: =IFERROR(C61/SUMIFS('Main Expenses'!$E$6:$E$10000,'Main Expenses'!$B$6:$B$10000,"Tiktok",'Main Expenses'!$K$6:$K$10000,$B$7,'Main Expenses'!$L$6:$L$10000,$C$7),0)
B62: ↳ Affiliate partner commission | C62: =IFERROR(SUMIFS('Sub Expenses'!$E$6:$E$10000,'Sub Expenses'!$B$6:$B$10000,"Tiktok",'Sub Expenses'!$C$6:$C$10000,"Fees",'Sub Expenses'!$D$6:$D$10000,"Affiliate partner commission",'Sub Expenses'!$J$6:$J$10000,$B$7,'Sub Expenses'!$K$6:$K$10000,$C$7),0) | D62: =IFERROR(C62/SUMIFS('Main Expenses'!$E$6:$E$10000,'Main Expenses'!$B$6:$B$10000,"Tiktok",'Main Expenses'!$K$6:$K$10000,$B$7,'Main Expenses'!$L$6:$L$10000,$C$7),0)
B63: ↳ Co-funded promotion service fee | C63: =IFERROR(SUMIFS('Sub Expenses'!$E$6:$E$10000,'Sub Expenses'!$B$6:$B$10000,"Tiktok",'Sub Expenses'!$C$6:$C$10000,"Fees",'Sub Expenses'!$D$6:$D$10000,"Co-funded promotion service fee",'Sub Expenses'!$J$6:$J$10000,$B$7,'Sub Expenses'!$K$6:$K$10000,$C$7),0) | D63: =IFERROR(C63/SUMIFS('Main Expenses'!$E$6:$E$10000,'Main Expenses'!$B$6:$B$10000,"Tiktok",'Main Expenses'!$K$6:$K$10000,$B$7,'Main Expenses'!$L$6:$L$10000,$C$7),0)
B64: ↳ Referral fee | C64: =IFERROR(SUMIFS('Sub Expenses'!$E$6:$E$10000,'Sub Expenses'!$B$6:$B$10000,"Tiktok",'Sub Expenses'!$C$6:$C$10000,"Fees",'Sub Expenses'!$D$6:$D$10000,"Referral fee",'Sub Expenses'!$J$6:$J$10000,$B$7,'Sub Expenses'!$K$6:$K$10000,$C$7),0) | D64: =IFERROR(C64/SUMIFS('Main Expenses'!$E$6:$E$10000,'Main Expenses'!$B$6:$B$10000,"Tiktok",'Main Expenses'!$K$6:$K$10000,$B$7,'Main Expenses'!$L$6:$L$10000,$C$7),0)
B65: ↳ Refund administration fee | C65: =IFERROR(SUMIFS('Sub Expenses'!$E$6:$E$10000,'Sub Expenses'!$B$6:$B$10000,"Tiktok",'Sub Expenses'!$C$6:$C$10000,"Fees",'Sub Expenses'!$D$6:$D$10000,"Refund administration fee",'Sub Expenses'!$J$6:$J$10000,$B$7,'Sub Expenses'!$K$6:$K$10000,$C$7),0) | D65: =IFERROR(C65/SUMIFS('Main Expenses'!$E$6:$E$10000,'Main Expenses'!$B$6:$B$10000,"Tiktok",'Main Expenses'!$K$6:$K$10000,$B$7,'Main Expenses'!$L$6:$L$10000,$C$7),0)
B66: ↳ Sales tax on referral fees | C66: =IFERROR(SUMIFS('Sub Expenses'!$E$6:$E$10000,'Sub Expenses'!$B$6:$B$10000,"Tiktok",'Sub Expenses'!$C$6:$C$10000,"Fees",'Sub Expenses'!$D$6:$D$10000,"Sales tax on referral fees",'Sub Expenses'!$J$6:$J$10000,$B$7,'Sub Expenses'!$K$6:$K$10000,$C$7),0) | D66: =IFERROR(C66/SUMIFS('Main Expenses'!$E$6:$E$10000,'Main Expenses'!$B$6:$B$10000,"Tiktok",'Main Expenses'!$K$6:$K$10000,$B$7,'Main Expenses'!$L$6:$L$10000,$C$7),0)
B67: ↳ Transaction fee | C67: =IFERROR(SUMIFS('Sub Expenses'!$E$6:$E$10000,'Sub Expenses'!$B$6:$B$10000,"Tiktok",'Sub Expenses'!$C$6:$C$10000,"Fees",'Sub Expenses'!$D$6:$D$10000,"Transaction fee",'Sub Expenses'!$J$6:$J$10000,$B$7,'Sub Expenses'!$K$6:$K$10000,$C$7),0) | D67: =IFERROR(C67/SUMIFS('Main Expenses'!$E$6:$E$10000,'Main Expenses'!$B$6:$B$10000,"Tiktok",'Main Expenses'!$K$6:$K$10000,$B$7,'Main Expenses'!$L$6:$L$10000,$C$7),0)
B68: Adjustments | C68: =IFERROR(SUMIFS('Main Expenses'!$E$6:$E$10000,'Main Expenses'!$B$6:$B$10000,"Tiktok",'Main Expenses'!$D$6:$D$10000,"Adjustments ",'Main Expenses'!$K$6:$K$10000,$B$7,'Main Expenses'!$L$6:$L$10000,$C$7),0) | D68: =IFERROR(C68/SUMIFS('Main Expenses'!$E$6:$E$10000,'Main Expenses'!$B$6:$B$10000,"Tiktok",'Main Expenses'!$K$6:$K$10000,$B$7,'Main Expenses'!$L$6:$L$10000,$C$7),0)
B69: ↳ Adjustment from settlement account | C69: =IFERROR(SUMIFS('Sub Expenses'!$E$6:$E$10000,'Sub Expenses'!$B$6:$B$10000,"Tiktok",'Sub Expenses'!$C$6:$C$10000,"Adjustments ",'Sub Expenses'!$D$6:$D$10000,"Adjustment from settlement account",'Sub Expenses'!$J$6:$J$10000,$B$7,'Sub Expenses'!$K$6:$K$10000,$C$7),0) | D69: =IFERROR(C69/SUMIFS('Main Expenses'!$E$6:$E$10000,'Main Expenses'!$B$6:$B$10000,"Tiktok",'Main Expenses'!$K$6:$K$10000,$B$7,'Main Expenses'!$L$6:$L$10000,$C$7),0)
B70: ↳ Chargeback | C70: =IFERROR(SUMIFS('Sub Expenses'!$E$6:$E$10000,'Sub Expenses'!$B$6:$B$10000,"Tiktok",'Sub Expenses'!$C$6:$C$10000,"Adjustments ",'Sub Expenses'!$D$6:$D$10000,"Chargeback",'Sub Expenses'!$J$6:$J$10000,$B$7,'Sub Expenses'!$K$6:$K$10000,$C$7),0) | D70: =IFERROR(C70/SUMIFS('Main Expenses'!$E$6:$E$10000,'Main Expenses'!$B$6:$B$10000,"Tiktok",'Main Expenses'!$K$6:$K$10000,$B$7,'Main Expenses'!$L$6:$L$10000,$C$7),0)
B71: ↳ Co-funded creator activity | C71: =IFERROR(SUMIFS('Sub Expenses'!$E$6:$E$10000,'Sub Expenses'!$B$6:$B$10000,"Tiktok",'Sub Expenses'!$C$6:$C$10000,"Adjustments ",'Sub Expenses'!$D$6:$D$10000,"Co-funded creator activity",'Sub Expenses'!$J$6:$J$10000,$B$7,'Sub Expenses'!$K$6:$K$10000,$C$7),0) | D71: =IFERROR(C71/SUMIFS('Main Expenses'!$E$6:$E$10000,'Main Expenses'!$B$6:$B$10000,"Tiktok",'Main Expenses'!$K$6:$K$10000,$B$7,'Main Expenses'!$L$6:$L$10000,$C$7),0)
B72: ↳ FBT warehouse service fee | C72: =IFERROR(SUMIFS('Sub Expenses'!$E$6:$E$10000,'Sub Expenses'!$B$6:$B$10000,"Tiktok",'Sub Expenses'!$C$6:$C$10000,"Adjustments ",'Sub Expenses'!$D$6:$D$10000,"FBT warehouse service fee",'Sub Expenses'!$J$6:$J$10000,$B$7,'Sub Expenses'!$K$6:$K$10000,$C$7),0) | D72: =IFERROR(C72/SUMIFS('Main Expenses'!$E$6:$E$10000,'Main Expenses'!$B$6:$B$10000,"Tiktok",'Main Expenses'!$K$6:$K$10000,$B$7,'Main Expenses'!$L$6:$L$10000,$C$7),0)
B73: ↳ FBT warehouse service fee using GMV payments | C73: =IFERROR(SUMIFS('Sub Expenses'!$E$6:$E$10000,'Sub Expenses'!$B$6:$B$10000,"Tiktok",'Sub Expenses'!$C$6:$C$10000,"Adjustments ",'Sub Expenses'!$D$6:$D$10000,"FBT warehouse service fee using GMV payments",'Sub Expenses'!$J$6:$J$10000,$B$7,'Sub Expenses'!$K$6:$K$10000,$C$7),0) | D73: =IFERROR(C73/SUMIFS('Main Expenses'!$E$6:$E$10000,'Main Expenses'!$B$6:$B$10000,"Tiktok",'Main Expenses'!$K$6:$K$10000,$B$7,'Main Expenses'!$L$6:$L$10000,$C$7),0)
B74: ↳ Logistics adjustment | C74: =IFERROR(SUMIFS('Sub Expenses'!$E$6:$E$10000,'Sub Expenses'!$B$6:$B$10000,"Tiktok",'Sub Expenses'!$C$6:$C$10000,"Adjustments ",'Sub Expenses'!$D$6:$D$10000,"Logistics adjustment",'Sub Expenses'!$J$6:$J$10000,$B$7,'Sub Expenses'!$K$6:$K$10000,$C$7),0) | D74: =IFERROR(C74/SUMIFS('Main Expenses'!$E$6:$E$10000,'Main Expenses'!$B$6:$B$10000,"Tiktok",'Main Expenses'!$K$6:$K$10000,$B$7,'Main Expenses'!$L$6:$L$10000,$C$7),0)
B75: ↳ Logistics deduction | C75: =IFERROR(SUMIFS('Sub Expenses'!$E$6:$E$10000,'Sub Expenses'!$B$6:$B$10000,"Tiktok",'Sub Expenses'!$C$6:$C$10000,"Adjustments ",'Sub Expenses'!$D$6:$D$10000,"Logistics deduction",'Sub Expenses'!$J$6:$J$10000,$B$7,'Sub Expenses'!$K$6:$K$10000,$C$7),0) | D75: =IFERROR(C75/SUMIFS('Main Expenses'!$E$6:$E$10000,'Main Expenses'!$B$6:$B$10000,"Tiktok",'Main Expenses'!$K$6:$K$10000,$B$7,'Main Expenses'!$L$6:$L$10000,$C$7),0)
B76: ↳ Logistics reimbursement | C76: =IFERROR(SUMIFS('Sub Expenses'!$E$6:$E$10000,'Sub Expenses'!$B$6:$B$10000,"Tiktok",'Sub Expenses'!$C$6:$C$10000,"Adjustments ",'Sub Expenses'!$D$6:$D$10000,"Logistics reimbursement",'Sub Expenses'!$J$6:$J$10000,$B$7,'Sub Expenses'!$K$6:$K$10000,$C$7),0) | D76: =IFERROR(C76/SUMIFS('Main Expenses'!$E$6:$E$10000,'Main Expenses'!$B$6:$B$10000,"Tiktok",'Main Expenses'!$K$6:$K$10000,$B$7,'Main Expenses'!$L$6:$L$10000,$C$7),0)
B77: ↳ Other adjustment | C77: =IFERROR(SUMIFS('Sub Expenses'!$E$6:$E$10000,'Sub Expenses'!$B$6:$B$10000,"Tiktok",'Sub Expenses'!$C$6:$C$10000,"Adjustments ",'Sub Expenses'!$D$6:$D$10000,"Other adjustment",'Sub Expenses'!$J$6:$J$10000,$B$7,'Sub Expenses'!$K$6:$K$10000,$C$7),0) | D77: =IFERROR(C77/SUMIFS('Main Expenses'!$E$6:$E$10000,'Main Expenses'!$B$6:$B$10000,"Tiktok",'Main Expenses'!$K$6:$K$10000,$B$7,'Main Expenses'!$L$6:$L$10000,$C$7),0)
B78: ↳ Policy violation deduction | C78: =IFERROR(SUMIFS('Sub Expenses'!$E$6:$E$10000,'Sub Expenses'!$B$6:$B$10000,"Tiktok",'Sub Expenses'!$C$6:$C$10000,"Adjustments ",'Sub Expenses'!$D$6:$D$10000,"Policy violation deduction",'Sub Expenses'!$J$6:$J$10000,$B$7,'Sub Expenses'!$K$6:$K$10000,$C$7),0) | D78: =IFERROR(C78/SUMIFS('Main Expenses'!$E$6:$E$10000,'Main Expenses'!$B$6:$B$10000,"Tiktok",'Main Expenses'!$K$6:$K$10000,$B$7,'Main Expenses'!$L$6:$L$10000,$C$7),0)
B79: ↳ Promotion adjustment | C79: =IFERROR(SUMIFS('Sub Expenses'!$E$6:$E$10000,'Sub Expenses'!$B$6:$B$10000,"Tiktok",'Sub Expenses'!$C$6:$C$10000,"Adjustments ",'Sub Expenses'!$D$6:$D$10000,"Promotion adjustment",'Sub Expenses'!$J$6:$J$10000,$B$7,'Sub Expenses'!$K$6:$K$10000,$C$7),0) | D79: =IFERROR(C79/SUMIFS('Main Expenses'!$E$6:$E$10000,'Main Expenses'!$B$6:$B$10000,"Tiktok",'Main Expenses'!$K$6:$K$10000,$B$7,'Main Expenses'!$L$6:$L$10000,$C$7),0)
B80: ↳ Rebate | C80: =IFERROR(SUMIFS('Sub Expenses'!$E$6:$E$10000,'Sub Expenses'!$B$6:$B$10000,"Tiktok",'Sub Expenses'!$C$6:$C$10000,"Adjustments ",'Sub Expenses'!$D$6:$D$10000,"Rebate",'Sub Expenses'!$J$6:$J$10000,$B$7,'Sub Expenses'!$K$6:$K$10000,$C$7),0) | D80: =IFERROR(C80/SUMIFS('Main Expenses'!$E$6:$E$10000,'Main Expenses'!$B$6:$B$10000,"Tiktok",'Main Expenses'!$K$6:$K$10000,$B$7,'Main Expenses'!$L$6:$L$10000,$C$7),0)
B81: ↳ TikTok Shop reimbursement | C81: =IFERROR(SUMIFS('Sub Expenses'!$E$6:$E$10000,'Sub Expenses'!$B$6:$B$10000,"Tiktok",'Sub Expenses'!$C$6:$C$10000,"Adjustments ",'Sub Expenses'!$D$6:$D$10000,"TikTok Shop reimbursement",'Sub Expenses'!$J$6:$J$10000,$B$7,'Sub Expenses'!$K$6:$K$10000,$C$7),0) | D81: =IFERROR(C81/SUMIFS('Main Expenses'!$E$6:$E$10000,'Main Expenses'!$B$6:$B$10000,"Tiktok",'Main Expenses'!$K$6:$K$10000,$B$7,'Main Expenses'!$L$6:$L$10000,$C$7),0)
B82: ↳ TikTok fees adjustment | C82: =IFERROR(SUMIFS('Sub Expenses'!$E$6:$E$10000,'Sub Expenses'!$B$6:$B$10000,"Tiktok",'Sub Expenses'!$C$6:$C$10000,"Adjustments ",'Sub Expenses'!$D$6:$D$10000,"TikTok fees adjustment",'Sub Expenses'!$J$6:$J$10000,$B$7,'Sub Expenses'!$K$6:$K$10000,$C$7),0) | D82: =IFERROR(C82/SUMIFS('Main Expenses'!$E$6:$E$10000,'Main Expenses'!$B$6:$B$10000,"Tiktok",'Main Expenses'!$K$6:$K$10000,$B$7,'Main Expenses'!$L$6:$L$10000,$C$7),0)
B83: ↳ Top up ads balance using GMV payments | C83: =IFERROR(SUMIFS('Sub Expenses'!$E$6:$E$10000,'Sub Expenses'!$B$6:$B$10000,"Tiktok",'Sub Expenses'!$C$6:$C$10000,"Adjustments ",'Sub Expenses'!$D$6:$D$10000,"Top up ads balance using GMV payments",'Sub Expenses'!$J$6:$J$10000,$B$7,'Sub Expenses'!$K$6:$K$10000,$C$7),0) | D83: =IFERROR(C83/SUMIFS('Main Expenses'!$E$6:$E$10000,'Main Expenses'!$B$6:$B$10000,"Tiktok",'Main Expenses'!$K$6:$K$10000,$B$7,'Main Expenses'!$L$6:$L$10000,$C$7),0)
B84: Cost of goods | C84: =IFERROR(SUMIFS('Main Expenses'!$E$6:$E$10000,'Main Expenses'!$B$6:$B$10000,"Tiktok",'Main Expenses'!$D$6:$D$10000,"Cost of goods",'Main Expenses'!$K$6:$K$10000,$B$7,'Main Expenses'!$L$6:$L$10000,$C$7),0) | D84: =IFERROR(C84/SUMIFS('Main Expenses'!$E$6:$E$10000,'Main Expenses'!$B$6:$B$10000,"Tiktok",'Main Expenses'!$K$6:$K$10000,$B$7,'Main Expenses'!$L$6:$L$10000,$C$7),0)
B85: ↳ Cost of goods sold | C85: =IFERROR(SUMIFS('Sub Expenses'!$E$6:$E$10000,'Sub Expenses'!$B$6:$B$10000,"Tiktok",'Sub Expenses'!$C$6:$C$10000,"Cost of goods",'Sub Expenses'!$D$6:$D$10000,"Cost of goods sold",'Sub Expenses'!$J$6:$J$10000,$B$7,'Sub Expenses'!$K$6:$K$10000,$C$7),0) | D85: =IFERROR(C85/SUMIFS('Main Expenses'!$E$6:$E$10000,'Main Expenses'!$B$6:$B$10000,"Tiktok",'Main Expenses'!$K$6:$K$10000,$B$7,'Main Expenses'!$L$6:$L$10000,$C$7),0)
B86: Advertising cost | C86: =IFERROR(SUMIFS('Main Expenses'!$E$6:$E$10000,'Main Expenses'!$B$6:$B$10000,"Tiktok",'Main Expenses'!$D$6:$D$10000,"Advertising cost",'Main Expenses'!$K$6:$K$10000,$B$7,'Main Expenses'!$L$6:$L$10000,$C$7),0) | D86: =IFERROR(C86/SUMIFS('Main Expenses'!$E$6:$E$10000,'Main Expenses'!$B$6:$B$10000,"Tiktok",'Main Expenses'!$K$6:$K$10000,$B$7,'Main Expenses'!$L$6:$L$10000,$C$7),0)
B87: ↳ Advertising Cost | C87: =IFERROR(SUMIFS('Sub Expenses'!$E$6:$E$10000,'Sub Expenses'!$B$6:$B$10000,"Tiktok",'Sub Expenses'!$C$6:$C$10000,"Advertising cost",'Sub Expenses'!$D$6:$D$10000,"Advertising Cost",'Sub Expenses'!$J$6:$J$10000,$B$7,'Sub Expenses'!$K$6:$K$10000,$C$7),0) | D87: =IFERROR(C87/SUMIFS('Main Expenses'!$E$6:$E$10000,'Main Expenses'!$B$6:$B$10000,"Tiktok",'Main Expenses'!$K$6:$K$10000,$B$7,'Main Expenses'!$L$6:$L$10000,$C$7),0)
B88: TOTAL EXPENSES | C88: =SUMIFS('Main Expenses'!$E$6:$E$10000,'Main Expenses'!$B$6:$B$10000,"Tiktok",'Main Expenses'!$K$6:$K$10000,$B$7,'Main Expenses'!$L$6:$L$10000,$C$7) | D88: 1 | J88: TOTAL SALES | K88: =SUMIFS('Sales Data'!$E$6:$E$10000,'Sales Data'!$B$6:$B$10000,"Tiktok",'Sales Data'!$BC$6:$BC$10000,$B$7,'Sales Data'!$BD$6:$BD$10000,$C$7) | L88: 1

Sheet Shopify Dashboard
B2: SHOPIFY & FAIRE DASHBOARD
B3: Click the + symbol on the left margin to expand sub-categories · all KPIs update live via SUMIFS formulas.
B6: MONTH | C6: YEAR | D6: CATEGORY
B7: Mar | C7: 2026 | D7: All Categories
B9: KEY METRICS
B11: SALES | D11: =SUMIFS('Sales Data'!$E$6:$E$10000,'Sales Data'!$B$6:$B$10000,"Shopify",'Sales Data'!$BC$6:$BC$10000,$B$7,'Sales Data'!$BD$6:$BD$10000,$C$7)
B12: UNIT SALES | D12: =SUMIFS('Sales Data'!$G$6:$G$10000,'Sales Data'!$B$6:$B$10000,"Shopify",'Sales Data'!$BC$6:$BC$10000,$B$7,'Sales Data'!$BD$6:$BD$10000,$C$7)
B13: ADVERTISING COST | D13: =SUMIFS('Sales Data'!$AD$6:$AD$10000,'Sales Data'!$B$6:$B$10000,"Shopify",'Sales Data'!$BC$6:$BC$10000,$B$7,'Sales Data'!$BD$6:$BD$10000,$C$7)
B14: SHIPPING COST | D14: =SUMIFS('Sales Data'!$AE$6:$AE$10000,'Sales Data'!$B$6:$B$10000,"Shopify",'Sales Data'!$BC$6:$BC$10000,$B$7,'Sales Data'!$BD$6:$BD$10000,$C$7)
B15: MCF SHIPPING FEE | D15: =SUMIFS('Sales Data'!$AF$6:$AF$10000,'Sales Data'!$B$6:$B$10000,"Shopify",'Sales Data'!$BC$6:$BC$10000,$B$7,'Sales Data'!$BD$6:$BD$10000,$C$7)
B16: 3PL LABEL COST | D16: =SUMIFS('Sales Data'!$AG$6:$AG$10000,'Sales Data'!$B$6:$B$10000,"Shopify",'Sales Data'!$BC$6:$BC$10000,$B$7,'Sales Data'!$BD$6:$BD$10000,$C$7)
B17: PAYMENT FEES | D17: =SUMIFS('Sales Data'!$AH$6:$AH$10000,'Sales Data'!$B$6:$B$10000,"Shopify",'Sales Data'!$BC$6:$BC$10000,$B$7,'Sales Data'!$BD$6:$BD$10000,$C$7)
B18: COGS | D18: =SUMIFS('Sales Data'!$AI$6:$AI$10000,'Sales Data'!$B$6:$B$10000,"Shopify",'Sales Data'!$BC$6:$BC$10000,$B$7,'Sales Data'!$BD$6:$BD$10000,$C$7)
B19: TAX | D19: =SUMIFS('Sales Data'!$AJ$6:$AJ$10000,'Sales Data'!$B$6:$B$10000,"Shopify",'Sales Data'!$BC$6:$BC$10000,$B$7,'Sales Data'!$BD$6:$BD$10000,$C$7)
B20: GROSS PROFIT (USD) | D20: =SUMIFS('Sales Data'!$AK$6:$AK$10000,'Sales Data'!$B$6:$B$10000,"Shopify",'Sales Data'!$BC$6:$BC$10000,$B$7,'Sales Data'!$BD$6:$BD$10000,$C$7)
B21: NET PROFIT (USD) | D21: =SUMIFS('Sales Data'!$AL$6:$AL$10000,'Sales Data'!$B$6:$B$10000,"Shopify",'Sales Data'!$BC$6:$BC$10000,$B$7,'Sales Data'!$BD$6:$BD$10000,$C$7)
B22: TACOS | D22: =SUMIFS('Sales Data'!$AM$6:$AM$10000,'Sales Data'!$B$6:$B$10000,"Shopify",'Sales Data'!$BC$6:$BC$10000,$B$7,'Sales Data'!$BD$6:$BD$10000,$C$7)
B23: % REFUNDS | D23: =SUMIFS('Sales Data'!$AN$6:$AN$10000,'Sales Data'!$B$6:$B$10000,"Shopify",'Sales Data'!$BC$6:$BC$10000,$B$7,'Sales Data'!$BD$6:$BD$10000,$C$7)
B24: MARGIN | D24: =SUMIFS('Sales Data'!$AO$6:$AO$10000,'Sales Data'!$B$6:$B$10000,"Shopify",'Sales Data'!$BC$6:$BC$10000,$B$7,'Sales Data'!$BD$6:$BD$10000,$C$7)
B25: ROI | D25: =SUMIFS('Sales Data'!$AP$6:$AP$10000,'Sales Data'!$B$6:$B$10000,"Shopify",'Sales Data'!$BC$6:$BC$10000,$B$7,'Sales Data'!$BD$6:$BD$10000,$C$7)
B28: MONTHLY TREND | I28: Trend Year: | J28: 2026
B30: METRIC | C30: Jan | D30: Feb | E30: Mar | F30: Apr | G30: May | H30: Jun | I30: Jul | J30: Aug | K30: Sep | L30: Oct | M30: Nov | N30: Dec | O30: YEAR TOTAL
B31: Sales (USD) | C31: =SUMIFS('Sales Data'!$E$6:$E$10000,'Sales Data'!$B$6:$B$10000,"Shopify",'Sales Data'!$BC$6:$BC$10000,"Jan",'Sales Data'!$BD$6:$BD$10000,$J$28) | D31: =SUMIFS('Sales Data'!$E$6:$E$10000,'Sales Data'!$B$6:$B$10000,"Shopify",'Sales Data'!$BC$6:$BC$10000,"Feb",'Sales Data'!$BD$6:$BD$10000,$J$28) | E31: =SUMIFS('Sales Data'!$E$6:$E$10000,'Sales Data'!$B$6:$B$10000,"Shopify",'Sales Data'!$BC$6:$BC$10000,"Mar",'Sales Data'!$BD$6:$BD$10000,$J$28) | F31: =SUMIFS('Sales Data'!$E$6:$E$10000,'Sales Data'!$B$6:$B$10000,"Shopify",'Sales Data'!$BC$6:$BC$10000,"Apr",'Sales Data'!$BD$6:$BD$10000,$J$28) | G31: =SUMIFS('Sales Data'!$E$6:$E$10000,'Sales Data'!$B$6:$B$10000,"Shopify",'Sales Data'!$BC$6:$BC$10000,"May",'Sales Data'!$BD$6:$BD$10000,$J$28) | H31: =SUMIFS('Sales Data'!$E$6:$E$10000,'Sales Data'!$B$6:$B$10000,"Shopify",'Sales Data'!$BC$6:$BC$10000,"Jun",'Sales Data'!$BD$6:$BD$10000,$J$28) | I31: =SUMIFS('Sales Data'!$E$6:$E$10000,'Sales Data'!$B$6:$B$10000,"Shopify",'Sales Data'!$BC$6:$BC$10000,"Jul",'Sales Data'!$BD$6:$BD$10000,$J$28) | J31: =SUMIFS('Sales Data'!$E$6:$E$10000,'Sales Data'!$B$6:$B$10000,"Shopify",'Sales Data'!$BC$6:$BC$10000,"Aug",'Sales Data'!$BD$6:$BD$10000,$J$28) | K31: =SUMIFS('Sales Data'!$E$6:$E$10000,'Sales Data'!$B$6:$B$10000,"Shopify",'Sales Data'!$BC$6:$BC$10000,"Sep",'Sales Data'!$BD$6:$BD$10000,$J$28) | L31: =SUMIFS('Sales Data'!$E$6:$E$10000,'Sales Data'!$B$6:$B$10000,"Shopify",'Sales Data'!$BC$6:$BC$10000,"Oct",'Sales Data'!$BD$6:$BD$10000,$J$28) | M31: =SUMIFS('Sales Data'!$E$6:$E$10000,'Sales Data'!$B$6:$B$10000,"Shopify",'Sales Data'!$BC$6:$BC$10000,"Nov",'Sales Data'!$BD$6:$BD$10000,$J$28) | N31: =SUMIFS('Sales Data'!$E$6:$E$10000,'Sales Data'!$B$6:$B$10000,"Shopify",'Sales Data'!$BC$6:$BC$10000,"Dec",'Sales Data'!$BD$6:$BD$10000,$J$28) | O31: =SUM(C31:N31)
B32: Units | C32: =SUMIFS('Sales Data'!$G$6:$G$10000,'Sales Data'!$B$6:$B$10000,"Shopify",'Sales Data'!$BC$6:$BC$10000,"Jan",'Sales Data'!$BD$6:$BD$10000,$J$28) | D32: =SUMIFS('Sales Data'!$G$6:$G$10000,'Sales Data'!$B$6:$B$10000,"Shopify",'Sales Data'!$BC$6:$BC$10000,"Feb",'Sales Data'!$BD$6:$BD$10000,$J$28) | E32: =SUMIFS('Sales Data'!$G$6:$G$10000,'Sales Data'!$B$6:$B$10000,"Shopify",'Sales Data'!$BC$6:$BC$10000,"Mar",'Sales Data'!$BD$6:$BD$10000,$J$28) | F32: =SUMIFS('Sales Data'!$G$6:$G$10000,'Sales Data'!$B$6:$B$10000,"Shopify",'Sales Data'!$BC$6:$BC$10000,"Apr",'Sales Data'!$BD$6:$BD$10000,$J$28) | G32: =SUMIFS('Sales Data'!$G$6:$G$10000,'Sales Data'!$B$6:$B$10000,"Shopify",'Sales Data'!$BC$6:$BC$10000,"May",'Sales Data'!$BD$6:$BD$10000,$J$28) | H32: =SUMIFS('Sales Data'!$G$6:$G$10000,'Sales Data'!$B$6:$B$10000,"Shopify",'Sales Data'!$BC$6:$BC$10000,"Jun",'Sales Data'!$BD$6:$BD$10000,$J$28) | I32: =SUMIFS('Sales Data'!$G$6:$G$10000,'Sales Data'!$B$6:$B$10000,"Shopify",'Sales Data'!$BC$6:$BC$10000,"Jul",'Sales Data'!$BD$6:$BD$10000,$J$28) | J32: =SUMIFS('Sales Data'!$G$6:$G$10000,'Sales Data'!$B$6:$B$10000,"Shopify",'Sales Data'!$BC$6:$BC$10000,"Aug",'Sales Data'!$BD$6:$BD$10000,$J$28) | K32: =SUMIFS('Sales Data'!$G$6:$G$10000,'Sales Data'!$B$6:$B$10000,"Shopify",'Sales Data'!$BC$6:$BC$10000,"Sep",'Sales Data'!$BD$6:$BD$10000,$J$28) | L32: =SUMIFS('Sales Data'!$G$6:$G$10000,'Sales Data'!$B$6:$B$10000,"Shopify",'Sales Data'!$BC$6:$BC$10000,"Oct",'Sales Data'!$BD$6:$BD$10000,$J$28) | M32: =SUMIFS('Sales Data'!$G$6:$G$10000,'Sales Data'!$B$6:$B$10000,"Shopify",'Sales Data'!$BC$6:$BC$10000,"Nov",'Sales Data'!$BD$6:$BD$10000,$J$28) | N32: =SUMIFS('Sales Data'!$G$6:$G$10000,'Sales Data'!$B$6:$B$10000,"Shopify",'Sales Data'!$BC$6:$BC$10000,"Dec",'Sales Data'!$BD$6:$BD$10000,$J$28) | O32: =SUM(C32:N32)
B33: Ad Cost | C33: =SUMIFS('Sales Data'!$AD$6:$AD$10000,'Sales Data'!$B$6:$B$10000,"Shopify",'Sales Data'!$BC$6:$BC$10000,"Jan",'Sales Data'!$BD$6:$BD$10000,$J$28) | D33: =SUMIFS('Sales Data'!$AD$6:$AD$10000,'Sales Data'!$B$6:$B$10000,"Shopify",'Sales Data'!$BC$6:$BC$10000,"Feb",'Sales Data'!$BD$6:$BD$10000,$J$28) | E33: =SUMIFS('Sales Data'!$AD$6:$AD$10000,'Sales Data'!$B$6:$B$10000,"Shopify",'Sales Data'!$BC$6:$BC$10000,"Mar",'Sales Data'!$BD$6:$BD$10000,$J$28) | F33: =SUMIFS('Sales Data'!$AD$6:$AD$10000,'Sales Data'!$B$6:$B$10000,"Shopify",'Sales Data'!$BC$6:$BC$10000,"Apr",'Sales Data'!$BD$6:$BD$10000,$J$28) | G33: =SUMIFS('Sales Data'!$AD$6:$AD$10000,'Sales Data'!$B$6:$B$10000,"Shopify",'Sales Data'!$BC$6:$BC$10000,"May",'Sales Data'!$BD$6:$BD$10000,$J$28) | H33: =SUMIFS('Sales Data'!$AD$6:$AD$10000,'Sales Data'!$B$6:$B$10000,"Shopify",'Sales Data'!$BC$6:$BC$10000,"Jun",'Sales Data'!$BD$6:$BD$10000,$J$28) | I33: =SUMIFS('Sales Data'!$AD$6:$AD$10000,'Sales Data'!$B$6:$B$10000,"Shopify",'Sales Data'!$BC$6:$BC$10000,"Jul",'Sales Data'!$BD$6:$BD$10000,$J$28) | J33: =SUMIFS('Sales Data'!$AD$6:$AD$10000,'Sales Data'!$B$6:$B$10000,"Shopify",'Sales Data'!$BC$6:$BC$10000,"Aug",'Sales Data'!$BD$6:$BD$10000,$J$28) | K33: =SUMIFS('Sales Data'!$AD$6:$AD$10000,'Sales Data'!$B$6:$B$10000,"Shopify",'Sales Data'!$BC$6:$BC$10000,"Sep",'Sales Data'!$BD$6:$BD$10000,$J$28) | L33: =SUMIFS('Sales Data'!$AD$6:$AD$10000,'Sales Data'!$B$6:$B$10000,"Shopify",'Sales Data'!$BC$6:$BC$10000,"Oct",'Sales Data'!$BD$6:$BD$10000,$J$28) | M33: =SUMIFS('Sales Data'!$AD$6:$AD$10000,'Sales Data'!$B$6:$B$10000,"Shopify",'Sales Data'!$BC$6:$BC$10000,"Nov",'Sales Data'!$BD$6:$BD$10000,$J$28) | N33: =SUMIFS('Sales Data'!$AD$6:$AD$10000,'Sales Data'!$B$6:$B$10000,"Shopify",'Sales Data'!$BC$6:$BC$10000,"Dec",'Sales Data'!$BD$6:$BD$10000,$J$28) | O33: =SUM(C33:N33)
B34: COGS | C34: =SUMIFS('Sales Data'!$AI$6:$AI$10000,'Sales Data'!$B$6:$B$10000,"Shopify",'Sales Data'!$BC$6:$BC$10000,"Jan",'Sales Data'!$BD$6:$BD$10000,$J$28) | D34: =SUMIFS('Sales Data'!$AI$6:$AI$10000,'Sales Data'!$B$6:$B$10000,"Shopify",'Sales Data'!$BC$6:$BC$10000,"Feb",'Sales Data'!$BD$6:$BD$10000,$J$28) | E34: =SUMIFS('Sales Data'!$AI$6:$AI$10000,'Sales Data'!$B$6:$B$10000,"Shopify",'Sales Data'!$BC$6:$BC$10000,"Mar",'Sales Data'!$BD$6:$BD$10000,$J$28) | F34: =SUMIFS('Sales Data'!$AI$6:$AI$10000,'Sales Data'!$B$6:$B$10000,"Shopify",'Sales Data'!$BC$6:$BC$10000,"Apr",'Sales Data'!$BD$6:$BD$10000,$J$28) | G34: =SUMIFS('Sales Data'!$AI$6:$AI$10000,'Sales Data'!$B$6:$B$10000,"Shopify",'Sales Data'!$BC$6:$BC$10000,"May",'Sales Data'!$BD$6:$BD$10000,$J$28) | H34: =SUMIFS('Sales Data'!$AI$6:$AI$10000,'Sales Data'!$B$6:$B$10000,"Shopify",'Sales Data'!$BC$6:$BC$10000,"Jun",'Sales Data'!$BD$6:$BD$10000,$J$28) | I34: =SUMIFS('Sales Data'!$AI$6:$AI$10000,'Sales Data'!$B$6:$B$10000,"Shopify",'Sales Data'!$BC$6:$BC$10000,"Jul",'Sales Data'!$BD$6:$BD$10000,$J$28) | J34: =SUMIFS('Sales Data'!$AI$6:$AI$10000,'Sales Data'!$B$6:$B$10000,"Shopify",'Sales Data'!$BC$6:$BC$10000,"Aug",'Sales Data'!$BD$6:$BD$10000,$J$28) | K34: =SUMIFS('Sales Data'!$AI$6:$AI$10000,'Sales Data'!$B$6:$B$10000,"Shopify",'Sales Data'!$BC$6:$BC$10000,"Sep",'Sales Data'!$BD$6:$BD$10000,$J$28) | L34: =SUMIFS('Sales Data'!$AI$6:$AI$10000,'Sales Data'!$B$6:$B$10000,"Shopify",'Sales Data'!$BC$6:$BC$10000,"Oct",'Sales Data'!$BD$6:$BD$10000,$J$28) | M34: =SUMIFS('Sales Data'!$AI$6:$AI$10000,'Sales Data'!$B$6:$B$10000,"Shopify",'Sales Data'!$BC$6:$BC$10000,"Nov",'Sales Data'!$BD$6:$BD$10000,$J$28) | N34: =SUMIFS('Sales Data'!$AI$6:$AI$10000,'Sales Data'!$B$6:$B$10000,"Shopify",'Sales Data'!$BC$6:$BC$10000,"Dec",'Sales Data'!$BD$6:$BD$10000,$J$28) | O34: =SUM(C34:N34)
B35: Gross Profit | C35: =SUMIFS('Sales Data'!$AK$6:$AK$10000,'Sales Data'!$B$6:$B$10000,"Shopify",'Sales Data'!$BC$6:$BC$10000,"Jan",'Sales Data'!$BD$6:$BD$10000,$J$28) | D35: =SUMIFS('Sales Data'!$AK$6:$AK$10000,'Sales Data'!$B$6:$B$10000,"Shopify",'Sales Data'!$BC$6:$BC$10000,"Feb",'Sales Data'!$BD$6:$BD$10000,$J$28) | E35: =SUMIFS('Sales Data'!$AK$6:$AK$10000,'Sales Data'!$B$6:$B$10000,"Shopify",'Sales Data'!$BC$6:$BC$10000,"Mar",'Sales Data'!$BD$6:$BD$10000,$J$28) | F35: =SUMIFS('Sales Data'!$AK$6:$AK$10000,'Sales Data'!$B$6:$B$10000,"Shopify",'Sales Data'!$BC$6:$BC$10000,"Apr",'Sales Data'!$BD$6:$BD$10000,$J$28) | G35: =SUMIFS('Sales Data'!$AK$6:$AK$10000,'Sales Data'!$B$6:$B$10000,"Shopify",'Sales Data'!$BC$6:$BC$10000,"May",'Sales Data'!$BD$6:$BD$10000,$J$28) | H35: =SUMIFS('Sales Data'!$AK$6:$AK$10000,'Sales Data'!$B$6:$B$10000,"Shopify",'Sales Data'!$BC$6:$BC$10000,"Jun",'Sales Data'!$BD$6:$BD$10000,$J$28) | I35: =SUMIFS('Sales Data'!$AK$6:$AK$10000,'Sales Data'!$B$6:$B$10000,"Shopify",'Sales Data'!$BC$6:$BC$10000,"Jul",'Sales Data'!$BD$6:$BD$10000,$J$28) | J35: =SUMIFS('Sales Data'!$AK$6:$AK$10000,'Sales Data'!$B$6:$B$10000,"Shopify",'Sales Data'!$BC$6:$BC$10000,"Aug",'Sales Data'!$BD$6:$BD$10000,$J$28) | K35: =SUMIFS('Sales Data'!$AK$6:$AK$10000,'Sales Data'!$B$6:$B$10000,"Shopify",'Sales Data'!$BC$6:$BC$10000,"Sep",'Sales Data'!$BD$6:$BD$10000,$J$28) | L35: =SUMIFS('Sales Data'!$AK$6:$AK$10000,'Sales Data'!$B$6:$B$10000,"Shopify",'Sales Data'!$BC$6:$BC$10000,"Oct",'Sales Data'!$BD$6:$BD$10000,$J$28) | M35: =SUMIFS('Sales Data'!$AK$6:$AK$10000,'Sales Data'!$B$6:$B$10000,"Shopify",'Sales Data'!$BC$6:$BC$10000,"Nov",'Sales Data'!$BD$6:$BD$10000,$J$28) | N35: =SUMIFS('Sales Data'!$AK$6:$AK$10000,'Sales Data'!$B$6:$B$10000,"Shopify",'Sales Data'!$BC$6:$BC$10000,"Dec",'Sales Data'!$BD$6:$BD$10000,$J$28) | O35: =SUM(C35:N35)
B36: Net Profit | C36: =SUMIFS('Sales Data'!$AL$6:$AL$10000,'Sales Data'!$B$6:$B$10000,"Shopify",'Sales Data'!$BC$6:$BC$10000,"Jan",'Sales Data'!$BD$6:$BD$10000,$J$28) | D36: =SUMIFS('Sales Data'!$AL$6:$AL$10000,'Sales Data'!$B$6:$B$10000,"Shopify",'Sales Data'!$BC$6:$BC$10000,"Feb",'Sales Data'!$BD$6:$BD$10000,$J$28) | E36: =SUMIFS('Sales Data'!$AL$6:$AL$10000,'Sales Data'!$B$6:$B$10000,"Shopify",'Sales Data'!$BC$6:$BC$10000,"Mar",'Sales Data'!$BD$6:$BD$10000,$J$28) | F36: =SUMIFS('Sales Data'!$AL$6:$AL$10000,'Sales Data'!$B$6:$B$10000,"Shopify",'Sales Data'!$BC$6:$BC$10000,"Apr",'Sales Data'!$BD$6:$BD$10000,$J$28) | G36: =SUMIFS('Sales Data'!$AL$6:$AL$10000,'Sales Data'!$B$6:$B$10000,"Shopify",'Sales Data'!$BC$6:$BC$10000,"May",'Sales Data'!$BD$6:$BD$10000,$J$28) | H36: =SUMIFS('Sales Data'!$AL$6:$AL$10000,'Sales Data'!$B$6:$B$10000,"Shopify",'Sales Data'!$BC$6:$BC$10000,"Jun",'Sales Data'!$BD$6:$BD$10000,$J$28) | I36: =SUMIFS('Sales Data'!$AL$6:$AL$10000,'Sales Data'!$B$6:$B$10000,"Shopify",'Sales Data'!$BC$6:$BC$10000,"Jul",'Sales Data'!$BD$6:$BD$10000,$J$28) | J36: =SUMIFS('Sales Data'!$AL$6:$AL$10000,'Sales Data'!$B$6:$B$10000,"Shopify",'Sales Data'!$BC$6:$BC$10000,"Aug",'Sales Data'!$BD$6:$BD$10000,$J$28) | K36: =SUMIFS('Sales Data'!$AL$6:$AL$10000,'Sales Data'!$B$6:$B$10000,"Shopify",'Sales Data'!$BC$6:$BC$10000,"Sep",'Sales Data'!$BD$6:$BD$10000,$J$28) | L36: =SUMIFS('Sales Data'!$AL$6:$AL$10000,'Sales Data'!$B$6:$B$10000,"Shopify",'Sales Data'!$BC$6:$BC$10000,"Oct",'Sales Data'!$BD$6:$BD$10000,$J$28) | M36: =SUMIFS('Sales Data'!$AL$6:$AL$10000,'Sales Data'!$B$6:$B$10000,"Shopify",'Sales Data'!$BC$6:$BC$10000,"Nov",'Sales Data'!$BD$6:$BD$10000,$J$28) | N36: =SUMIFS('Sales Data'!$AL$6:$AL$10000,'Sales Data'!$B$6:$B$10000,"Shopify",'Sales Data'!$BC$6:$BC$10000,"Dec",'Sales Data'!$BD$6:$BD$10000,$J$28) | O36: =SUM(C36:N36)
B37: TACOS | C37: =SUMIFS('Sales Data'!$AM$6:$AM$10000,'Sales Data'!$B$6:$B$10000,"Shopify",'Sales Data'!$BC$6:$BC$10000,"Jan",'Sales Data'!$BD$6:$BD$10000,$J$28) | D37: =SUMIFS('Sales Data'!$AM$6:$AM$10000,'Sales Data'!$B$6:$B$10000,"Shopify",'Sales Data'!$BC$6:$BC$10000,"Feb",'Sales Data'!$BD$6:$BD$10000,$J$28) | E37: =SUMIFS('Sales Data'!$AM$6:$AM$10000,'Sales Data'!$B$6:$B$10000,"Shopify",'Sales Data'!$BC$6:$BC$10000,"Mar",'Sales Data'!$BD$6:$BD$10000,$J$28) | F37: =SUMIFS('Sales Data'!$AM$6:$AM$10000,'Sales Data'!$B$6:$B$10000,"Shopify",'Sales Data'!$BC$6:$BC$10000,"Apr",'Sales Data'!$BD$6:$BD$10000,$J$28) | G37: =SUMIFS('Sales Data'!$AM$6:$AM$10000,'Sales Data'!$B$6:$B$10000,"Shopify",'Sales Data'!$BC$6:$BC$10000,"May",'Sales Data'!$BD$6:$BD$10000,$J$28) | H37: =SUMIFS('Sales Data'!$AM$6:$AM$10000,'Sales Data'!$B$6:$B$10000,"Shopify",'Sales Data'!$BC$6:$BC$10000,"Jun",'Sales Data'!$BD$6:$BD$10000,$J$28) | I37: =SUMIFS('Sales Data'!$AM$6:$AM$10000,'Sales Data'!$B$6:$B$10000,"Shopify",'Sales Data'!$BC$6:$BC$10000,"Jul",'Sales Data'!$BD$6:$BD$10000,$J$28) | J37: =SUMIFS('Sales Data'!$AM$6:$AM$10000,'Sales Data'!$B$6:$B$10000,"Shopify",'Sales Data'!$BC$6:$BC$10000,"Aug",'Sales Data'!$BD$6:$BD$10000,$J$28) | K37: =SUMIFS('Sales Data'!$AM$6:$AM$10000,'Sales Data'!$B$6:$B$10000,"Shopify",'Sales Data'!$BC$6:$BC$10000,"Sep",'Sales Data'!$BD$6:$BD$10000,$J$28) | L37: =SUMIFS('Sales Data'!$AM$6:$AM$10000,'Sales Data'!$B$6:$B$10000,"Shopify",'Sales Data'!$BC$6:$BC$10000,"Oct",'Sales Data'!$BD$6:$BD$10000,$J$28) | M37: =SUMIFS('Sales Data'!$AM$6:$AM$10000,'Sales Data'!$B$6:$B$10000,"Shopify",'Sales Data'!$BC$6:$BC$10000,"Nov",'Sales Data'!$BD$6:$BD$10000,$J$28) | N37: =SUMIFS('Sales Data'!$AM$6:$AM$10000,'Sales Data'!$B$6:$B$10000,"Shopify",'Sales Data'!$BC$6:$BC$10000,"Dec",'Sales Data'!$BD$6:$BD$10000,$J$28) | O37: =IFERROR(AVERAGE(C37:N37),0)
B38: Margin | C38: =SUMIFS('Sales Data'!$AO$6:$AO$10000,'Sales Data'!$B$6:$B$10000,"Shopify",'Sales Data'!$BC$6:$BC$10000,"Jan",'Sales Data'!$BD$6:$BD$10000,$J$28) | D38: =SUMIFS('Sales Data'!$AO$6:$AO$10000,'Sales Data'!$B$6:$B$10000,"Shopify",'Sales Data'!$BC$6:$BC$10000,"Feb",'Sales Data'!$BD$6:$BD$10000,$J$28) | E38: =SUMIFS('Sales Data'!$AO$6:$AO$10000,'Sales Data'!$B$6:$B$10000,"Shopify",'Sales Data'!$BC$6:$BC$10000,"Mar",'Sales Data'!$BD$6:$BD$10000,$J$28) | F38: =SUMIFS('Sales Data'!$AO$6:$AO$10000,'Sales Data'!$B$6:$B$10000,"Shopify",'Sales Data'!$BC$6:$BC$10000,"Apr",'Sales Data'!$BD$6:$BD$10000,$J$28) | G38: =SUMIFS('Sales Data'!$AO$6:$AO$10000,'Sales Data'!$B$6:$B$10000,"Shopify",'Sales Data'!$BC$6:$BC$10000,"May",'Sales Data'!$BD$6:$BD$10000,$J$28) | H38: =SUMIFS('Sales Data'!$AO$6:$AO$10000,'Sales Data'!$B$6:$B$10000,"Shopify",'Sales Data'!$BC$6:$BC$10000,"Jun",'Sales Data'!$BD$6:$BD$10000,$J$28) | I38: =SUMIFS('Sales Data'!$AO$6:$AO$10000,'Sales Data'!$B$6:$B$10000,"Shopify",'Sales Data'!$BC$6:$BC$10000,"Jul",'Sales Data'!$BD$6:$BD$10000,$J$28) | J38: =SUMIFS('Sales Data'!$AO$6:$AO$10000,'Sales Data'!$B$6:$B$10000,"Shopify",'Sales Data'!$BC$6:$BC$10000,"Aug",'Sales Data'!$BD$6:$BD$10000,$J$28) | K38: =SUMIFS('Sales Data'!$AO$6:$AO$10000,'Sales Data'!$B$6:$B$10000,"Shopify",'Sales Data'!$BC$6:$BC$10000,"Sep",'Sales Data'!$BD$6:$BD$10000,$J$28) | L38: =SUMIFS('Sales Data'!$AO$6:$AO$10000,'Sales Data'!$B$6:$B$10000,"Shopify",'Sales Data'!$BC$6:$BC$10000,"Oct",'Sales Data'!$BD$6:$BD$10000,$J$28) | M38: =SUMIFS('Sales Data'!$AO$6:$AO$10000,'Sales Data'!$B$6:$B$10000,"Shopify",'Sales Data'!$BC$6:$BC$10000,"Nov",'Sales Data'!$BD$6:$BD$10000,$J$28) | N38: =SUMIFS('Sales Data'!$AO$6:$AO$10000,'Sales Data'!$B$6:$B$10000,"Shopify",'Sales Data'!$BC$6:$BC$10000,"Dec",'Sales Data'!$BD$6:$BD$10000,$J$28) | O38: =IFERROR(AVERAGE(C38:N38),0)
B41: EXPENSE BREAKDOWN · MAIN & SUB CATEGORY | J41: SALES BREAKDOWN · SUB-CATEGORY
B42: CATEGORY | C42: AMOUNT | D42: % OF EXPENSES | J42: SUB CATEGORY | K42: SALES AMOUNT | L42: % OF SALES
B43: Advertising cost | C43: =IFERROR(SUMIFS('Main Expenses'!$E$6:$E$10000,'Main Expenses'!$B$6:$B$10000,"Shopify",'Main Expenses'!$D$6:$D$10000,"Advertising cost",'Main Expenses'!$K$6:$K$10000,$B$7,'Main Expenses'!$L$6:$L$10000,$C$7),0) | D43: =IFERROR(C43/SUMIFS('Main Expenses'!$E$6:$E$10000,'Main Expenses'!$B$6:$B$10000,"Shopify",'Main Expenses'!$K$6:$K$10000,$B$7,'Main Expenses'!$L$6:$L$10000,$C$7),0) | J43: Gross sales | K43: =IFERROR(SUMIFS('Sales Data'!$E$6:$E$10000,'Sales Data'!$B$6:$B$10000,"Shopify",'Sales Data'!$D$6:$D$10000,"Gross sales",'Sales Data'!$BC$6:$BC$10000,$B$7,'Sales Data'!$BD$6:$BD$10000,$C$7),0) | L43: =IFERROR(K43/SUMIFS('Sales Data'!$E$6:$E$10000,'Sales Data'!$B$6:$B$10000,"Shopify",'Sales Data'!$BC$6:$BC$10000,$B$7,'Sales Data'!$BD$6:$BD$10000,$C$7),0)
B44: ↳ Advertising Cost | C44: =IFERROR(SUMIFS('Sub Expenses'!$E$6:$E$10000,'Sub Expenses'!$B$6:$B$10000,"Shopify",'Sub Expenses'!$C$6:$C$10000,"Advertising cost",'Sub Expenses'!$D$6:$D$10000,"Advertising Cost",'Sub Expenses'!$J$6:$J$10000,$B$7,'Sub Expenses'!$K$6:$K$10000,$C$7),0) | D44: =IFERROR(C44/SUMIFS('Main Expenses'!$E$6:$E$10000,'Main Expenses'!$B$6:$B$10000,"Shopify",'Main Expenses'!$K$6:$K$10000,$B$7,'Main Expenses'!$L$6:$L$10000,$C$7),0) | J44: Promo | K44: =IFERROR(SUMIFS('Sales Data'!$E$6:$E$10000,'Sales Data'!$B$6:$B$10000,"Shopify",'Sales Data'!$D$6:$D$10000,"Promo",'Sales Data'!$BC$6:$BC$10000,$B$7,'Sales Data'!$BD$6:$BD$10000,$C$7),0) | L44: =IFERROR(K44/SUMIFS('Sales Data'!$E$6:$E$10000,'Sales Data'!$B$6:$B$10000,"Shopify",'Sales Data'!$BC$6:$BC$10000,$B$7,'Sales Data'!$BD$6:$BD$10000,$C$7),0)
B45: Cost of goods | C45: =IFERROR(SUMIFS('Main Expenses'!$E$6:$E$10000,'Main Expenses'!$B$6:$B$10000,"Shopify",'Main Expenses'!$D$6:$D$10000,"Cost of goods",'Main Expenses'!$K$6:$K$10000,$B$7,'Main Expenses'!$L$6:$L$10000,$C$7),0) | D45: =IFERROR(C45/SUMIFS('Main Expenses'!$E$6:$E$10000,'Main Expenses'!$B$6:$B$10000,"Shopify",'Main Expenses'!$K$6:$K$10000,$B$7,'Main Expenses'!$L$6:$L$10000,$C$7),0) | J45: Shipping | K45: =IFERROR(SUMIFS('Sales Data'!$E$6:$E$10000,'Sales Data'!$B$6:$B$10000,"Shopify",'Sales Data'!$D$6:$D$10000,"Shipping",'Sales Data'!$BC$6:$BC$10000,$B$7,'Sales Data'!$BD$6:$BD$10000,$C$7),0) | L45: =IFERROR(K45/SUMIFS('Sales Data'!$E$6:$E$10000,'Sales Data'!$B$6:$B$10000,"Shopify",'Sales Data'!$BC$6:$BC$10000,$B$7,'Sales Data'!$BD$6:$BD$10000,$C$7),0)
B46: ↳ Cost of goods sold | C46: =IFERROR(SUMIFS('Sub Expenses'!$E$6:$E$10000,'Sub Expenses'!$B$6:$B$10000,"Shopify",'Sub Expenses'!$C$6:$C$10000,"Cost of goods",'Sub Expenses'!$D$6:$D$10000,"Cost of goods sold",'Sub Expenses'!$J$6:$J$10000,$B$7,'Sub Expenses'!$K$6:$K$10000,$C$7),0) | D46: =IFERROR(C46/SUMIFS('Main Expenses'!$E$6:$E$10000,'Main Expenses'!$B$6:$B$10000,"Shopify",'Main Expenses'!$K$6:$K$10000,$B$7,'Main Expenses'!$L$6:$L$10000,$C$7),0) | J46: Sales tax | K46: =IFERROR(SUMIFS('Sales Data'!$E$6:$E$10000,'Sales Data'!$B$6:$B$10000,"Shopify",'Sales Data'!$D$6:$D$10000,"Sales tax",'Sales Data'!$BC$6:$BC$10000,$B$7,'Sales Data'!$BD$6:$BD$10000,$C$7),0) | L46: =IFERROR(K46/SUMIFS('Sales Data'!$E$6:$E$10000,'Sales Data'!$B$6:$B$10000,"Shopify",'Sales Data'!$BC$6:$BC$10000,$B$7,'Sales Data'!$BD$6:$BD$10000,$C$7),0)
B47: Payment fees | C47: =IFERROR(SUMIFS('Main Expenses'!$E$6:$E$10000,'Main Expenses'!$B$6:$B$10000,"Shopify",'Main Expenses'!$D$6:$D$10000,"Payment fees",'Main Expenses'!$K$6:$K$10000,$B$7,'Main Expenses'!$L$6:$L$10000,$C$7),0) | D47: =IFERROR(C47/SUMIFS('Main Expenses'!$E$6:$E$10000,'Main Expenses'!$B$6:$B$10000,"Shopify",'Main Expenses'!$K$6:$K$10000,$B$7,'Main Expenses'!$L$6:$L$10000,$C$7),0) | J47: Refunded amount | K47: =IFERROR(SUMIFS('Sales Data'!$E$6:$E$10000,'Sales Data'!$B$6:$B$10000,"Shopify",'Sales Data'!$D$6:$D$10000,"Refunded amount",'Sales Data'!$BC$6:$BC$10000,$B$7,'Sales Data'!$BD$6:$BD$10000,$C$7),0) | L47: =IFERROR(K47/SUMIFS('Sales Data'!$E$6:$E$10000,'Sales Data'!$B$6:$B$10000,"Shopify",'Sales Data'!$BC$6:$BC$10000,$B$7,'Sales Data'!$BD$6:$BD$10000,$C$7),0)
B48: ↳ Shopify Payments fee | C48: =IFERROR(SUMIFS('Sub Expenses'!$E$6:$E$10000,'Sub Expenses'!$B$6:$B$10000,"Shopify",'Sub Expenses'!$C$6:$C$10000,"Payment fees",'Sub Expenses'!$D$6:$D$10000,"Shopify Payments fee",'Sub Expenses'!$J$6:$J$10000,$B$7,'Sub Expenses'!$K$6:$K$10000,$C$7),0) | D48: =IFERROR(C48/SUMIFS('Main Expenses'!$E$6:$E$10000,'Main Expenses'!$B$6:$B$10000,"Shopify",'Main Expenses'!$K$6:$K$10000,$B$7,'Main Expenses'!$L$6:$L$10000,$C$7),0) | J48: Refunded shipping | K48: =IFERROR(SUMIFS('Sales Data'!$E$6:$E$10000,'Sales Data'!$B$6:$B$10000,"Shopify",'Sales Data'!$D$6:$D$10000,"Refunded shipping",'Sales Data'!$BC$6:$BC$10000,$B$7,'Sales Data'!$BD$6:$BD$10000,$C$7),0) | L48: =IFERROR(K48/SUMIFS('Sales Data'!$E$6:$E$10000,'Sales Data'!$B$6:$B$10000,"Shopify",'Sales Data'!$BC$6:$BC$10000,$B$7,'Sales Data'!$BD$6:$BD$10000,$C$7),0)
B49: Tax | C49: =IFERROR(SUMIFS('Main Expenses'!$E$6:$E$10000,'Main Expenses'!$B$6:$B$10000,"Shopify",'Main Expenses'!$D$6:$D$10000,"Tax",'Main Expenses'!$K$6:$K$10000,$B$7,'Main Expenses'!$L$6:$L$10000,$C$7),0) | D49: =IFERROR(C49/SUMIFS('Main Expenses'!$E$6:$E$10000,'Main Expenses'!$B$6:$B$10000,"Shopify",'Main Expenses'!$K$6:$K$10000,$B$7,'Main Expenses'!$L$6:$L$10000,$C$7),0)
B50: ↳ Anderson Co Education Capital Improvement | C50: =IFERROR(SUMIFS('Sub Expenses'!$E$6:$E$10000,'Sub Expenses'!$B$6:$B$10000,"Shopify",'Sub Expenses'!$C$6:$C$10000,"Tax",'Sub Expenses'!$D$6:$D$10000,"Anderson Co Education Capital Improvement",'Sub Expenses'!$J$6:$J$10000,$B$7,'Sub Expenses'!$K$6:$K$10000,$C$7),0) | D50: =IFERROR(C50/SUMIFS('Main Expenses'!$E$6:$E$10000,'Main Expenses'!$B$6:$B$10000,"Shopify",'Main Expenses'!$K$6:$K$10000,$B$7,'Main Expenses'!$L$6:$L$10000,$C$7),0)
B51: ↳ CONTRA COSTA CO LOC | C51: =IFERROR(SUMIFS('Sub Expenses'!$E$6:$E$10000,'Sub Expenses'!$B$6:$B$10000,"Shopify",'Sub Expenses'!$C$6:$C$10000,"Tax",'Sub Expenses'!$D$6:$D$10000,"CONTRA COSTA CO LOC",'Sub Expenses'!$J$6:$J$10000,$B$7,'Sub Expenses'!$K$6:$K$10000,$C$7),0) | D51: =IFERROR(C51/SUMIFS('Main Expenses'!$E$6:$E$10000,'Main Expenses'!$B$6:$B$10000,"Shopify",'Main Expenses'!$K$6:$K$10000,$B$7,'Main Expenses'!$L$6:$L$10000,$C$7),0)
B52: ↳ CONTRA COSTA COUNTY | C52: =IFERROR(SUMIFS('Sub Expenses'!$E$6:$E$10000,'Sub Expenses'!$B$6:$B$10000,"Shopify",'Sub Expenses'!$C$6:$C$10000,"Tax",'Sub Expenses'!$D$6:$D$10000,"CONTRA COSTA COUNTY",'Sub Expenses'!$J$6:$J$10000,$B$7,'Sub Expenses'!$K$6:$K$10000,$C$7),0) | D52: =IFERROR(C52/SUMIFS('Main Expenses'!$E$6:$E$10000,'Main Expenses'!$B$6:$B$10000,"Shopify",'Main Expenses'!$K$6:$K$10000,$B$7,'Main Expenses'!$L$6:$L$10000,$C$7),0)
B53: ↳ California State Tax | C53: =IFERROR(SUMIFS('Sub Expenses'!$E$6:$E$10000,'Sub Expenses'!$B$6:$B$10000,"Shopify",'Sub Expenses'!$C$6:$C$10000,"Tax",'Sub Expenses'!$D$6:$D$10000,"California State Tax",'Sub Expenses'!$J$6:$J$10000,$B$7,'Sub Expenses'!$K$6:$K$10000,$C$7),0) | D53: =IFERROR(C53/SUMIFS('Main Expenses'!$E$6:$E$10000,'Main Expenses'!$B$6:$B$10000,"Shopify",'Main Expenses'!$K$6:$K$10000,$B$7,'Main Expenses'!$L$6:$L$10000,$C$7),0)
B54: ↳ Contra Costa County Tax | C54: =IFERROR(SUMIFS('Sub Expenses'!$E$6:$E$10000,'Sub Expenses'!$B$6:$B$10000,"Shopify",'Sub Expenses'!$C$6:$C$10000,"Tax",'Sub Expenses'!$D$6:$D$10000,"Contra Costa County Tax",'Sub Expenses'!$J$6:$J$10000,$B$7,'Sub Expenses'!$K$6:$K$10000,$C$7),0) | D54: =IFERROR(C54/SUMIFS('Main Expenses'!$E$6:$E$10000,'Main Expenses'!$B$6:$B$10000,"Shopify",'Main Expenses'!$K$6:$K$10000,$B$7,'Main Expenses'!$L$6:$L$10000,$C$7),0)
B55: ↳ Cuyahoga County Tax | C55: =IFERROR(SUMIFS('Sub Expenses'!$E$6:$E$10000,'Sub Expenses'!$B$6:$B$10000,"Shopify",'Sub Expenses'!$C$6:$C$10000,"Tax",'Sub Expenses'!$D$6:$D$10000,"Cuyahoga County Tax",'Sub Expenses'!$J$6:$J$10000,$B$7,'Sub Expenses'!$K$6:$K$10000,$C$7),0) | D55: =IFERROR(C55/SUMIFS('Main Expenses'!$E$6:$E$10000,'Main Expenses'!$B$6:$B$10000,"Shopify",'Main Expenses'!$K$6:$K$10000,$B$7,'Main Expenses'!$L$6:$L$10000,$C$7),0)
B56: ↳ Dekalb Co Tsplost Sp | C56: =IFERROR(SUMIFS('Sub Expenses'!$E$6:$E$10000,'Sub Expenses'!$B$6:$B$10000,"Shopify",'Sub Expenses'!$C$6:$C$10000,"Tax",'Sub Expenses'!$D$6:$D$10000,"Dekalb Co Tsplost Sp",'Sub Expenses'!$J$6:$J$10000,$B$7,'Sub Expenses'!$K$6:$K$10000,$C$7),0) | D56: =IFERROR(C56/SUMIFS('Main Expenses'!$E$6:$E$10000,'Main Expenses'!$B$6:$B$10000,"Shopify",'Main Expenses'!$K$6:$K$10000,$B$7,'Main Expenses'!$L$6:$L$10000,$C$7),0)
B57: ↳ Dekalb County Tax | C57: =IFERROR(SUMIFS('Sub Expenses'!$E$6:$E$10000,'Sub Expenses'!$B$6:$B$10000,"Shopify",'Sub Expenses'!$C$6:$C$10000,"Tax",'Sub Expenses'!$D$6:$D$10000,"Dekalb County Tax",'Sub Expenses'!$J$6:$J$10000,$B$7,'Sub Expenses'!$K$6:$K$10000,$C$7),0) | D57: =IFERROR(C57/SUMIFS('Main Expenses'!$E$6:$E$10000,'Main Expenses'!$B$6:$B$10000,"Shopify",'Main Expenses'!$K$6:$K$10000,$B$7,'Main Expenses'!$L$6:$L$10000,$C$7),0)
B58: ↳ Duval County Tax | C58: =IFERROR(SUMIFS('Sub Expenses'!$E$6:$E$10000,'Sub Expenses'!$B$6:$B$10000,"Shopify",'Sub Expenses'!$C$6:$C$10000,"Tax",'Sub Expenses'!$D$6:$D$10000,"Duval County Tax",'Sub Expenses'!$J$6:$J$10000,$B$7,'Sub Expenses'!$K$6:$K$10000,$C$7),0) | D58: =IFERROR(C58/SUMIFS('Main Expenses'!$E$6:$E$10000,'Main Expenses'!$B$6:$B$10000,"Shopify",'Main Expenses'!$K$6:$K$10000,$B$7,'Main Expenses'!$L$6:$L$10000,$C$7),0)
B59: ↳ Federal Way City Tax | C59: =IFERROR(SUMIFS('Sub Expenses'!$E$6:$E$10000,'Sub Expenses'!$B$6:$B$10000,"Shopify",'Sub Expenses'!$C$6:$C$10000,"Tax",'Sub Expenses'!$D$6:$D$10000,"Federal Way City Tax",'Sub Expenses'!$J$6:$J$10000,$B$7,'Sub Expenses'!$K$6:$K$10000,$C$7),0) | D59: =IFERROR(C59/SUMIFS('Main Expenses'!$E$6:$E$10000,'Main Expenses'!$B$6:$B$10000,"Shopify",'Main Expenses'!$K$6:$K$10000,$B$7,'Main Expenses'!$L$6:$L$10000,$C$7),0)
B60: ↳ Florida State Tax | C60: =IFERROR(SUMIFS('Sub Expenses'!$E$6:$E$10000,'Sub Expenses'!$B$6:$B$10000,"Shopify",'Sub Expenses'!$C$6:$C$10000,"Tax",'Sub Expenses'!$D$6:$D$10000,"Florida State Tax",'Sub Expenses'!$J$6:$J$10000,$B$7,'Sub Expenses'!$K$6:$K$10000,$C$7),0) | D60: =IFERROR(C60/SUMIFS('Main Expenses'!$E$6:$E$10000,'Main Expenses'!$B$6:$B$10000,"Shopify",'Main Expenses'!$K$6:$K$10000,$B$7,'Main Expenses'!$L$6:$L$10000,$C$7),0)
B61: ↳ Forsyth County Tax | C61: =IFERROR(SUMIFS('Sub Expenses'!$E$6:$E$10000,'Sub Expenses'!$B$6:$B$10000,"Shopify",'Sub Expenses'!$C$6:$C$10000,"Tax",'Sub Expenses'!$D$6:$D$10000,"Forsyth County Tax",'Sub Expenses'!$J$6:$J$10000,$B$7,'Sub Expenses'!$K$6:$K$10000,$C$7),0) | D61: =IFERROR(C61/SUMIFS('Main Expenses'!$E$6:$E$10000,'Main Expenses'!$B$6:$B$10000,"Shopify",'Main Expenses'!$K$6:$K$10000,$B$7,'Main Expenses'!$L$6:$L$10000,$C$7),0)
B62: ↳ Galveston City Tax | C62: =IFERROR(SUMIFS('Sub Expenses'!$E$6:$E$10000,'Sub Expenses'!$B$6:$B$10000,"Shopify",'Sub Expenses'!$C$6:$C$10000,"Tax",'Sub Expenses'!$D$6:$D$10000,"Galveston City Tax",'Sub Expenses'!$J$6:$J$10000,$B$7,'Sub Expenses'!$K$6:$K$10000,$C$7),0) | D62: =IFERROR(C62/SUMIFS('Main Expenses'!$E$6:$E$10000,'Main Expenses'!$B$6:$B$10000,"Shopify",'Main Expenses'!$K$6:$K$10000,$B$7,'Main Expenses'!$L$6:$L$10000,$C$7),0)
B63: ↳ Georgia State Tax | C63: =IFERROR(SUMIFS('Sub Expenses'!$E$6:$E$10000,'Sub Expenses'!$B$6:$B$10000,"Shopify",'Sub Expenses'!$C$6:$C$10000,"Tax",'Sub Expenses'!$D$6:$D$10000,"Georgia State Tax",'Sub Expenses'!$J$6:$J$10000,$B$7,'Sub Expenses'!$K$6:$K$10000,$C$7),0) | D63: =IFERROR(C63/SUMIFS('Main Expenses'!$E$6:$E$10000,'Main Expenses'!$B$6:$B$10000,"Shopify",'Main Expenses'!$K$6:$K$10000,$B$7,'Main Expenses'!$L$6:$L$10000,$C$7),0)
B64: ↳ Henrico Co Sp | C64: =IFERROR(SUMIFS('Sub Expenses'!$E$6:$E$10000,'Sub Expenses'!$B$6:$B$10000,"Shopify",'Sub Expenses'!$C$6:$C$10000,"Tax",'Sub Expenses'!$D$6:$D$10000,"Henrico Co Sp",'Sub Expenses'!$J$6:$J$10000,$B$7,'Sub Expenses'!$K$6:$K$10000,$C$7),0) | D64: =IFERROR(C64/SUMIFS('Main Expenses'!$E$6:$E$10000,'Main Expenses'!$B$6:$B$10000,"Shopify",'Main Expenses'!$K$6:$K$10000,$B$7,'Main Expenses'!$L$6:$L$10000,$C$7),0)
B65: ↳ Henrico County Tax | C65: =IFERROR(SUMIFS('Sub Expenses'!$E$6:$E$10000,'Sub Expenses'!$B$6:$B$10000,"Shopify",'Sub Expenses'!$C$6:$C$10000,"Tax",'Sub Expenses'!$D$6:$D$10000,"Henrico County Tax",'Sub Expenses'!$J$6:$J$10000,$B$7,'Sub Expenses'!$K$6:$K$10000,$C$7),0) | D65: =IFERROR(C65/SUMIFS('Main Expenses'!$E$6:$E$10000,'Main Expenses'!$B$6:$B$10000,"Shopify",'Main Expenses'!$K$6:$K$10000,$B$7,'Main Expenses'!$L$6:$L$10000,$C$7),0)
B66: ↳ Maryland State Tax | C66: =IFERROR(SUMIFS('Sub Expenses'!$E$6:$E$10000,'Sub Expenses'!$B$6:$B$10000,"Shopify",'Sub Expenses'!$C$6:$C$10000,"Tax",'Sub Expenses'!$D$6:$D$10000,"Maryland State Tax",'Sub Expenses'!$J$6:$J$10000,$B$7,'Sub Expenses'!$K$6:$K$10000,$C$7),0) | D66: =IFERROR(C66/SUMIFS('Main Expenses'!$E$6:$E$10000,'Main Expenses'!$B$6:$B$10000,"Shopify",'Main Expenses'!$K$6:$K$10000,$B$7,'Main Expenses'!$L$6:$L$10000,$C$7),0)
B67: ↳ Metropolitan Commuter Transportation District | C67: =IFERROR(SUMIFS('Sub Expenses'!$E$6:$E$10000,'Sub Expenses'!$B$6:$B$10000,"Shopify",'Sub Expenses'!$C$6:$C$10000,"Tax",'Sub Expenses'!$D$6:$D$10000,"Metropolitan Commuter Transportation District",'Sub Expenses'!$J$6:$J$10000,$B$7,'Sub Expenses'!$K$6:$K$10000,$C$7),0) | D67: =IFERROR(C67/SUMIFS('Main Expenses'!$E$6:$E$10000,'Main Expenses'!$B$6:$B$10000,"Shopify",'Main Expenses'!$K$6:$K$10000,$B$7,'Main Expenses'!$L$6:$L$10000,$C$7),0)
B68: ↳ Miami Dade County Tax | C68: =IFERROR(SUMIFS('Sub Expenses'!$E$6:$E$10000,'Sub Expenses'!$B$6:$B$10000,"Shopify",'Sub Expenses'!$C$6:$C$10000,"Tax",'Sub Expenses'!$D$6:$D$10000,"Miami Dade County Tax",'Sub Expenses'!$J$6:$J$10000,$B$7,'Sub Expenses'!$K$6:$K$10000,$C$7),0) | D68: =IFERROR(C68/SUMIFS('Main Expenses'!$E$6:$E$10000,'Main Expenses'!$B$6:$B$10000,"Shopify",'Main Expenses'!$K$6:$K$10000,$B$7,'Main Expenses'!$L$6:$L$10000,$C$7),0)
B69: ↳ New Jersey State Tax | C69: =IFERROR(SUMIFS('Sub Expenses'!$E$6:$E$10000,'Sub Expenses'!$B$6:$B$10000,"Shopify",'Sub Expenses'!$C$6:$C$10000,"Tax",'Sub Expenses'!$D$6:$D$10000,"New Jersey State Tax",'Sub Expenses'!$J$6:$J$10000,$B$7,'Sub Expenses'!$K$6:$K$10000,$C$7),0) | D69: =IFERROR(C69/SUMIFS('Main Expenses'!$E$6:$E$10000,'Main Expenses'!$B$6:$B$10000,"Shopify",'Main Expenses'!$K$6:$K$10000,$B$7,'Main Expenses'!$L$6:$L$10000,$C$7),0)
B70: ↳ New York City Tax | C70: =IFERROR(SUMIFS('Sub Expenses'!$E$6:$E$10000,'Sub Expenses'!$B$6:$B$10000,"Shopify",'Sub Expenses'!$C$6:$C$10000,"Tax",'Sub Expenses'!$D$6:$D$10000,"New York City Tax ",'Sub Expenses'!$J$6:$J$10000,$B$7,'Sub Expenses'!$K$6:$K$10000,$C$7),0) | D70: =IFERROR(C70/SUMIFS('Main Expenses'!$E$6:$E$10000,'Main Expenses'!$B$6:$B$10000,"Shopify",'Main Expenses'!$K$6:$K$10000,$B$7,'Main Expenses'!$L$6:$L$10000,$C$7),0)
B71: ↳ Ohio State Tax | C71: =IFERROR(SUMIFS('Sub Expenses'!$E$6:$E$10000,'Sub Expenses'!$B$6:$B$10000,"Shopify",'Sub Expenses'!$C$6:$C$10000,"Tax",'Sub Expenses'!$D$6:$D$10000,"Ohio State Tax",'Sub Expenses'!$J$6:$J$10000,$B$7,'Sub Expenses'!$K$6:$K$10000,$C$7),0) | D71: =IFERROR(C71/SUMIFS('Main Expenses'!$E$6:$E$10000,'Main Expenses'!$B$6:$B$10000,"Shopify",'Main Expenses'!$K$6:$K$10000,$B$7,'Main Expenses'!$L$6:$L$10000,$C$7),0)
B72: ↳ Refunded Galveston City Tax | C72: =IFERROR(SUMIFS('Sub Expenses'!$E$6:$E$10000,'Sub Expenses'!$B$6:$B$10000,"Shopify",'Sub Expenses'!$C$6:$C$10000,"Tax",'Sub Expenses'!$D$6:$D$10000,"Refunded Galveston City Tax",'Sub Expenses'!$J$6:$J$10000,$B$7,'Sub Expenses'!$K$6:$K$10000,$C$7),0) | D72: =IFERROR(C72/SUMIFS('Main Expenses'!$E$6:$E$10000,'Main Expenses'!$B$6:$B$10000,"Shopify",'Main Expenses'!$K$6:$K$10000,$B$7,'Main Expenses'!$L$6:$L$10000,$C$7),0)
B73: ↳ Refunded Texas State Tax | C73: =IFERROR(SUMIFS('Sub Expenses'!$E$6:$E$10000,'Sub Expenses'!$B$6:$B$10000,"Shopify",'Sub Expenses'!$C$6:$C$10000,"Tax",'Sub Expenses'!$D$6:$D$10000,"Refunded Texas State Tax",'Sub Expenses'!$J$6:$J$10000,$B$7,'Sub Expenses'!$K$6:$K$10000,$C$7),0) | D73: =IFERROR(C73/SUMIFS('Main Expenses'!$E$6:$E$10000,'Main Expenses'!$B$6:$B$10000,"Shopify",'Main Expenses'!$K$6:$K$10000,$B$7,'Main Expenses'!$L$6:$L$10000,$C$7),0)
B74: ↳ South Carolina State Tax | C74: =IFERROR(SUMIFS('Sub Expenses'!$E$6:$E$10000,'Sub Expenses'!$B$6:$B$10000,"Shopify",'Sub Expenses'!$C$6:$C$10000,"Tax",'Sub Expenses'!$D$6:$D$10000,"South Carolina State Tax",'Sub Expenses'!$J$6:$J$10000,$B$7,'Sub Expenses'!$K$6:$K$10000,$C$7),0) | D74: =IFERROR(C74/SUMIFS('Main Expenses'!$E$6:$E$10000,'Main Expenses'!$B$6:$B$10000,"Shopify",'Main Expenses'!$K$6:$K$10000,$B$7,'Main Expenses'!$L$6:$L$10000,$C$7),0)
B75: ↳ Texas State Tax | C75: =IFERROR(SUMIFS('Sub Expenses'!$E$6:$E$10000,'Sub Expenses'!$B$6:$B$10000,"Shopify",'Sub Expenses'!$C$6:$C$10000,"Tax",'Sub Expenses'!$D$6:$D$10000,"Texas State Tax",'Sub Expenses'!$J$6:$J$10000,$B$7,'Sub Expenses'!$K$6:$K$10000,$C$7),0) | D75: =IFERROR(C75/SUMIFS('Main Expenses'!$E$6:$E$10000,'Main Expenses'!$B$6:$B$10000,"Shopify",'Main Expenses'!$K$6:$K$10000,$B$7,'Main Expenses'!$L$6:$L$10000,$C$7),0)
B76: ↳ Virginia State Tax | C76: =IFERROR(SUMIFS('Sub Expenses'!$E$6:$E$10000,'Sub Expenses'!$B$6:$B$10000,"Shopify",'Sub Expenses'!$C$6:$C$10000,"Tax",'Sub Expenses'!$D$6:$D$10000,"Virginia State Tax",'Sub Expenses'!$J$6:$J$10000,$B$7,'Sub Expenses'!$K$6:$K$10000,$C$7),0) | D76: =IFERROR(C76/SUMIFS('Main Expenses'!$E$6:$E$10000,'Main Expenses'!$B$6:$B$10000,"Shopify",'Main Expenses'!$K$6:$K$10000,$B$7,'Main Expenses'!$L$6:$L$10000,$C$7),0)
B77: ↳ Volusia County Tax | C77: =IFERROR(SUMIFS('Sub Expenses'!$E$6:$E$10000,'Sub Expenses'!$B$6:$B$10000,"Shopify",'Sub Expenses'!$C$6:$C$10000,"Tax",'Sub Expenses'!$D$6:$D$10000,"Volusia County Tax",'Sub Expenses'!$J$6:$J$10000,$B$7,'Sub Expenses'!$K$6:$K$10000,$C$7),0) | D77: =IFERROR(C77/SUMIFS('Main Expenses'!$E$6:$E$10000,'Main Expenses'!$B$6:$B$10000,"Shopify",'Main Expenses'!$K$6:$K$10000,$B$7,'Main Expenses'!$L$6:$L$10000,$C$7),0)
B78: ↳ Washington State Tax | C78: =IFERROR(SUMIFS('Sub Expenses'!$E$6:$E$10000,'Sub Expenses'!$B$6:$B$10000,"Shopify",'Sub Expenses'!$C$6:$C$10000,"Tax",'Sub Expenses'!$D$6:$D$10000,"Washington State Tax",'Sub Expenses'!$J$6:$J$10000,$B$7,'Sub Expenses'!$K$6:$K$10000,$C$7),0) | D78: =IFERROR(C78/SUMIFS('Main Expenses'!$E$6:$E$10000,'Main Expenses'!$B$6:$B$10000,"Shopify",'Main Expenses'!$K$6:$K$10000,$B$7,'Main Expenses'!$L$6:$L$10000,$C$7),0)
B79: ↳ Wisconsin State Tax | C79: =IFERROR(SUMIFS('Sub Expenses'!$E$6:$E$10000,'Sub Expenses'!$B$6:$B$10000,"Shopify",'Sub Expenses'!$C$6:$C$10000,"Tax",'Sub Expenses'!$D$6:$D$10000,"Wisconsin State Tax",'Sub Expenses'!$J$6:$J$10000,$B$7,'Sub Expenses'!$K$6:$K$10000,$C$7),0) | D79: =IFERROR(C79/SUMIFS('Main Expenses'!$E$6:$E$10000,'Main Expenses'!$B$6:$B$10000,"Shopify",'Main Expenses'!$K$6:$K$10000,$B$7,'Main Expenses'!$L$6:$L$10000,$C$7),0)
B80: Shipping Cost | C80: =IFERROR(SUMIFS('Main Expenses'!$E$6:$E$10000,'Main Expenses'!$B$6:$B$10000,"Shopify",'Main Expenses'!$D$6:$D$10000,"Shipping Cost",'Main Expenses'!$K$6:$K$10000,$B$7,'Main Expenses'!$L$6:$L$10000,$C$7),0) | D80: =IFERROR(C80/SUMIFS('Main Expenses'!$E$6:$E$10000,'Main Expenses'!$B$6:$B$10000,"Shopify",'Main Expenses'!$K$6:$K$10000,$B$7,'Main Expenses'!$L$6:$L$10000,$C$7),0)
B81: ↳ Shipping Cost | C81: =IFERROR(SUMIFS('Sub Expenses'!$E$6:$E$10000,'Sub Expenses'!$B$6:$B$10000,"Shopify",'Sub Expenses'!$C$6:$C$10000,"Shipping Cost",'Sub Expenses'!$D$6:$D$10000,"Shipping Cost",'Sub Expenses'!$J$6:$J$10000,$B$7,'Sub Expenses'!$K$6:$K$10000,$C$7),0) | D81: =IFERROR(C81/SUMIFS('Main Expenses'!$E$6:$E$10000,'Main Expenses'!$B$6:$B$10000,"Shopify",'Main Expenses'!$K$6:$K$10000,$B$7,'Main Expenses'!$L$6:$L$10000,$C$7),0)
B82: MCF Shipping fees | C82: =IFERROR(SUMIFS('Main Expenses'!$E$6:$E$10000,'Main Expenses'!$B$6:$B$10000,"Shopify",'Main Expenses'!$D$6:$D$10000,"MCF Shipping fees",'Main Expenses'!$K$6:$K$10000,$B$7,'Main Expenses'!$L$6:$L$10000,$C$7),0) | D82: =IFERROR(C82/SUMIFS('Main Expenses'!$E$6:$E$10000,'Main Expenses'!$B$6:$B$10000,"Shopify",'Main Expenses'!$K$6:$K$10000,$B$7,'Main Expenses'!$L$6:$L$10000,$C$7),0)
B83: ↳ MCF Shipping fees | C83: =IFERROR(SUMIFS('Sub Expenses'!$E$6:$E$10000,'Sub Expenses'!$B$6:$B$10000,"Shopify",'Sub Expenses'!$C$6:$C$10000,"MCF Shipping fees",'Sub Expenses'!$D$6:$D$10000,"MCF Shipping fees",'Sub Expenses'!$J$6:$J$10000,$B$7,'Sub Expenses'!$K$6:$K$10000,$C$7),0) | D83: =IFERROR(C83/SUMIFS('Main Expenses'!$E$6:$E$10000,'Main Expenses'!$B$6:$B$10000,"Shopify",'Main Expenses'!$K$6:$K$10000,$B$7,'Main Expenses'!$L$6:$L$10000,$C$7),0)
B84: ↳ Shiphype Label Cost | C84: =IFERROR(SUMIFS('Sub Expenses'!$E$6:$E$10000,'Sub Expenses'!$B$6:$B$10000,"Shopify",'Sub Expenses'!$C$6:$C$10000,"MCF Shipping fees",'Sub Expenses'!$D$6:$D$10000,"Shiphype Label Cost",'Sub Expenses'!$J$6:$J$10000,$B$7,'Sub Expenses'!$K$6:$K$10000,$C$7),0) | D84: =IFERROR(C84/SUMIFS('Main Expenses'!$E$6:$E$10000,'Main Expenses'!$B$6:$B$10000,"Shopify",'Main Expenses'!$K$6:$K$10000,$B$7,'Main Expenses'!$L$6:$L$10000,$C$7),0)
B85: TOTAL EXPENSES | C85: =SUMIFS('Main Expenses'!$E$6:$E$10000,'Main Expenses'!$B$6:$B$10000,"Shopify",'Main Expenses'!$K$6:$K$10000,$B$7,'Main Expenses'!$L$6:$L$10000,$C$7) | D85: 1 | J85: TOTAL SALES | K85: =SUMIFS('Sales Data'!$E$6:$E$10000,'Sales Data'!$B$6:$B$10000,"Shopify",'Sales Data'!$BC$6:$BC$10000,$B$7,'Sales Data'!$BD$6:$BD$10000,$C$7) | L85: 1

Sheet Walmart Dashboard
B2: WALMART DASHBOARD
B3: Click the + symbol on the left margin to expand sub-categories · all KPIs update live via SUMIFS formulas.
B6: MONTH | C6: YEAR | D6: CATEGORY
B7: Mar | C7: 2026 | D7: All Categories
B9: KEY METRICS
B11: SALES | D11: =SUMIFS('Sales Data'!$E$6:$E$10000,'Sales Data'!$B$6:$B$10000,"Walmart",'Sales Data'!$BC$6:$BC$10000,$B$7,'Sales Data'!$BD$6:$BD$10000,$C$7)
B12: UNIT SALES | D12: =SUMIFS('Sales Data'!$G$6:$G$10000,'Sales Data'!$B$6:$B$10000,"Walmart",'Sales Data'!$BC$6:$BC$10000,$B$7,'Sales Data'!$BD$6:$BD$10000,$C$7)
B13: ADVERTISING COST | D13: =SUMIFS('Sales Data'!$AQ$6:$AQ$10000,'Sales Data'!$B$6:$B$10000,"Walmart",'Sales Data'!$BC$6:$BC$10000,$B$7,'Sales Data'!$BD$6:$BD$10000,$C$7)
B14: WFS SHIPPING COST | D14: =SUMIFS('Sales Data'!$AR$6:$AR$10000,'Sales Data'!$B$6:$B$10000,"Walmart",'Sales Data'!$BC$6:$BC$10000,$B$7,'Sales Data'!$BD$6:$BD$10000,$C$7)
B15: MCF SHIPPING FEES | D15: =SUMIFS('Sales Data'!$AS$6:$AS$10000,'Sales Data'!$B$6:$B$10000,"Walmart",'Sales Data'!$BC$6:$BC$10000,$B$7,'Sales Data'!$BD$6:$BD$10000,$C$7)
B16: 3PL LABEL COST | D16: =SUMIFS('Sales Data'!$AT$6:$AT$10000,'Sales Data'!$B$6:$B$10000,"Walmart",'Sales Data'!$BC$6:$BC$10000,$B$7,'Sales Data'!$BD$6:$BD$10000,$C$7)
B17: FEES (Commission on product) | D17: =SUMIFS('Sales Data'!$AU$6:$AU$10000,'Sales Data'!$B$6:$B$10000,"Walmart",'Sales Data'!$BC$6:$BC$10000,$B$7,'Sales Data'!$BD$6:$BD$10000,$C$7)
B18: FEES (Storage fee) | D18: =SUMIFS('Sales Data'!$AV$6:$AV$10000,'Sales Data'!$B$6:$B$10000,"Walmart",'Sales Data'!$BC$6:$BC$10000,$B$7,'Sales Data'!$BD$6:$BD$10000,$C$7)
B19: OTHER FEES | D19: =SUMIFS('Sales Data'!$AW$6:$AW$10000,'Sales Data'!$B$6:$B$10000,"Walmart",'Sales Data'!$BC$6:$BC$10000,$B$7,'Sales Data'!$BD$6:$BD$10000,$C$7)
B20: COGS | D20: =SUMIFS('Sales Data'!$AX$6:$AX$10000,'Sales Data'!$B$6:$B$10000,"Walmart",'Sales Data'!$BC$6:$BC$10000,$B$7,'Sales Data'!$BD$6:$BD$10000,$C$7)
B21: NET PROFIT (USD) | D21: =SUMIFS('Sales Data'!$AY$6:$AY$10000,'Sales Data'!$B$6:$B$10000,"Walmart",'Sales Data'!$BC$6:$BC$10000,$B$7,'Sales Data'!$BD$6:$BD$10000,$C$7)
B22: TACOS | D22: =SUMIFS('Sales Data'!$M$6:$M$10000,'Sales Data'!$B$6:$B$10000,"Walmart",'Sales Data'!$BC$6:$BC$10000,$B$7,'Sales Data'!$BD$6:$BD$10000,$C$7)
B23: % REFUNDS | D23: =SUMIFS('Sales Data'!$N$6:$N$10000,'Sales Data'!$B$6:$B$10000,"Walmart",'Sales Data'!$BC$6:$BC$10000,$B$7,'Sales Data'!$BD$6:$BD$10000,$C$7)
B24: MARGIN | D24: =SUMIFS('Sales Data'!$P$6:$P$10000,'Sales Data'!$B$6:$B$10000,"Walmart",'Sales Data'!$BC$6:$BC$10000,$B$7,'Sales Data'!$BD$6:$BD$10000,$C$7)
B27: MONTHLY TREND | I27: Trend Year: | J27: 2026
B29: METRIC | C29: Jan | D29: Feb | E29: Mar | F29: Apr | G29: May | H29: Jun | I29: Jul | J29: Aug | K29: Sep | L29: Oct | M29: Nov | N29: Dec | O29: YEAR TOTAL
B30: Sales (USD) | C30: =SUMIFS('Sales Data'!$E$6:$E$10000,'Sales Data'!$B$6:$B$10000,"Walmart",'Sales Data'!$BC$6:$BC$10000,"Jan",'Sales Data'!$BD$6:$BD$10000,$J$27) | D30: =SUMIFS('Sales Data'!$E$6:$E$10000,'Sales Data'!$B$6:$B$10000,"Walmart",'Sales Data'!$BC$6:$BC$10000,"Feb",'Sales Data'!$BD$6:$BD$10000,$J$27) | E30: =SUMIFS('Sales Data'!$E$6:$E$10000,'Sales Data'!$B$6:$B$10000,"Walmart",'Sales Data'!$BC$6:$BC$10000,"Mar",'Sales Data'!$BD$6:$BD$10000,$J$27) | F30: =SUMIFS('Sales Data'!$E$6:$E$10000,'Sales Data'!$B$6:$B$10000,"Walmart",'Sales Data'!$BC$6:$BC$10000,"Apr",'Sales Data'!$BD$6:$BD$10000,$J$27) | G30: =SUMIFS('Sales Data'!$E$6:$E$10000,'Sales Data'!$B$6:$B$10000,"Walmart",'Sales Data'!$BC$6:$BC$10000,"May",'Sales Data'!$BD$6:$BD$10000,$J$27) | H30: =SUMIFS('Sales Data'!$E$6:$E$10000,'Sales Data'!$B$6:$B$10000,"Walmart",'Sales Data'!$BC$6:$BC$10000,"Jun",'Sales Data'!$BD$6:$BD$10000,$J$27) | I30: =SUMIFS('Sales Data'!$E$6:$E$10000,'Sales Data'!$B$6:$B$10000,"Walmart",'Sales Data'!$BC$6:$BC$10000,"Jul",'Sales Data'!$BD$6:$BD$10000,$J$27) | J30: =SUMIFS('Sales Data'!$E$6:$E$10000,'Sales Data'!$B$6:$B$10000,"Walmart",'Sales Data'!$BC$6:$BC$10000,"Aug",'Sales Data'!$BD$6:$BD$10000,$J$27) | K30: =SUMIFS('Sales Data'!$E$6:$E$10000,'Sales Data'!$B$6:$B$10000,"Walmart",'Sales Data'!$BC$6:$BC$10000,"Sep",'Sales Data'!$BD$6:$BD$10000,$J$27) | L30: =SUMIFS('Sales Data'!$E$6:$E$10000,'Sales Data'!$B$6:$B$10000,"Walmart",'Sales Data'!$BC$6:$BC$10000,"Oct",'Sales Data'!$BD$6:$BD$10000,$J$27) | M30: =SUMIFS('Sales Data'!$E$6:$E$10000,'Sales Data'!$B$6:$B$10000,"Walmart",'Sales Data'!$BC$6:$BC$10000,"Nov",'Sales Data'!$BD$6:$BD$10000,$J$27) | N30: =SUMIFS('Sales Data'!$E$6:$E$10000,'Sales Data'!$B$6:$B$10000,"Walmart",'Sales Data'!$BC$6:$BC$10000,"Dec",'Sales Data'!$BD$6:$BD$10000,$J$27) | O30: =SUM(C30:N30)
B31: Units | C31: =SUMIFS('Sales Data'!$G$6:$G$10000,'Sales Data'!$B$6:$B$10000,"Walmart",'Sales Data'!$BC$6:$BC$10000,"Jan",'Sales Data'!$BD$6:$BD$10000,$J$27) | D31: =SUMIFS('Sales Data'!$G$6:$G$10000,'Sales Data'!$B$6:$B$10000,"Walmart",'Sales Data'!$BC$6:$BC$10000,"Feb",'Sales Data'!$BD$6:$BD$10000,$J$27) | E31: =SUMIFS('Sales Data'!$G$6:$G$10000,'Sales Data'!$B$6:$B$10000,"Walmart",'Sales Data'!$BC$6:$BC$10000,"Mar",'Sales Data'!$BD$6:$BD$10000,$J$27) | F31: =SUMIFS('Sales Data'!$G$6:$G$10000,'Sales Data'!$B$6:$B$10000,"Walmart",'Sales Data'!$BC$6:$BC$10000,"Apr",'Sales Data'!$BD$6:$BD$10000,$J$27) | G31: =SUMIFS('Sales Data'!$G$6:$G$10000,'Sales Data'!$B$6:$B$10000,"Walmart",'Sales Data'!$BC$6:$BC$10000,"May",'Sales Data'!$BD$6:$BD$10000,$J$27) | H31: =SUMIFS('Sales Data'!$G$6:$G$10000,'Sales Data'!$B$6:$B$10000,"Walmart",'Sales Data'!$BC$6:$BC$10000,"Jun",'Sales Data'!$BD$6:$BD$10000,$J$27) | I31: =SUMIFS('Sales Data'!$G$6:$G$10000,'Sales Data'!$B$6:$B$10000,"Walmart",'Sales Data'!$BC$6:$BC$10000,"Jul",'Sales Data'!$BD$6:$BD$10000,$J$27) | J31: =SUMIFS('Sales Data'!$G$6:$G$10000,'Sales Data'!$B$6:$B$10000,"Walmart",'Sales Data'!$BC$6:$BC$10000,"Aug",'Sales Data'!$BD$6:$BD$10000,$J$27) | K31: =SUMIFS('Sales Data'!$G$6:$G$10000,'Sales Data'!$B$6:$B$10000,"Walmart",'Sales Data'!$BC$6:$BC$10000,"Sep",'Sales Data'!$BD$6:$BD$10000,$J$27) | L31: =SUMIFS('Sales Data'!$G$6:$G$10000,'Sales Data'!$B$6:$B$10000,"Walmart",'Sales Data'!$BC$6:$BC$10000,"Oct",'Sales Data'!$BD$6:$BD$10000,$J$27) | M31: =SUMIFS('Sales Data'!$G$6:$G$10000,'Sales Data'!$B$6:$B$10000,"Walmart",'Sales Data'!$BC$6:$BC$10000,"Nov",'Sales Data'!$BD$6:$BD$10000,$J$27) | N31: =SUMIFS('Sales Data'!$G$6:$G$10000,'Sales Data'!$B$6:$B$10000,"Walmart",'Sales Data'!$BC$6:$BC$10000,"Dec",'Sales Data'!$BD$6:$BD$10000,$J$27) | O31: =SUM(C31:N31)
B32: Ad Cost | C32: =SUMIFS('Sales Data'!$AQ$6:$AQ$10000,'Sales Data'!$B$6:$B$10000,"Walmart",'Sales Data'!$BC$6:$BC$10000,"Jan",'Sales Data'!$BD$6:$BD$10000,$J$27) | D32: =SUMIFS('Sales Data'!$AQ$6:$AQ$10000,'Sales Data'!$B$6:$B$10000,"Walmart",'Sales Data'!$BC$6:$BC$10000,"Feb",'Sales Data'!$BD$6:$BD$10000,$J$27) | E32: =SUMIFS('Sales Data'!$AQ$6:$AQ$10000,'Sales Data'!$B$6:$B$10000,"Walmart",'Sales Data'!$BC$6:$BC$10000,"Mar",'Sales Data'!$BD$6:$BD$10000,$J$27) | F32: =SUMIFS('Sales Data'!$AQ$6:$AQ$10000,'Sales Data'!$B$6:$B$10000,"Walmart",'Sales Data'!$BC$6:$BC$10000,"Apr",'Sales Data'!$BD$6:$BD$10000,$J$27) | G32: =SUMIFS('Sales Data'!$AQ$6:$AQ$10000,'Sales Data'!$B$6:$B$10000,"Walmart",'Sales Data'!$BC$6:$BC$10000,"May",'Sales Data'!$BD$6:$BD$10000,$J$27) | H32: =SUMIFS('Sales Data'!$AQ$6:$AQ$10000,'Sales Data'!$B$6:$B$10000,"Walmart",'Sales Data'!$BC$6:$BC$10000,"Jun",'Sales Data'!$BD$6:$BD$10000,$J$27) | I32: =SUMIFS('Sales Data'!$AQ$6:$AQ$10000,'Sales Data'!$B$6:$B$10000,"Walmart",'Sales Data'!$BC$6:$BC$10000,"Jul",'Sales Data'!$BD$6:$BD$10000,$J$27) | J32: =SUMIFS('Sales Data'!$AQ$6:$AQ$10000,'Sales Data'!$B$6:$B$10000,"Walmart",'Sales Data'!$BC$6:$BC$10000,"Aug",'Sales Data'!$BD$6:$BD$10000,$J$27) | K32: =SUMIFS('Sales Data'!$AQ$6:$AQ$10000,'Sales Data'!$B$6:$B$10000,"Walmart",'Sales Data'!$BC$6:$BC$10000,"Sep",'Sales Data'!$BD$6:$BD$10000,$J$27) | L32: =SUMIFS('Sales Data'!$AQ$6:$AQ$10000,'Sales Data'!$B$6:$B$10000,"Walmart",'Sales Data'!$BC$6:$BC$10000,"Oct",'Sales Data'!$BD$6:$BD$10000,$J$27) | M32: =SUMIFS('Sales Data'!$AQ$6:$AQ$10000,'Sales Data'!$B$6:$B$10000,"Walmart",'Sales Data'!$BC$6:$BC$10000,"Nov",'Sales Data'!$BD$6:$BD$10000,$J$27) | N32: =SUMIFS('Sales Data'!$AQ$6:$AQ$10000,'Sales Data'!$B$6:$B$10000,"Walmart",'Sales Data'!$BC$6:$BC$10000,"Dec",'Sales Data'!$BD$6:$BD$10000,$J$27) | O32: =SUM(C32:N32)
B33: COGS | C33: =SUMIFS('Sales Data'!$AX$6:$AX$10000,'Sales Data'!$B$6:$B$10000,"Walmart",'Sales Data'!$BC$6:$BC$10000,"Jan",'Sales Data'!$BD$6:$BD$10000,$J$27) | D33: =SUMIFS('Sales Data'!$AX$6:$AX$10000,'Sales Data'!$B$6:$B$10000,"Walmart",'Sales Data'!$BC$6:$BC$10000,"Feb",'Sales Data'!$BD$6:$BD$10000,$J$27) | E33: =SUMIFS('Sales Data'!$AX$6:$AX$10000,'Sales Data'!$B$6:$B$10000,"Walmart",'Sales Data'!$BC$6:$BC$10000,"Mar",'Sales Data'!$BD$6:$BD$10000,$J$27) | F33: =SUMIFS('Sales Data'!$AX$6:$AX$10000,'Sales Data'!$B$6:$B$10000,"Walmart",'Sales Data'!$BC$6:$BC$10000,"Apr",'Sales Data'!$BD$6:$BD$10000,$J$27) | G33: =SUMIFS('Sales Data'!$AX$6:$AX$10000,'Sales Data'!$B$6:$B$10000,"Walmart",'Sales Data'!$BC$6:$BC$10000,"May",'Sales Data'!$BD$6:$BD$10000,$J$27) | H33: =SUMIFS('Sales Data'!$AX$6:$AX$10000,'Sales Data'!$B$6:$B$10000,"Walmart",'Sales Data'!$BC$6:$BC$10000,"Jun",'Sales Data'!$BD$6:$BD$10000,$J$27) | I33: =SUMIFS('Sales Data'!$AX$6:$AX$10000,'Sales Data'!$B$6:$B$10000,"Walmart",'Sales Data'!$BC$6:$BC$10000,"Jul",'Sales Data'!$BD$6:$BD$10000,$J$27) | J33: =SUMIFS('Sales Data'!$AX$6:$AX$10000,'Sales Data'!$B$6:$B$10000,"Walmart",'Sales Data'!$BC$6:$BC$10000,"Aug",'Sales Data'!$BD$6:$BD$10000,$J$27) | K33: =SUMIFS('Sales Data'!$AX$6:$AX$10000,'Sales Data'!$B$6:$B$10000,"Walmart",'Sales Data'!$BC$6:$BC$10000,"Sep",'Sales Data'!$BD$6:$BD$10000,$J$27) | L33: =SUMIFS('Sales Data'!$AX$6:$AX$10000,'Sales Data'!$B$6:$B$10000,"Walmart",'Sales Data'!$BC$6:$BC$10000,"Oct",'Sales Data'!$BD$6:$BD$10000,$J$27) | M33: =SUMIFS('Sales Data'!$AX$6:$AX$10000,'Sales Data'!$B$6:$B$10000,"Walmart",'Sales Data'!$BC$6:$BC$10000,"Nov",'Sales Data'!$BD$6:$BD$10000,$J$27) | N33: =SUMIFS('Sales Data'!$AX$6:$AX$10000,'Sales Data'!$B$6:$B$10000,"Walmart",'Sales Data'!$BC$6:$BC$10000,"Dec",'Sales Data'!$BD$6:$BD$10000,$J$27) | O33: =SUM(C33:N33)
B34: Net Profit | C34: =SUMIFS('Sales Data'!$AY$6:$AY$10000,'Sales Data'!$B$6:$B$10000,"Walmart",'Sales Data'!$BC$6:$BC$10000,"Jan",'Sales Data'!$BD$6:$BD$10000,$J$27) | D34: =SUMIFS('Sales Data'!$AY$6:$AY$10000,'Sales Data'!$B$6:$B$10000,"Walmart",'Sales Data'!$BC$6:$BC$10000,"Feb",'Sales Data'!$BD$6:$BD$10000,$J$27) | E34: =SUMIFS('Sales Data'!$AY$6:$AY$10000,'Sales Data'!$B$6:$B$10000,"Walmart",'Sales Data'!$BC$6:$BC$10000,"Mar",'Sales Data'!$BD$6:$BD$10000,$J$27) | F34: =SUMIFS('Sales Data'!$AY$6:$AY$10000,'Sales Data'!$B$6:$B$10000,"Walmart",'Sales Data'!$BC$6:$BC$10000,"Apr",'Sales Data'!$BD$6:$BD$10000,$J$27) | G34: =SUMIFS('Sales Data'!$AY$6:$AY$10000,'Sales Data'!$B$6:$B$10000,"Walmart",'Sales Data'!$BC$6:$BC$10000,"May",'Sales Data'!$BD$6:$BD$10000,$J$27) | H34: =SUMIFS('Sales Data'!$AY$6:$AY$10000,'Sales Data'!$B$6:$B$10000,"Walmart",'Sales Data'!$BC$6:$BC$10000,"Jun",'Sales Data'!$BD$6:$BD$10000,$J$27) | I34: =SUMIFS('Sales Data'!$AY$6:$AY$10000,'Sales Data'!$B$6:$B$10000,"Walmart",'Sales Data'!$BC$6:$BC$10000,"Jul",'Sales Data'!$BD$6:$BD$10000,$J$27) | J34: =SUMIFS('Sales Data'!$AY$6:$AY$10000,'Sales Data'!$B$6:$B$10000,"Walmart",'Sales Data'!$BC$6:$BC$10000,"Aug",'Sales Data'!$BD$6:$BD$10000,$J$27) | K34: =SUMIFS('Sales Data'!$AY$6:$AY$10000,'Sales Data'!$B$6:$B$10000,"Walmart",'Sales Data'!$BC$6:$BC$10000,"Sep",'Sales Data'!$BD$6:$BD$10000,$J$27) | L34: =SUMIFS('Sales Data'!$AY$6:$AY$10000,'Sales Data'!$B$6:$B$10000,"Walmart",'Sales Data'!$BC$6:$BC$10000,"Oct",'Sales Data'!$BD$6:$BD$10000,$J$27) | M34: =SUMIFS('Sales Data'!$AY$6:$AY$10000,'Sales Data'!$B$6:$B$10000,"Walmart",'Sales Data'!$BC$6:$BC$10000,"Nov",'Sales Data'!$BD$6:$BD$10000,$J$27) | N34: =SUMIFS('Sales Data'!$AY$6:$AY$10000,'Sales Data'!$B$6:$B$10000,"Walmart",'Sales Data'!$BC$6:$BC$10000,"Dec",'Sales Data'!$BD$6:$BD$10000,$J$27) | O34: =SUM(C34:N34)
B35: TACOS | C35: =SUMIFS('Sales Data'!$M$6:$M$10000,'Sales Data'!$B$6:$B$10000,"Walmart",'Sales Data'!$BC$6:$BC$10000,"Jan",'Sales Data'!$BD$6:$BD$10000,$J$27) | D35: =SUMIFS('Sales Data'!$M$6:$M$10000,'Sales Data'!$B$6:$B$10000,"Walmart",'Sales Data'!$BC$6:$BC$10000,"Feb",'Sales Data'!$BD$6:$BD$10000,$J$27) | E35: =SUMIFS('Sales Data'!$M$6:$M$10000,'Sales Data'!$B$6:$B$10000,"Walmart",'Sales Data'!$BC$6:$BC$10000,"Mar",'Sales Data'!$BD$6:$BD$10000,$J$27) | F35: =SUMIFS('Sales Data'!$M$6:$M$10000,'Sales Data'!$B$6:$B$10000,"Walmart",'Sales Data'!$BC$6:$BC$10000,"Apr",'Sales Data'!$BD$6:$BD$10000,$J$27) | G35: =SUMIFS('Sales Data'!$M$6:$M$10000,'Sales Data'!$B$6:$B$10000,"Walmart",'Sales Data'!$BC$6:$BC$10000,"May",'Sales Data'!$BD$6:$BD$10000,$J$27) | H35: =SUMIFS('Sales Data'!$M$6:$M$10000,'Sales Data'!$B$6:$B$10000,"Walmart",'Sales Data'!$BC$6:$BC$10000,"Jun",'Sales Data'!$BD$6:$BD$10000,$J$27) | I35: =SUMIFS('Sales Data'!$M$6:$M$10000,'Sales Data'!$B$6:$B$10000,"Walmart",'Sales Data'!$BC$6:$BC$10000,"Jul",'Sales Data'!$BD$6:$BD$10000,$J$27) | J35: =SUMIFS('Sales Data'!$M$6:$M$10000,'Sales Data'!$B$6:$B$10000,"Walmart",'Sales Data'!$BC$6:$BC$10000,"Aug",'Sales Data'!$BD$6:$BD$10000,$J$27) | K35: =SUMIFS('Sales Data'!$M$6:$M$10000,'Sales Data'!$B$6:$B$10000,"Walmart",'Sales Data'!$BC$6:$BC$10000,"Sep",'Sales Data'!$BD$6:$BD$10000,$J$27) | L35: =SUMIFS('Sales Data'!$M$6:$M$10000,'Sales Data'!$B$6:$B$10000,"Walmart",'Sales Data'!$BC$6:$BC$10000,"Oct",'Sales Data'!$BD$6:$BD$10000,$J$27) | M35: =SUMIFS('Sales Data'!$M$6:$M$10000,'Sales Data'!$B$6:$B$10000,"Walmart",'Sales Data'!$BC$6:$BC$10000,"Nov",'Sales Data'!$BD$6:$BD$10000,$J$27) | N35: =SUMIFS('Sales Data'!$M$6:$M$10000,'Sales Data'!$B$6:$B$10000,"Walmart",'Sales Data'!$BC$6:$BC$10000,"Dec",'Sales Data'!$BD$6:$BD$10000,$J$27) | O35: =IFERROR(AVERAGE(C35:N35),0)
B36: Margin | C36: =SUMIFS('Sales Data'!$P$6:$P$10000,'Sales Data'!$B$6:$B$10000,"Walmart",'Sales Data'!$BC$6:$BC$10000,"Jan",'Sales Data'!$BD$6:$BD$10000,$J$27) | D36: =SUMIFS('Sales Data'!$P$6:$P$10000,'Sales Data'!$B$6:$B$10000,"Walmart",'Sales Data'!$BC$6:$BC$10000,"Feb",'Sales Data'!$BD$6:$BD$10000,$J$27) | E36: =SUMIFS('Sales Data'!$P$6:$P$10000,'Sales Data'!$B$6:$B$10000,"Walmart",'Sales Data'!$BC$6:$BC$10000,"Mar",'Sales Data'!$BD$6:$BD$10000,$J$27) | F36: =SUMIFS('Sales Data'!$P$6:$P$10000,'Sales Data'!$B$6:$B$10000,"Walmart",'Sales Data'!$BC$6:$BC$10000,"Apr",'Sales Data'!$BD$6:$BD$10000,$J$27) | G36: =SUMIFS('Sales Data'!$P$6:$P$10000,'Sales Data'!$B$6:$B$10000,"Walmart",'Sales Data'!$BC$6:$BC$10000,"May",'Sales Data'!$BD$6:$BD$10000,$J$27) | H36: =SUMIFS('Sales Data'!$P$6:$P$10000,'Sales Data'!$B$6:$B$10000,"Walmart",'Sales Data'!$BC$6:$BC$10000,"Jun",'Sales Data'!$BD$6:$BD$10000,$J$27) | I36: =SUMIFS('Sales Data'!$P$6:$P$10000,'Sales Data'!$B$6:$B$10000,"Walmart",'Sales Data'!$BC$6:$BC$10000,"Jul",'Sales Data'!$BD$6:$BD$10000,$J$27) | J36: =SUMIFS('Sales Data'!$P$6:$P$10000,'Sales Data'!$B$6:$B$10000,"Walmart",'Sales Data'!$BC$6:$BC$10000,"Aug",'Sales Data'!$BD$6:$BD$10000,$J$27) | K36: =SUMIFS('Sales Data'!$P$6:$P$10000,'Sales Data'!$B$6:$B$10000,"Walmart",'Sales Data'!$BC$6:$BC$10000,"Sep",'Sales Data'!$BD$6:$BD$10000,$J$27) | L36: =SUMIFS('Sales Data'!$P$6:$P$10000,'Sales Data'!$B$6:$B$10000,"Walmart",'Sales Data'!$BC$6:$BC$10000,"Oct",'Sales Data'!$BD$6:$BD$10000,$J$27) | M36: =SUMIFS('Sales Data'!$P$6:$P$10000,'Sales Data'!$B$6:$B$10000,"Walmart",'Sales Data'!$BC$6:$BC$10000,"Nov",'Sales Data'!$BD$6:$BD$10000,$J$27) | N36: =SUMIFS('Sales Data'!$P$6:$P$10000,'Sales Data'!$B$6:$B$10000,"Walmart",'Sales Data'!$BC$6:$BC$10000,"Dec",'Sales Data'!$BD$6:$BD$10000,$J$27) | O36: =IFERROR(AVERAGE(C36:N36),0)
B39: EXPENSE BREAKDOWN · MAIN & SUB CATEGORY | J39: SALES BREAKDOWN · SUB-CATEGORY
B40: CATEGORY | C40: AMOUNT | D40: % OF EXPENSES | J40: SUB CATEGORY | K40: SALES AMOUNT | L40: % OF SALES
B41: Advertising cost | C41: =IFERROR(SUMIFS('Main Expenses'!$E$6:$E$10000,'Main Expenses'!$B$6:$B$10000,"Walmart",'Main Expenses'!$D$6:$D$10000,"Advertising cost",'Main Expenses'!$K$6:$K$10000,$B$7,'Main Expenses'!$L$6:$L$10000,$C$7),0) | D41: =IFERROR(C41/SUMIFS('Main Expenses'!$E$6:$E$10000,'Main Expenses'!$B$6:$B$10000,"Walmart",'Main Expenses'!$K$6:$K$10000,$B$7,'Main Expenses'!$L$6:$L$10000,$C$7),0) | J41: Sales | K41: =IFERROR(SUMIFS('Sales Data'!$E$6:$E$10000,'Sales Data'!$B$6:$B$10000,"Walmart",'Sales Data'!$D$6:$D$10000,"Sales",'Sales Data'!$BC$6:$BC$10000,$B$7,'Sales Data'!$BD$6:$BD$10000,$C$7),0) | L41: =IFERROR(K41/SUMIFS('Sales Data'!$E$6:$E$10000,'Sales Data'!$B$6:$B$10000,"Walmart",'Sales Data'!$BC$6:$BC$10000,$B$7,'Sales Data'!$BD$6:$BD$10000,$C$7),0)
B42: ↳ Advertising Cost | C42: =IFERROR(SUMIFS('Sub Expenses'!$E$6:$E$10000,'Sub Expenses'!$B$6:$B$10000,"Walmart",'Sub Expenses'!$C$6:$C$10000,"Advertising cost",'Sub Expenses'!$D$6:$D$10000,"Advertising Cost",'Sub Expenses'!$J$6:$J$10000,$B$7,'Sub Expenses'!$K$6:$K$10000,$C$7),0) | D42: =IFERROR(C42/SUMIFS('Main Expenses'!$E$6:$E$10000,'Main Expenses'!$B$6:$B$10000,"Walmart",'Main Expenses'!$K$6:$K$10000,$B$7,'Main Expenses'!$L$6:$L$10000,$C$7),0)
B43: Shipping Cost | C43: =IFERROR(SUMIFS('Main Expenses'!$E$6:$E$10000,'Main Expenses'!$B$6:$B$10000,"Walmart",'Main Expenses'!$D$6:$D$10000,"Shipping Cost",'Main Expenses'!$K$6:$K$10000,$B$7,'Main Expenses'!$L$6:$L$10000,$C$7),0) | D43: =IFERROR(C43/SUMIFS('Main Expenses'!$E$6:$E$10000,'Main Expenses'!$B$6:$B$10000,"Walmart",'Main Expenses'!$K$6:$K$10000,$B$7,'Main Expenses'!$L$6:$L$10000,$C$7),0)
B44: ↳ MCF Shipping fees | C44: =IFERROR(SUMIFS('Sub Expenses'!$E$6:$E$10000,'Sub Expenses'!$B$6:$B$10000,"Walmart",'Sub Expenses'!$C$6:$C$10000,"Shipping Cost",'Sub Expenses'!$D$6:$D$10000,"MCF Shipping fees",'Sub Expenses'!$J$6:$J$10000,$B$7,'Sub Expenses'!$K$6:$K$10000,$C$7),0) | D44: =IFERROR(C44/SUMIFS('Main Expenses'!$E$6:$E$10000,'Main Expenses'!$B$6:$B$10000,"Walmart",'Main Expenses'!$K$6:$K$10000,$B$7,'Main Expenses'!$L$6:$L$10000,$C$7),0)
B45: ↳ Shiphero Shipping Cost | C45: =IFERROR(SUMIFS('Sub Expenses'!$E$6:$E$10000,'Sub Expenses'!$B$6:$B$10000,"Walmart",'Sub Expenses'!$C$6:$C$10000,"Shipping Cost",'Sub Expenses'!$D$6:$D$10000,"Shiphero Shipping Cost",'Sub Expenses'!$J$6:$J$10000,$B$7,'Sub Expenses'!$K$6:$K$10000,$C$7),0) | D45: =IFERROR(C45/SUMIFS('Main Expenses'!$E$6:$E$10000,'Main Expenses'!$B$6:$B$10000,"Walmart",'Main Expenses'!$K$6:$K$10000,$B$7,'Main Expenses'!$L$6:$L$10000,$C$7),0)
